Workbook
Name AsAt: Settings!$B$4
Name HRA: Settings!$B$5
Name TemplateVersion: Settings!$B$6
Name PeriodFrom: Settings!$B$7
Name LM_live: 'Loan maths'!$B$4:$B$1000
Name LM_profile: 'Loan maths'!$C$4:$C$1000
Name LM_step: 'Loan maths'!$D$4:$D$1000
Name LM_first: 'Loan maths'!$E$4:$E$1000
Name LM_rate: 'Loan maths'!$F$4:$F$1000
Name LM_payments: 'Loan maths'!$G$4:$G$1000
Name LM_paid: 'Loan maths'!$H$4:$H$1000
Name LM_eip: 'Loan maths'!$J$4:$J$1000
Name LM_annuity: 'Loan maths'!$K$4:$K$1000
Name LM_out: 'Loan maths'!$L$4:$L$1000
Name LM_safe: 'Loan maths'!$M$4:$M$1000
Name LM_cycles: 'Loan maths'!$N$4:$N$1000
Name LM_stub: 'Loan maths'!$O$4:$O$1000
Name LM_life: 'Loan maths'!$P$4:$P$1000
Name LM_order: 'Loan maths'!$Q$4:$Q$1000
Name LM_anchor: 'Loan maths'!$R$4:$R$1000
Name LM_end: 'Loan maths'!$S$4:$S$1000
Name LM_runs: 'Loan maths'!$T$4:$T$1000
Name LN_principal: 'Deal maths'!$Y$4:$Y$1000
Name LN_maturity: 'Deal maths'!$AA$4:$AA$1000
Name LN_fund: 'Deal maths'!$AF$4:$AF$1000
Name LN_call: 'Deal maths'!$AG$4:$AG$1000
Name LN_start: 'Deal maths'!$Z$4:$Z$1000
Name TermTypes: Lists!$A$4:$A$10
Name CounterpartyTypes: Lists!$B$4:$B$11
Name HRAOptions: Lists!$C$4:$C$6
Name CallTypes: Lists!$D$4:$D$7
Name LoanTypes: Lists!$E$4:$E$9
Name LenderTypes: Lists!$F$4:$F$8
Name Profiles: Lists!$G$4:$G$6
Name Frequencies: Lists!$H$4:$H$6
Name Funds: Lists!$I$4:$I$5
Name FundTypes: Lists!$J$4:$J$9

Sheet Start here
B2: PWLBreports
B3: Deal list · the workbook the report tool reads
B4: from PWLBtoday
B7: Your deals, in one workbook you own.
B8: One row per deal, with the words from the drop-downs. Keep matured deals and repaid loans in: they are the period’s activity. Your projection goes on its own sheet, a row a year. Save it in Excel, point the report tool at it, and the tool fills the holdings, the projection and the draft from it. The Dashboard sheet reads the same rows for checking as you type, the Position sheet and the two lists beside it set out what is held, and the Benchmark sheet draws the liability benchmark from the projection.
B10: Where to go
B11: Sheet | C11: What goes there | D11: Rows so far
B12: Settings | C12: The As at date, the HRA pooling, the template version and the period the averages cover. | D12: ="4 cells" -> 4 cells
B13: Term investments | C13: Fixed-term deposits, CDs, Treasury bills, gilts and bonds, loans to other authorities. Keep matured deals in. Room for 1,997 rows. | D13: =COUNTA('Term investments'!A4:A2000)&" rows" -> 0 rows
B14: Call accounts and MMFs | C14: Instant-access and notice accounts and money market funds, with the average over the period. Room for 1,997 rows. | D14: =COUNTA('Call accounts and MMFs'!A4:A2000)&" rows" -> 0 rows
B15: Loans | C15: Every loan outstanding, with its profile; keep repaid loans in. Room for 997 rows. | D15: =COUNTA('Loans'!A4:A1000)&" rows" -> 0 rows
B16: Pooled funds | C16: Strategic pooled funds: carrying value, latest value and the income rate. Room for 1,997 rows. | D16: =COUNTA('Pooled funds'!A4:A2000)&" rows" -> 0 rows
B17: Projections | C17: Your projection, one row a year, a block per fund: the report tool's figures grid. The tool reads it and locks its grid while this workbook is in use; leave it blank to type there. | D17: =COUNT('Projections'!B7:B57)&" years typed" -> 0 years typed
B18: Dashboard | C18: What the rows add up to, with charts: for checking as you type. | D18: ="7 views" -> 7 views
B19: Position | C19: The treasury position: borrowing and investments at the start of the period and at As at, by type, with rates and average lives; pooled funds; the counterparties by size. | D19: ="4 tables" -> 4 tables
B20: Debt outstanding | C20: Every loan still out at As at, soonest maturity first: principal, rate, average life and a year's interest. | D20: =SUM(LM_live)&" loans" -> 0 loans
B21: Investments held | C21: Every investment held at As at: money on call first, then term deals by maturity, with amount, rate and days left. | D21: =COUNT('List maths'!$E$4:$E$3997)&" deals" -> 0 deals
B22: Benchmark | C22: The liability benchmark and the other indicators from the Projections sheet and the loans as they run off, with the Code's five charts: whole authority, General Fund, HRA. | D22: ="14 charts" -> 14 charts
B24: Ready to read?
B25: =IF(COUNTIF(B26:B60,"✘")=0,"Ready: the report tool and the deal list page will read this workbook as it is.","Not ready: "&COUNTIF(B26:B60,"✘")&" of the checks below failed. Put each right, or paste your rows into a fresh template.") -> Ready: the report tool and the deal list page will read this workbook as it is.
B26: =IF(ISNUMBER(AsAt),"✔","✘") -> ✔ | C26: Settings: As at is a date — Type the date in the yellow As at cell on Settings, as a date.
B27: =IF(COUNTIF(HRAOptions,HRA)=1,"✔","✘") -> ✔ | C27: Settings: HRA is None, One pool or Two pools — Pick it from the drop-down on Settings.
B28: =IF(AND(ISNUMBER(PeriodFrom),PeriodFrom<AsAt),"✔","✘") -> ✔ | C28: Settings: Period from is before As at — The period the averages cover ends at the As at date; 1 April is the usual start.
B29: =IF(TemplateVersion=3,"✔","✘") -> ✔ | C29: Settings: template version is 3 — The page reads version 3; the cell is locked, so this means the sheet was rebuilt by hand.
B30: =IF(NOT(ISERROR(ROWS(TermTypes)+ROWS(CounterpartyTypes)+ROWS(HRAOptions)+ROWS(CallTypes)+ROWS(LoanTypes)+ROWS(LenderTypes)+ROWS(Profiles)+ROWS(Frequencies)+ROWS(Funds)+ROWS(FundTypes))),"✔","✘") -> ✔ | C30: Lists: the drop-down words are all there — A list was deleted: download a fresh template and paste your rows into it.
B31: =IF(IFERROR(ROWS(TermInvestments[#All])>0,FALSE),"✔","✘") -> ✔ | C31: Term investments: the table TermInvestments is there — The table was converted to a range or renamed. Select the rows with their headers, Insert → Table, and name it TermInvestments on the Table Design tab.
B32: =IF(AND('Term investments'!$A$3="Type",'Term investments'!$B$3="Counterparty",'Term investments'!$C$3="Counterparty type",'Term investments'!$D$3="Principal",'Term investments'!$E$3="Start date",'Term investments'!$F$3="Maturity date",'Term investments'!$G$3="Rate",'Term investments'!$H$3="Face value",'Term investments'!$I$3="Carrying value",'Term investments'!$J$3="Rating",'Term investments'!$K$3="Notes"),"✔","✘") -> ✔ | C32: Term investments: the headers are as the page expects — A header was changed. Put the exact words back, or paste your rows into a fresh template.
B33: =IF(IFERROR(COUNTA('Term investments'!$A$4:$A$1048576)-SUMPRODUCT((TermInvestments[Type]<>"")*1)=0,FALSE),"✔","✘") -> ✔ | C33: Term investments: every row typed is inside the table — Rows typed beneath the table are read, but flagged: drag the table's corner handle down over them so they are in it.
B34: =IF(COUNTA('Term investments'!$A$2001:$K$1048576)=0,"✔","✘") -> ✔ | C34: Term investments: nothing is typed past row 2,000 — This workbook's own sums stop at row 2,000 (room for 1,997 rows); the page and the report tool read rows past it, so their figures would differ from this workbook's.
B35: =IF(SUMPRODUCT(('Term investments'!$A$4:$A$2000<>"")*(COUNTIF(TermTypes,TRIM('Term investments'!$A$4:$A$2000))=0))+SUMPRODUCT(('Term investments'!$C$4:$C$2000<>"")*(COUNTIF(CounterpartyTypes,TRIM('Term investments'!$C$4:$C$2000))=0))=0,"✔","✘") -> ✔ | C35: Term investments: every drop-down word is on its list — A word off the list is marked amber in the sheet: pick it from the drop-down. A pasted word is not checked at entry, only here.
B36: =IF(SUMPRODUCT(('Term investments'!$D$4:$D$2000<>"")*((1-ISNUMBER('Term investments'!$D$4:$D$2000))+ISNUMBER('Term investments'!$D$4:$D$2000)*('Term investments'!$D$4:$D$2000>0)*('Term investments'!$D$4:$D$2000<1000)))+SUMPRODUCT(('Term investments'!$H$4:$H$2000<>"")*((1-ISNUMBER('Term investments'!$H$4:$H$2000))+ISNUMBER('Term investments'!$H$4:$H$2000)*('Term investments'!$H$4:$H$2000>0)*('Term investments'!$H$4:$H$2000<1000)))+SUMPRODUCT(('Term investments'!$I$4:$I$2000<>"")*((1-ISNUMBER('Term investments'!$I$4:$I$2000))+ISNUMBER('Term investments'!$I$4:$I$2000)*('Term investments'!$I$4:$I$2000>0)*('Term investments'!$I$4:$I$2000<1000)))=0,"✔","✘") -> ✔ | C36: Term investments: amounts are numbers, in pounds — Amounts are in pounds, not £ millions (5,000,000 for £5m), and typed as numbers. A figure typed as text is marked red, one below £1,000 amber.
B37: =IF(SUMPRODUCT(('Term investments'!$E$4:$E$2000<>"")*(1-ISNUMBER('Term investments'!$E$4:$E$2000)))+SUMPRODUCT(('Term investments'!$F$4:$F$2000<>"")*(1-ISNUMBER('Term investments'!$F$4:$F$2000)))=0,"✔","✘") -> ✔ | C37: Term investments: dates are dates — A date typed as text is marked red: type it as a date (30/09/2026).
B38: =IF(IFERROR(ROWS(CallAccounts[#All])>0,FALSE),"✔","✘") -> ✔ | C38: Call accounts and MMFs: the table CallAccounts is there — The table was converted to a range or renamed. Select the rows with their headers, Insert → Table, and name it CallAccounts on the Table Design tab.
B39: =IF(AND('Call accounts and MMFs'!$A$3="Type",'Call accounts and MMFs'!$B$3="Counterparty",'Call accounts and MMFs'!$C$3="Counterparty type",'Call accounts and MMFs'!$D$3="Balance",'Call accounts and MMFs'!$E$3="Rate",'Call accounts and MMFs'!$F$3="Notice days",'Call accounts and MMFs'!$G$3="Rating",'Call accounts and MMFs'!$H$3="Average balance",'Call accounts and MMFs'!$I$3="Average rate",'Call accounts and MMFs'!$J$3="Notes"),"✔","✘") -> ✔ | C39: Call accounts and MMFs: the headers are as the page expects — A header was changed. Put the exact words back, or paste your rows into a fresh template.
B40: =IF(IFERROR(COUNTA('Call accounts and MMFs'!$A$4:$A$1048576)-SUMPRODUCT((CallAccounts[Type]<>"")*1)=0,FALSE),"✔","✘") -> ✔ | C40: Call accounts and MMFs: every row typed is inside the table — Rows typed beneath the table are read, but flagged: drag the table's corner handle down over them so they are in it.
B41: =IF(COUNTA('Call accounts and MMFs'!$A$2001:$J$1048576)=0,"✔","✘") -> ✔ | C41: Call accounts and MMFs: nothing is typed past row 2,000 — This workbook's own sums stop at row 2,000 (room for 1,997 rows); the page and the report tool read rows past it, so their figures would differ from this workbook's.
B42: =IF(SUMPRODUCT(('Call accounts and MMFs'!$A$4:$A$2000<>"")*(COUNTIF(CallTypes,TRIM('Call accounts and MMFs'!$A$4:$A$2000))=0))+SUMPRODUCT(('Call accounts and MMFs'!$C$4:$C$2000<>"")*(COUNTIF(CounterpartyTypes,TRIM('Call accounts and MMFs'!$C$4:$C$2000))=0))=0,"✔","✘") -> ✔ | C42: Call accounts and MMFs: every drop-down word is on its list — A word off the list is marked amber in the sheet: pick it from the drop-down. A pasted word is not checked at entry, only here.
B43: =IF(SUMPRODUCT(('Call accounts and MMFs'!$D$4:$D$2000<>"")*((1-ISNUMBER('Call accounts and MMFs'!$D$4:$D$2000))+ISNUMBER('Call accounts and MMFs'!$D$4:$D$2000)*('Call accounts and MMFs'!$D$4:$D$2000>0)*('Call accounts and MMFs'!$D$4:$D$2000<1000)))+SUMPRODUCT(('Call accounts and MMFs'!$H$4:$H$2000<>"")*((1-ISNUMBER('Call accounts and MMFs'!$H$4:$H$2000))+ISNUMBER('Call accounts and MMFs'!$H$4:$H$2000)*('Call accounts and MMFs'!$H$4:$H$2000>0)*('Call accounts and MMFs'!$H$4:$H$2000<1000)))=0,"✔","✘") -> ✔ | C43: Call accounts and MMFs: amounts are numbers, in pounds — Amounts are in pounds, not £ millions (5,000,000 for £5m), and typed as numbers. A figure typed as text is marked red, one below £1,000 amber.
B44: =IF(IFERROR(ROWS(Loans[#All])>0,FALSE),"✔","✘") -> ✔ | C44: Loans: the table Loans is there — The table was converted to a range or renamed. Select the rows with their headers, Insert → Table, and name it Loans on the Table Design tab.
B45: =IF(AND('Loans'!$A$3="Type",'Loans'!$B$3="Lender",'Loans'!$C$3="Lender type",'Loans'!$D$3="Principal",'Loans'!$E$3="Start date",'Loans'!$F$3="Maturity date",'Loans'!$G$3="Rate",'Loans'!$H$3="Profile",'Loans'!$I$3="Frequency",'Loans'!$J$3="First repayment date",'Loans'!$K$3="Fund",'Loans'!$L$3="Next call date",'Loans'!$M$3="Notes"),"✔","✘") -> ✔ | C45: Loans: the headers are as the page expects — A header was changed. Put the exact words back, or paste your rows into a fresh template.
B46: =IF(IFERROR(COUNTA('Loans'!$A$4:$A$1048576)-SUMPRODUCT((Loans[Type]<>"")*1)=0,FALSE),"✔","✘") -> ✔ | C46: Loans: every row typed is inside the table — Rows typed beneath the table are read, but flagged: drag the table's corner handle down over them so they are in it.
B47: =IF(COUNTA('Loans'!$A$1001:$M$1048576)=0,"✔","✘") -> ✔ | C47: Loans: nothing is typed past row 1,000 — This workbook's own sums stop at row 1,000 (room for 997 rows); the page and the report tool read rows past it, so their figures would differ from this workbook's.
B48: =IF(SUMPRODUCT(('Loans'!$A$4:$A$1000<>"")*(COUNTIF(LoanTypes,TRIM('Loans'!$A$4:$A$1000))=0))+SUMPRODUCT(('Loans'!$C$4:$C$1000<>"")*(COUNTIF(LenderTypes,TRIM('Loans'!$C$4:$C$1000))=0))+SUMPRODUCT(('Loans'!$H$4:$H$1000<>"")*(COUNTIF(Profiles,TRIM('Loans'!$H$4:$H$1000))=0))+SUMPRODUCT(('Loans'!$I$4:$I$1000<>"")*(COUNTIF(Frequencies,TRIM('Loans'!$I$4:$I$1000))=0))+SUMPRODUCT(('Loans'!$K$4:$K$1000<>"")*(COUNTIF(Funds,TRIM('Loans'!$K$4:$K$1000))=0))=0,"✔","✘") -> ✔ | C48: Loans: every drop-down word is on its list — A word off the list is marked amber in the sheet: pick it from the drop-down. A pasted word is not checked at entry, only here.
B49: =IF(SUMPRODUCT(('Loans'!$D$4:$D$1000<>"")*((1-ISNUMBER('Loans'!$D$4:$D$1000))+ISNUMBER('Loans'!$D$4:$D$1000)*('Loans'!$D$4:$D$1000>0)*('Loans'!$D$4:$D$1000<1000)))=0,"✔","✘") -> ✔ | C49: Loans: amounts are numbers, in pounds — Amounts are in pounds, not £ millions (5,000,000 for £5m), and typed as numbers. A figure typed as text is marked red, one below £1,000 amber.
B50: =IF(SUMPRODUCT(('Loans'!$E$4:$E$1000<>"")*(1-ISNUMBER('Loans'!$E$4:$E$1000)))+SUMPRODUCT(('Loans'!$F$4:$F$1000<>"")*(1-ISNUMBER('Loans'!$F$4:$F$1000)))+SUMPRODUCT(('Loans'!$J$4:$J$1000<>"")*(1-ISNUMBER('Loans'!$J$4:$J$1000)))+SUMPRODUCT(('Loans'!$L$4:$L$1000<>"")*(1-ISNUMBER('Loans'!$L$4:$L$1000)))=0,"✔","✘") -> ✔ | C50: Loans: dates are dates — A date typed as text is marked red: type it as a date (30/09/2026).
B51: =IF(IFERROR(ROWS(PooledFunds[#All])>0,FALSE),"✔","✘") -> ✔ | C51: Pooled funds: the table PooledFunds is there — The table was converted to a range or renamed. Select the rows with their headers, Insert → Table, and name it PooledFunds on the Table Design tab.
B52: =IF(AND('Pooled funds'!$A$3="Fund name",'Pooled funds'!$B$3="Fund type",'Pooled funds'!$C$3="Carrying value",'Pooled funds'!$D$3="Latest value",'Pooled funds'!$E$3="Current rate",'Pooled funds'!$F$3="Purchase date",'Pooled funds'!$G$3="Average value",'Pooled funds'!$H$3="Average rate",'Pooled funds'!$I$3="Notes"),"✔","✘") -> ✔ | C52: Pooled funds: the headers are as the page expects — A header was changed. Put the exact words back, or paste your rows into a fresh template.
B53: =IF(IFERROR(COUNTA('Pooled funds'!$A$4:$A$1048576)-SUMPRODUCT((PooledFunds[Fund name]<>"")*1)=0,FALSE),"✔","✘") -> ✔ | C53: Pooled funds: every row typed is inside the table — Rows typed beneath the table are read, but flagged: drag the table's corner handle down over them so they are in it.
B54: =IF(COUNTA('Pooled funds'!$A$2001:$I$1048576)=0,"✔","✘") -> ✔ | C54: Pooled funds: nothing is typed past row 2,000 — This workbook's own sums stop at row 2,000 (room for 1,997 rows); the page and the report tool read rows past it, so their figures would differ from this workbook's.
B55: =IF(SUMPRODUCT(('Pooled funds'!$B$4:$B$2000<>"")*(COUNTIF(FundTypes,TRIM('Pooled funds'!$B$4:$B$2000))=0))=0,"✔","✘") -> ✔ | C55: Pooled funds: every drop-down word is on its list — A word off the list is marked amber in the sheet: pick it from the drop-down. A pasted word is not checked at entry, only here.
B56: =IF(SUMPRODUCT(('Pooled funds'!$C$4:$C$2000<>"")*((1-ISNUMBER('Pooled funds'!$C$4:$C$2000))+ISNUMBER('Pooled funds'!$C$4:$C$2000)*('Pooled funds'!$C$4:$C$2000>0)*('Pooled funds'!$C$4:$C$2000<1000)))+SUMPRODUCT(('Pooled funds'!$D$4:$D$2000<>"")*((1-ISNUMBER('Pooled funds'!$D$4:$D$2000))+ISNUMBER('Pooled funds'!$D$4:$D$2000)*('Pooled funds'!$D$4:$D$2000>0)*('Pooled funds'!$D$4:$D$2000<1000)))+SUMPRODUCT(('Pooled funds'!$G$4:$G$2000<>"")*((1-ISNUMBER('Pooled funds'!$G$4:$G$2000))+ISNUMBER('Pooled funds'!$G$4:$G$2000)*('Pooled funds'!$G$4:$G$2000>0)*('Pooled funds'!$G$4:$G$2000<1000)))=0,"✔","✘") -> ✔ | C56: Pooled funds: amounts are numbers, in pounds — Amounts are in pounds, not £ millions (5,000,000 for £5m), and typed as numbers. A figure typed as text is marked red, one below £1,000 amber.
B57: =IF(SUMPRODUCT(('Pooled funds'!$F$4:$F$2000<>"")*(1-ISNUMBER('Pooled funds'!$F$4:$F$2000)))=0,"✔","✘") -> ✔ | C57: Pooled funds: dates are dates — A date typed as text is marked red: type it as a date (30/09/2026).
B58: =IF(AND(OR(COUNTA('Projections'!$A$5:$O$57)=0,AND('Projections'!$A$5="Year end",'Projections'!$B$5="Capital financing requirement",'Projections'!$C$5="MRP",'Projections'!$D$5="Capital receipts applied",'Projections'!$E$5="Other balance sheet items",'Projections'!$F$5="Existing loan commitments",'Projections'!$G$5="Existing investment commitments",'Projections'!$H$5="Liquidity allowance",'Projections'!$I$5="Capital expenditure financed by borrowing",'Projections'!$J$5="Interest payable",'Projections'!$K$5="Interest paid to the HRA",'Projections'!$L$5="Interest received from the HRA",'Projections'!$M$5="Investment income",'Projections'!$N$5="Net revenue stream",'Projections'!$O$5="Non-treasury investment income")),OR(COUNTA('Projections'!$A$61:$O$113)=0,AND('Projections'!$A$61="Year end",'Projections'!$B$61="Capital financing requirement",'Projections'!$C$61="MRP",'Projections'!$D$61="Capital receipts applied",'Projections'!$E$61="Other balance sheet items",'Projections'!$F$61="Existing loan commitments",'Projections'!$G$61="Existing investment commitments",'Projections'!$H$61="Liquidity allowance",'Projections'!$I$61="Capital expenditure financed by borrowing",'Projections'!$J$61="Interest payable",'Projections'!$K$61="Interest paid to the General Fund",'Projections'!$L$61="Interest received from the General Fund",'Projections'!$M$61="Investment income",'Projections'!$N$61="Net revenue stream",'Projections'!$O$61="Non-treasury investment income"))),"✔","✘") -> ✔ | C58: Projections: the headings are as the tool expects — A heading was changed: put the exact words back, or paste a fresh copy of the grid from the tool (Copy for Excel) at cell A5. The tool matches columns by heading.
B59: =IF(AND(OR(COUNTA('Projections'!$A$5:$O$57)=0,IFERROR(AND(VALUE(LEFT('Projections'!$A$6,4))=(YEAR(AsAt)-(MONTH(AsAt)<4))-1,RIGHT('Projections'!$A$6,6)="actual",VALUE(LEFT('Projections'!$A$7,4))=(YEAR(AsAt)-(MONTH(AsAt)<4)),VALUE(LEFT('Projections'!$A$57,4))=(YEAR(AsAt)-(MONTH(AsAt)<4))+50),FALSE)),OR(COUNTA('Projections'!$A$61:$O$113)=0,IFERROR(AND(VALUE(LEFT('Projections'!$A$62,4))=(YEAR(AsAt)-(MONTH(AsAt)<4))-1,RIGHT('Projections'!$A$62,6)="actual",VALUE(LEFT('Projections'!$A$63,4))=(YEAR(AsAt)-(MONTH(AsAt)<4)),VALUE(LEFT('Projections'!$A$113,4))=(YEAR(AsAt)-(MONTH(AsAt)<4))+50),FALSE))),"✔","✘") -> ✔ | C59: Projections: the years follow the As at date — The first row is the actual year before the As at date's year, then fifty-one years from As at's (2026/27 for an As at in 2026/27), and the tool matches rows by year: put the labels right, or paste a fresh copy of the grid from the tool at cell A5.
B60: =IF(SUMPRODUCT(('Projections'!$B$6:$O$57<>"")*(1-ISNUMBER('Projections'!$B$6:$O$57)))+SUMPRODUCT(ISNUMBER('Projections'!$B$6:$O$57)*(('Projections'!$B$6:$O$57>100000)+('Projections'!$B$6:$O$57<-100000)))+SUMPRODUCT(('Projections'!$B$62:$O$113<>"")*(1-ISNUMBER('Projections'!$B$62:$O$113)))+SUMPRODUCT(ISNUMBER('Projections'!$B$62:$O$113)*(('Projections'!$B$62:$O$113>100000)+('Projections'!$B$62:$O$113<-100000)))=0,"✔","✘") -> ✔ | C60: Projections: figures are numbers, in £ millions — This sheet is in £ millions to one decimal (58.1 for £58.1m). A figure above 100,000 is marked amber, text red.
B62: How it works
B63: 1. Settings | C63: the As at date every balance is struck at, the HRA pooling (None, One pool or Two pools: it decides which blocks and columns of the projection are read, and whose loans are whose), and the period the averages cover.
B64: 2. The four tables | C64: Term investments, Call accounts and MMFs, Loans, Pooled funds: a row per deal, the drop-down words exactly. A cell that is wrong or missing is marked as you type.
B65: 3. Projections | C65: your projection, one row a year, a block per fund — the report tool's figures grid in the workbook. Fill it and the tool reads it; leave it blank and you type in the tool instead.
B66: 4. The Dashboard and the Benchmark | C66: what the rows add up to, for checking: positions, ladders, the next twelve months, the period’s activity, the rows that need attention; and the liability benchmark with the Code's five charts, from the projection and the loans as they run off.
B67: 5. The Position and the lists | C67: the treasury position at the start of the period and at the As at date, with average rates and lives and the counterparties by size; and every loan and every investment held, one row each. The same figures the report tool works out, and every sheet set to print on A4.
B68: 6. Hidden sheets | C68: Loan maths, Deal maths and List maths hold the formulas' working, and Lists the drop-down words: hidden, so nothing there is typed over. To look at them, Review → Protect Workbook to lift the lock (there is no password), then right-click any tab → Unhide.
B69: 7. The report tool | C69: reads this file in your browser and never changes it. It keeps a copy of the rows and the projection it read with your report, in your PWLBtoday account.
B71: Open the report tool ↗ | C71: Read this workbook into a report: the holdings, the projections, the draft and its appendix.
B72: The deal list page ↗ | C72: The same workbook read on its own: every chart, every row as read, nothing stored.
B74: This workbook stays on your own computer. The page and the report tool read it in your browser and never change it: the workbook is the record, they are readers for it. The report tool keeps a copy of the rows it read with your report, in your PWLBtoday account.
B75: Protected against accidents, not against you: the sheets cannot be renamed or deleted, the sheets of formulas and the Lists are locked, and on Settings only the yellow cells are open. The sheets you type in, the four holding sheets and Projections, are open throughout: an Excel Table cannot grow on a protected sheet, and a grid copied from the tool pastes at Projections cell A5 in one go. There is no password: Review → Unprotect Sheet, or Protect Workbook, lifts any of it in one click.

Sheet Settings
A1: Settings | D1: the dates and the pooling | F1: ◂ Start here
A2: Fill the yellow cells. Each other tab is a table: keep the headers and put your rows beneath them. This file stays on your own computer: the page and the report tool read it in your browser and never change it.
A4: As at | B4: 46295 | C4: The date every balance in this file is struck at
A5: HRA | B5: None | C5: None, One pool or Two pools — with two pools, each loan says which fund it belongs to
A6: Template version | B6: 3 | C6: Leave this: the page checks it
A7: Period from | B7: 46113 | C7: The start of the period the averages on the call account and pooled fund sheets cover, to the As at date: usually 1 April

Sheet Term investments
A1: Term investments | K1: one row per deal | M1: ◂ Start here
A2: Fixed-term deposits, CDs, Treasury bills, gilts and bonds, and loans to other authorities. Principal is the amount placed or paid. For a tradeable instrument also give the Face value (the nominal that comes back at maturity) and, if you have it, the Carrying value at the as-at date; leave both blank for a deposit. Keep a deal after it matures: the page reads it as history for the activity figures, not as a holding.
A3: Type | B3: Counterparty | C3: Counterparty type | D3: Principal | E3: Start date | F3: Maturity date | G3: Rate | H3: Face value | I3: Carrying value | J3: Rating | K3: Notes | M3: Example rows: replace them with your own

Sheet Call accounts and MMFs
A1: Call accounts and MMFs | J1: one row per deal | L1: ◂ Start here
A2: Instant-access and notice accounts and money market funds, at their balance on the as-at date — and, over the period on Settings, the average balance held and the average rate earned, which is what the income figures are read from.
A3: Type | B3: Counterparty | C3: Counterparty type | D3: Balance | E3: Rate | F3: Notice days | G3: Rating | H3: Average balance | I3: Average rate | J3: Notes | L3: Example rows: replace them with your own

Sheet Loans
A1: Loans | M1: one row per deal | O1: ◂ Start here
A2: Every loan. Principal is the amount outstanding at the as-at date, or for a loan repaid before it, the amount repaid; keep a repaid loan as history for the activity figures. Profile is Maturity (all repaid at the end), EIP (equal instalments of principal) or Annuity (level payments). Frequency may be left blank: half-yearly, as PWLB loans pay, is assumed. The First repayment date may be left blank: the first payment date after the start, on the cycle that ends at the maturity date, is assumed (a PWLB loan's front-end stub). Fund applies only when Settings says Two pools. Next call date is for LOBOs.
A3: Type | B3: Lender | C3: Lender type | D3: Principal | E3: Start date | F3: Maturity date | G3: Rate | H3: Profile | I3: Frequency | J3: First repayment date | K3: Fund | L3: Next call date | M3: Notes | O3: Example rows: replace them with your own

Sheet Pooled funds
A1: Pooled funds | I1: one row per deal | K1: ◂ Start here
A2: Strategic pooled funds held for the long term: the carrying value, the latest valuation and the current income rate — and, over the period on Settings, the average value and the average income rate.
A3: Fund name | B3: Fund type | C3: Carrying value | D3: Latest value | E3: Current rate | F3: Purchase date | G3: Average value | H3: Average rate | I3: Notes | K3: Example rows: replace them with your own

Sheet Projections
A1: Projections | O1: the report tool's figures grid, in £m | Q1: ◂ Start here
A2: Your projection, in £m to one decimal: one row a year, one column a figure, a block for each fund — the report tool's own grid, laid out as its Copy for Excel block. The tool reads this sheet into its projection and locks the grid while this workbook is in use; leave it blank and you type there instead. Leave Existing loan commitments and Existing investment commitments blank to take the run-off of the Loans and investment sheets (the Benchmark sheet and the tool both work it the same way); type a figure to state your own. The budget lines (grey beyond the fifth year) are read for the MTFP only. The HRA block is read when Settings says One pool or Two pools; under One pool its loans, interest payable and the General Fund-only columns are not read, and the inter-fund columns are read only where there are two funds. The year headings are text, as the tool writes them.
A4: General Fund | C4: read whatever Settings says
A5: Year end | B5: Capital financing requirement | C5: MRP | D5: Capital receipts applied | E5: Other balance sheet items | F5: Existing loan commitments | G5: Existing investment commitments | H5: Liquidity allowance | I5: Capital expenditure financed by borrowing | J5: Interest payable | K5: Interest paid to the HRA | L5: Interest received from the HRA | M5: Investment income | N5: Net revenue stream | O5: Non-treasury investment income | Q5: Type your figures in £m, or leave the blocks blank to type them in the tool
A6: 2025/26 actual
A7: 2026/27
A8: 2027/28
A9: 2028/29
A10: 2029/30
A11: 2030/31
A12: 2031/32
A13: 2032/33
A14: 2033/34
A15: 2034/35
A16: 2035/36
A17: 2036/37
... A57: 2076/77
A60: HRA | C60: read when Settings says One pool or Two pools; the greyed columns are not
A61: Year end | B61: Capital financing requirement | C61: MRP | D61: Capital receipts applied | E61: Other balance sheet items | F61: Existing loan commitments | G61: Existing investment commitments | H61: Liquidity allowance | I61: Capital expenditure financed by borrowing | J61: Interest payable | K61: Interest paid to the General Fund | L61: Interest received from the General Fund | M61: Investment income | N61: Net revenue stream | O61: Non-treasury investment income
A62: 2025/26 actual
A63: 2026/27
A64: 2027/28
A65: 2028/29
A66: 2029/30
A67: 2030/31
A68: 2031/32
A69: 2032/33
A70: 2033/34
A71: 2034/35
A72: 2035/36
A73: 2036/37
... A113: 2076/77

Sheet Dashboard
A1: Dashboard | J1: for checking what the rows add up to | L1: ◂ Start here
B2: What the four tables add up to as at the Settings date, for checking as you type: term deals at nominal while they are out, loans at principal outstanding, a LOBO at its next call, EIP and annuity loans instalment by instalment on the cycle that ends at maturity (the Loan maths sheet shows each loan's). Nothing here is read by the page or the tool, which do the same sums their own way.
B3: As at | C3: =AsAt -> 46295 | D3: Period from | E3: =PeriodFrom -> 46113 | F3: HRA | G3: =HRA -> None
B5: =SUMPRODUCT(('Deal maths'!$F$4:$F$2000>AsAt)*('Deal maths'!$E$4:$E$2000<=AsAt)*('Deal maths'!$H$4:$H$2000+('Deal maths'!$H$4:$H$2000=0)*'Deal maths'!$D$4:$D$2000))+SUM('Deal maths'!$M$4:$M$2000) -> 0 | C5: =SUMPRODUCT(('Deal maths'!$F$4:$F$2000>AsAt)*('Deal maths'!$E$4:$E$2000<=AsAt)*(('Deal maths'!$H$4:$H$2000+('Deal maths'!$H$4:$H$2000=0)*'Deal maths'!$D$4:$D$2000)>0)) -> 0 | D5: =SUM('Deal maths'!$M$4:$M$2000) -> 0 | E5: =IFERROR((SUMPRODUCT(('Deal maths'!$F$4:$F$2000>AsAt)*('Deal maths'!$E$4:$E$2000<=AsAt)*('Deal maths'!$H$4:$H$2000+('Deal maths'!$H$4:$H$2000=0)*'Deal maths'!$D$4:$D$2000)*'Deal maths'!$G$4:$G$2000)+SUMPRODUCT('Deal maths'!$M$4:$M$2000*'Deal maths'!$N$4:$N$2000))/(SUMPRODUCT(('Deal maths'!$F$4:$F$2000>AsAt)*('Deal maths'!$E$4:$E$2000<=AsAt)*('Deal maths'!$H$4:$H$2000+('Deal maths'!$H$4:$H$2000=0)*'Deal maths'!$D$4:$D$2000)*'Deal maths'!$I$4:$I$2000)+SUMPRODUCT('Deal maths'!$M$4:$M$2000*'Deal maths'!$P$4:$P$2000)),0) -> 0 | F5: =SUMPRODUCT((LN_maturity>AsAt)*(LN_start<=AsAt)*LN_principal) -> 0 | G5: =SUM(LM_live) -> 0 | H5: =IFERROR(SUMPRODUCT((LN_maturity>AsAt)*(LN_start<=AsAt)*LN_principal*'Deal maths'!$AB$4:$AB$1000)/SUMPRODUCT((LN_maturity>AsAt)*(LN_start<=AsAt)*LN_principal*'Deal maths'!$AH$4:$AH$1000),0) -> 0 | I5: =SUMPRODUCT(('Deal maths'!$R$4:$R$2000>0)*('Deal maths'!$S$4:$S$2000+('Deal maths'!$S$4:$S$2000=0)*'Deal maths'!$R$4:$R$2000)) -> 0
B6: Invested | C6: Term deals | D6: On call and in MMFs | E6: Investment rate | F6: Borrowed | G6: Loans | H6: Debt rate | I6: Pooled funds, latest
B8: Investments by counterparty type
B9: Counterparty type | C9: Amount | D9: Share
B10: UK bank | C10: =SUMPRODUCT(('Deal maths'!$F$4:$F$2000>AsAt)*('Deal maths'!$E$4:$E$2000<=AsAt)*('Deal maths'!$C$4:$C$2000="UK bank")*('Deal maths'!$H$4:$H$2000+('Deal maths'!$H$4:$H$2000=0)*'Deal maths'!$D$4:$D$2000))+SUMPRODUCT(('Deal maths'!$L$4:$L$2000="UK bank")*'Deal maths'!$M$4:$M$2000) -> 0 | D10: =IFERROR(C10/C$19,0) -> 0
B11: Overseas bank | C11: =SUMPRODUCT(('Deal maths'!$F$4:$F$2000>AsAt)*('Deal maths'!$E$4:$E$2000<=AsAt)*('Deal maths'!$C$4:$C$2000="Overseas bank")*('Deal maths'!$H$4:$H$2000+('Deal maths'!$H$4:$H$2000=0)*'Deal maths'!$D$4:$D$2000))+SUMPRODUCT(('Deal maths'!$L$4:$L$2000="Overseas bank")*'Deal maths'!$M$4:$M$2000) -> 0 | D11: =IFERROR(C11/C$19,0) -> 0
B12: Building society | C12: =SUMPRODUCT(('Deal maths'!$F$4:$F$2000>AsAt)*('Deal maths'!$E$4:$E$2000<=AsAt)*('Deal maths'!$C$4:$C$2000="Building society")*('Deal maths'!$H$4:$H$2000+('Deal maths'!$H$4:$H$2000=0)*'Deal maths'!$D$4:$D$2000))+SUMPRODUCT(('Deal maths'!$L$4:$L$2000="Building society")*'Deal maths'!$M$4:$M$2000) -> 0 | D12: =IFERROR(C12/C$19,0) -> 0
B13: Local authority | C13: =SUMPRODUCT(('Deal maths'!$F$4:$F$2000>AsAt)*('Deal maths'!$E$4:$E$2000<=AsAt)*('Deal maths'!$C$4:$C$2000="Local authority")*('Deal maths'!$H$4:$H$2000+('Deal maths'!$H$4:$H$2000=0)*'Deal maths'!$D$4:$D$2000))+SUMPRODUCT(('Deal maths'!$L$4:$L$2000="Local authority")*'Deal maths'!$M$4:$M$2000) -> 0 | D13: =IFERROR(C13/C$19,0) -> 0
B14: UK Government | C14: =SUMPRODUCT(('Deal maths'!$F$4:$F$2000>AsAt)*('Deal maths'!$E$4:$E$2000<=AsAt)*('Deal maths'!$C$4:$C$2000="UK Government")*('Deal maths'!$H$4:$H$2000+('Deal maths'!$H$4:$H$2000=0)*'Deal maths'!$D$4:$D$2000))+SUMPRODUCT(('Deal maths'!$L$4:$L$2000="UK Government")*'Deal maths'!$M$4:$M$2000) -> 0 | D14: =IFERROR(C14/C$19,0) -> 0
B15: Money market fund | C15: =SUMPRODUCT(('Deal maths'!$F$4:$F$2000>AsAt)*('Deal maths'!$E$4:$E$2000<=AsAt)*('Deal maths'!$C$4:$C$2000="Money market fund")*('Deal maths'!$H$4:$H$2000+('Deal maths'!$H$4:$H$2000=0)*'Deal maths'!$D$4:$D$2000))+SUMPRODUCT(('Deal maths'!$L$4:$L$2000="Money market fund")*'Deal maths'!$M$4:$M$2000) -> 0 | D15: =IFERROR(C15/C$19,0) -> 0
B16: Pooled fund | C16: =SUMPRODUCT(('Deal maths'!$F$4:$F$2000>AsAt)*('Deal maths'!$E$4:$E$2000<=AsAt)*('Deal maths'!$C$4:$C$2000="Pooled fund")*('Deal maths'!$H$4:$H$2000+('Deal maths'!$H$4:$H$2000=0)*'Deal maths'!$D$4:$D$2000))+SUMPRODUCT(('Deal maths'!$L$4:$L$2000="Pooled fund")*'Deal maths'!$M$4:$M$2000) -> 0 | D16: =IFERROR(C16/C$19,0) -> 0
B17: Other | C17: =SUMPRODUCT(('Deal maths'!$F$4:$F$2000>AsAt)*('Deal maths'!$E$4:$E$2000<=AsAt)*('Deal maths'!$C$4:$C$2000="Other")*('Deal maths'!$H$4:$H$2000+('Deal maths'!$H$4:$H$2000=0)*'Deal maths'!$D$4:$D$2000))+SUMPRODUCT(('Deal maths'!$L$4:$L$2000="Other")*'Deal maths'!$M$4:$M$2000) -> 0 | D17: =IFERROR(C17/C$19,0) -> 0
B18: Not on the list | C18: =SUMPRODUCT(('Deal maths'!$F$4:$F$2000>AsAt)*('Deal maths'!$E$4:$E$2000<=AsAt)*(COUNTIF(CounterpartyTypes,'Deal maths'!$C$4:$C$2000)=0)*('Deal maths'!$H$4:$H$2000+('Deal maths'!$H$4:$H$2000=0)*'Deal maths'!$D$4:$D$2000))+SUMPRODUCT((COUNTIF(CounterpartyTypes,'Deal maths'!$L$4:$L$2000)=0)*'Deal maths'!$M$4:$M$2000) -> 0 | D18: =IFERROR(C18/C$19,0) -> 0
B19: Total | C19: =SUM(C10:C18) -> 0 | D19: =IFERROR(SUM(D10:D18),0) -> 0
B20: Term deals at nominal and call balances together, by the Counterparty type column; a type not on the list (or blank) in its own row.
B22: Maturity ladder
B23: Available | C23: Amount
B24: On call | C24: =SUMPRODUCT(('Deal maths'!$O$4:$O$2000=0)*'Deal maths'!$M$4:$M$2000) -> 0
B25: Under 3 months | C25: =SUMPRODUCT(('Deal maths'!$F$4:$F$2000>AsAt)*('Deal maths'!$E$4:$E$2000<=AsAt)*('Deal maths'!$F$4:$F$2000<IF(DAY(AsAt+1)=1,EOMONTH(AsAt,3),EDATE(AsAt,3)))*('Deal maths'!$H$4:$H$2000+('Deal maths'!$H$4:$H$2000=0)*'Deal maths'!$D$4:$D$2000))+SUMPRODUCT(('Deal maths'!$O$4:$O$2000>0)*(AsAt+'Deal maths'!$O$4:$O$2000>=AsAt)*(AsAt+'Deal maths'!$O$4:$O$2000<IF(DAY(AsAt+1)=1,EOMONTH(AsAt,3),EDATE(AsAt,3)))*'Deal maths'!$M$4:$M$2000) -> 0
B26: 3 to 6 months | C26: =SUMPRODUCT(('Deal maths'!$F$4:$F$2000>AsAt)*('Deal maths'!$E$4:$E$2000<=AsAt)*('Deal maths'!$F$4:$F$2000>=IF(DAY(AsAt+1)=1,EOMONTH(AsAt,3),EDATE(AsAt,3)))*('Deal maths'!$F$4:$F$2000<IF(DAY(AsAt+1)=1,EOMONTH(AsAt,6),EDATE(AsAt,6)))*('Deal maths'!$H$4:$H$2000+('Deal maths'!$H$4:$H$2000=0)*'Deal maths'!$D$4:$D$2000))+SUMPRODUCT(('Deal maths'!$O$4:$O$2000>0)*(AsAt+'Deal maths'!$O$4:$O$2000>=IF(DAY(AsAt+1)=1,EOMONTH(AsAt,3),EDATE(AsAt,3)))*(AsAt+'Deal maths'!$O$4:$O$2000<IF(DAY(AsAt+1)=1,EOMONTH(AsAt,6),EDATE(AsAt,6)))*'Deal maths'!$M$4:$M$2000) -> 0
B27: 6 to 12 months | C27: =SUMPRODUCT(('Deal maths'!$F$4:$F$2000>AsAt)*('Deal maths'!$E$4:$E$2000<=AsAt)*('Deal maths'!$F$4:$F$2000>=IF(DAY(AsAt+1)=1,EOMONTH(AsAt,6),EDATE(AsAt,6)))*('Deal maths'!$F$4:$F$2000<IF(DAY(AsAt+1)=1,EOMONTH(AsAt,12),EDATE(AsAt,12)))*('Deal maths'!$H$4:$H$2000+('Deal maths'!$H$4:$H$2000=0)*'Deal maths'!$D$4:$D$2000))+SUMPRODUCT(('Deal maths'!$O$4:$O$2000>0)*(AsAt+'Deal maths'!$O$4:$O$2000>=IF(DAY(AsAt+1)=1,EOMONTH(AsAt,6),EDATE(AsAt,6)))*(AsAt+'Deal maths'!$O$4:$O$2000<IF(DAY(AsAt+1)=1,EOMONTH(AsAt,12),EDATE(AsAt,12)))*'Deal maths'!$M$4:$M$2000) -> 0
B28: 1 to 2 years | C28: =SUMPRODUCT(('Deal maths'!$F$4:$F$2000>AsAt)*('Deal maths'!$E$4:$E$2000<=AsAt)*('Deal maths'!$F$4:$F$2000>=IF(DAY(AsAt+1)=1,EOMONTH(AsAt,12),EDATE(AsAt,12)))*('Deal maths'!$F$4:$F$2000<IF(DAY(AsAt+1)=1,EOMONTH(AsAt,24),EDATE(AsAt,24)))*('Deal maths'!$H$4:$H$2000+('Deal maths'!$H$4:$H$2000=0)*'Deal maths'!$D$4:$D$2000))+SUMPRODUCT(('Deal maths'!$O$4:$O$2000>0)*(AsAt+'Deal maths'!$O$4:$O$2000>=IF(DAY(AsAt+1)=1,EOMONTH(AsAt,12),EDATE(AsAt,12)))*(AsAt+'Deal maths'!$O$4:$O$2000<IF(DAY(AsAt+1)=1,EOMONTH(AsAt,24),EDATE(AsAt,24)))*'Deal maths'!$M$4:$M$2000) -> 0
B29: 2 to 5 years | C29: =SUMPRODUCT(('Deal maths'!$F$4:$F$2000>AsAt)*('Deal maths'!$E$4:$E$2000<=AsAt)*('Deal maths'!$F$4:$F$2000>=IF(DAY(AsAt+1)=1,EOMONTH(AsAt,24),EDATE(AsAt,24)))*('Deal maths'!$F$4:$F$2000<IF(DAY(AsAt+1)=1,EOMONTH(AsAt,60),EDATE(AsAt,60)))*('Deal maths'!$H$4:$H$2000+('Deal maths'!$H$4:$H$2000=0)*'Deal maths'!$D$4:$D$2000))+SUMPRODUCT(('Deal maths'!$O$4:$O$2000>0)*(AsAt+'Deal maths'!$O$4:$O$2000>=IF(DAY(AsAt+1)=1,EOMONTH(AsAt,24),EDATE(AsAt,24)))*(AsAt+'Deal maths'!$O$4:$O$2000<IF(DAY(AsAt+1)=1,EOMONTH(AsAt,60),EDATE(AsAt,60)))*'Deal maths'!$M$4:$M$2000) -> 0
B30: Over 5 years | C30: =SUMPRODUCT(('Deal maths'!$F$4:$F$2000>AsAt)*('Deal maths'!$E$4:$E$2000<=AsAt)*('Deal maths'!$F$4:$F$2000>=IF(DAY(AsAt+1)=1,EOMONTH(AsAt,60),EDATE(AsAt,60)))*1*('Deal maths'!$H$4:$H$2000+('Deal maths'!$H$4:$H$2000=0)*'Deal maths'!$D$4:$D$2000))+SUMPRODUCT(('Deal maths'!$O$4:$O$2000>0)*(AsAt+'Deal maths'!$O$4:$O$2000>=IF(DAY(AsAt+1)=1,EOMONTH(AsAt,60),EDATE(AsAt,60)))*'Deal maths'!$M$4:$M$2000) -> 0
B31: Total | C31: =SUM(C24:C30) -> 0
B32: Money on call first, a notice account at its notice, term deals at nominal by time to maturity; pooled funds are not here.
B35: Borrowing by lender type
B36: Lender type | C36: Outstanding | D36: Share
B37: PWLB | C37: =SUMPRODUCT((LN_maturity>AsAt)*(LN_start<=AsAt)*('Deal maths'!$X$4:$X$1000="PWLB")*LN_principal) -> 0 | D37: =IFERROR(C37/C$43,0) -> 0
B38: Local authority | C38: =SUMPRODUCT((LN_maturity>AsAt)*(LN_start<=AsAt)*('Deal maths'!$X$4:$X$1000="Local authority")*LN_principal) -> 0 | D38: =IFERROR(C38/C$43,0) -> 0
B39: UK bank | C39: =SUMPRODUCT((LN_maturity>AsAt)*(LN_start<=AsAt)*('Deal maths'!$X$4:$X$1000="UK bank")*LN_principal) -> 0 | D39: =IFERROR(C39/C$43,0) -> 0
B40: Overseas bank | C40: =SUMPRODUCT((LN_maturity>AsAt)*(LN_start<=AsAt)*('Deal maths'!$X$4:$X$1000="Overseas bank")*LN_principal) -> 0 | D40: =IFERROR(C40/C$43,0) -> 0
B41: Other | C41: =SUMPRODUCT((LN_maturity>AsAt)*(LN_start<=AsAt)*('Deal maths'!$X$4:$X$1000="Other")*LN_principal) -> 0 | D41: =IFERROR(C41/C$43,0) -> 0
B42: Not on the list | C42: =SUMPRODUCT((LN_maturity>AsAt)*(LN_start<=AsAt)*(COUNTIF(LenderTypes,'Deal maths'!$X$4:$X$1000)=0)*LN_principal) -> 0 | D42: =IFERROR(C42/C$43,0) -> 0
B43: Total | C43: =SUM(C37:C42) -> 0 | D43: =IFERROR(SUM(D37:D42),0) -> 0
B44: By fund (Settings: Two pools)
B45: Fund | C45: Outstanding
B46: General Fund | C46: =SUMPRODUCT((LN_maturity>AsAt)*(LN_start<=AsAt)*(LN_fund="General Fund")*LN_principal) -> 0
B47: HRA | C47: =SUMPRODUCT((LN_maturity>AsAt)*(LN_start<=AsAt)*(LN_fund="HRA")*LN_principal) -> 0
B48: Not stated | C48: =SUMPRODUCT((LN_maturity>AsAt)*(LN_start<=AsAt)*(LN_fund="")*LN_principal) -> 0
B49: Total | C49: =SUM(C46:C48) -> 0
B51: Maturity structure of borrowing
B52: Maturing in | C52: Principal | D52: Share
B53: Under 1 year | C53: =SUMPRODUCT(LM_live*(LM_profile="EIP")*LM_eip*((('Loan maths'!$U$2>=LM_first)*((INT(((YEAR('Loan maths'!$U$2)-YEAR(LM_first))*12+MONTH('Loan maths'!$U$2)-MONTH(LM_first)-(DAY('Loan maths'!$U$2)<(LM_anchor-(LM_anchor-DAY(EOMONTH('Loan maths'!$U$2,0)))*(LM_anchor>DAY(EOMONTH('Loan maths'!$U$2,0))))))/(LM_step+(LM_step=0)))+1)+(LM_cycles-(INT(((YEAR('Loan maths'!$U$2)-YEAR(LM_first))*12+MONTH('Loan maths'!$U$2)-MONTH(LM_first)-(DAY('Loan maths'!$U$2)<(LM_anchor-(LM_anchor-DAY(EOMONTH('Loan maths'!$U$2,0)))*(LM_anchor>DAY(EOMONTH('Loan maths'!$U$2,0))))))/(LM_step+(LM_step=0)))+1))*((INT(((YEAR('Loan maths'!$U$2)-YEAR(LM_first))*12+MONTH('Loan maths'!$U$2)-MONTH(LM_first)-(DAY('Loan maths'!$U$2)<(LM_anchor-(LM_anchor-DAY(EOMONTH('Loan maths'!$U$2,0)))*(LM_anchor>DAY(EOMONTH('Loan maths'!$U$2,0))))))/(LM_step+(LM_step=0)))+1)>LM_cycles))+LM_stub*('Loan maths'!$U$2>=LN_maturity))-LM_paid))+SUMPRODUCT(LM_live*(LM_profile="Annuity")*(((LM_rate>0)*(LM_out*(1+LM_rate)^(LM_paid-LM_paid)-LM_annuity*((1+LM_rate)^(LM_paid-LM_paid)-1)/LM_safe)+(LM_rate=0)*(LM_out-LM_annuity*(LM_paid-LM_paid)))-((LM_rate>0)*(LM_out*(1+LM_rate)^((('Loan maths'!$U$2>=LM_first)*((INT(((YEAR('Loan maths'!$U$2)-YEAR(LM_first))*12+MONTH('Loan maths'!$U$2)-MONTH(LM_first)-(DAY('Loan maths'!$U$2)<(LM_anchor-(LM_anchor-DAY(EOMONTH('Loan maths'!$U$2,0)))*(LM_anchor>DAY(EOMONTH('Loan maths'!$U$2,0))))))/(LM_step+(LM_step=0)))+1)+(LM_cycles-(INT(((YEAR('Loan maths'!$U$2)-YEAR(LM_first))*12+MONTH('Loan maths'!$U$2)-MONTH(LM_first)-(DAY('Loan maths'!$U$2)<(LM_anchor-(LM_anchor-DAY(EOMONTH('Loan maths'!$U$2,0)))*(LM_anchor>DAY(EOMONTH('Loan maths'!$U$2,0))))))/(LM_step+(LM_step=0)))+1))*((INT(((YEAR('Loan maths'!$U$2)-YEAR(LM_first))*12+MONTH('Loan maths'!$U$2)-MONTH(LM_first)-(DAY('Loan maths'!$U$2)<(LM_anchor-(LM_anchor-DAY(EOMONTH('Loan maths'!$U$2,0)))*(LM_anchor>DAY(EOMONTH('Loan maths'!$U$2,0))))))/(LM_step+(LM_step=0)))+1)>LM_cycles))+LM_stub*('Loan maths'!$U$2>=LN_maturity))-LM_paid)-LM_annuity*((1+LM_rate)^((('Loan maths'!$U$2>=LM_first)*((INT(((YEAR('Loan maths'!$U$2)-YEAR(LM_first))*12+MONTH('Loan maths'!$U$2)-MONTH(LM_first)-(DAY('Loan maths'!$U$2)<(LM_anchor-(LM_anchor-DAY(EOMONTH('Loan maths'!$U$2,0)))*(LM_anchor>DAY(EOMONTH('Loan maths'!$U$2,0))))))/(LM_step+(LM_step=0)))+1)+(LM_cycles-(INT(((YEAR('Loan maths'!$U$2)-YEAR(LM_first))*12+MONTH('Loan maths'!$U$2)-MONTH(LM_first)-(DAY('Loan maths'!$U$2)<(LM_anchor-(LM_anchor-DAY(EOMONTH('Loan maths'!$U$2,0)))*(LM_anchor>DAY(EOMONTH('Loan maths'!$U$2,0))))))/(LM_step+(LM_step=0)))+1))*((INT(((YEAR('Loan maths'!$U$2)-YEAR(LM_first))*12+MONTH('Loan maths'!$U$2)-MONTH(LM_first)-(DAY('Loan maths'!$U$2)<(LM_anchor-(LM_anchor-DAY(EOMONTH('Loan maths'!$U$2,0)))*(LM_anchor>DAY(EOMONTH('Loan maths'!$U$2,0))))))/(LM_step+(LM_step=0)))+1)>LM_cycles))+LM_stub*('Loan maths'!$U$2>=LN_maturity))-LM_paid)-1)/LM_safe)+(LM_rate=0)*(LM_out-LM_annuity*((('Loan maths'!$U$2>=LM_first)*((INT(((YEAR('Loan maths'!$U$2)-YEAR(LM_first))*12+MONTH('Loan maths'!$U$2)-MONTH(LM_first)-(DAY('Loan maths'!$U$2)<(LM_anchor-(LM_anchor-DAY(EOMONTH('Loan maths'!$U$2,0)))*(LM_anchor>DAY(EOMONTH('Loan maths'!$U$2,0))))))/(LM_step+(LM_step=0)))+1)+(LM_cycles-(INT(((YEAR('Loan maths'!$U$2)-YEAR(LM_first))*12+MONTH('Loan maths'!$U$2)-MONTH(LM_first)-(DAY('Loan maths'!$U$2)<(LM_anchor-(LM_anchor-DAY(EOMONTH('Loan maths'!$U$2,0)))*(LM_anchor>DAY(EOMONTH('Loan maths'!$U$2,0))))))/(LM_step+(LM_step=0)))+1))*((INT(((YEAR('Loan maths'!$U$2)-YEAR(LM_first))*12+MONTH('Loan maths'!$U$2)-MONTH(LM_first)-(DAY('Loan maths'!$U$2)<(LM_anchor-(LM_anchor-DAY(EOMONTH('Loan maths'!$U$2,0)))*(LM_anchor>DAY(EOMONTH('Loan maths'!$U$2,0))))))/(LM_step+(LM_step=0)))+1)>LM_cycles))+LM_stub*('Loan maths'!$U$2>=LN_maturity))-LM_paid)))))+SUMPRODUCT(LM_live*((LM_profile<>"EIP")*(LM_profile<>"Annuity"))*(LM_end>AsAt)*(LM_end<='Loan maths'!$U$2)*LN_principal) -> 0 | D53: =IFERROR(C53/C$62,0) -> 0
B54: 1 to 2 years | C54: =SUMPRODUCT(LM_live*(LM_profile="EIP")*LM_eip*((('Loan maths'!$V$2>=LM_first)*((INT(((YEAR('Loan maths'!$V$2)-YEAR(LM_first))*12+MONTH('Loan maths'!$V$2)-MONTH(LM_first)-(DAY('Loan maths'!$V$2)<(LM_anchor-(LM_anchor-DAY(EOMONTH('Loan maths'!$V$2,0)))*(LM_anchor>DAY(EOMONTH('Loan maths'!$V$2,0))))))/(LM_step+(LM_step=0)))+1)+(LM_cycles-(INT(((YEAR('Loan maths'!$V$2)-YEAR(LM_first))*12+MONTH('Loan maths'!$V$2)-MONTH(LM_first)-(DAY('Loan maths'!$V$2)<(LM_anchor-(LM_anchor-DAY(EOMONTH('Loan maths'!$V$2,0)))*(LM_anchor>DAY(EOMONTH('Loan maths'!$V$2,0))))))/(LM_step+(LM_step=0)))+1))*((INT(((YEAR('Loan maths'!$V$2)-YEAR(LM_first))*12+MONTH('Loan maths'!$V$2)-MONTH(LM_first)-(DAY('Loan maths'!$V$2)<(LM_anchor-(LM_anchor-DAY(EOMONTH('Loan maths'!$V$2,0)))*(LM_anchor>DAY(EOMONTH('Loan maths'!$V$2,0))))))/(LM_step+(LM_step=0)))+1)>LM_cycles))+LM_stub*('Loan maths'!$V$2>=LN_maturity))-(('Loan maths'!$U$2>=LM_first)*((INT(((YEAR('Loan maths'!$U$2)-YEAR(LM_first))*12+MONTH('Loan maths'!$U$2)-MONTH(LM_first)-(DAY('Loan maths'!$U$2)<(LM_anchor-(LM_anchor-DAY(EOMONTH('Loan maths'!$U$2,0)))*(LM_anchor>DAY(EOMONTH('Loan maths'!$U$2,0))))))/(LM_step+(LM_step=0)))+1)+(LM_cycles-(INT(((YEAR('Loan maths'!$U$2)-YEAR(LM_first))*12+MONTH('Loan maths'!$U$2)-MONTH(LM_first)-(DAY('Loan maths'!$U$2)<(LM_anchor-(LM_anchor-DAY(EOMONTH('Loan maths'!$U$2,0)))*(LM_anchor>DAY(EOMONTH('Loan maths'!$U$2,0))))))/(LM_step+(LM_step=0)))+1))*((INT(((YEAR('Loan maths'!$U$2)-YEAR(LM_first))*12+MONTH('Loan maths'!$U$2)-MONTH(LM_first)-(DAY('Loan maths'!$U$2)<(LM_anchor-(LM_anchor-DAY(EOMONTH('Loan maths'!$U$2,0)))*(LM_anchor>DAY(EOMONTH('Loan maths'!$U$2,0))))))/(LM_step+(LM_step=0)))+1)>LM_cycles))+LM_stub*('Loan maths'!$U$2>=LN_maturity))))+SUMPRODUCT(LM_live*(LM_profile="Annuity")*(((LM_rate>0)*(LM_out*(1+LM_rate)^((('Loan maths'!$U$2>=LM_first)*((INT(((YEAR('Loan maths'!$U$2)-YEAR(LM_first))*12+MONTH('Loan maths'!$U$2)-MONTH(LM_first)-(DAY('Loan maths'!$U$2)<(LM_anchor-(LM_anchor-DAY(EOMONTH('Loan maths'!$U$2,0)))*(LM_anchor>DAY(EOMONTH('Loan maths'!$U$2,0))))))/(LM_step+(LM_step=0)))+1)+(LM_cycles-(INT(((YEAR('Loan maths'!$U$2)-YEAR(LM_first))*12+MONTH('Loan maths'!$U$2)-MONTH(LM_first)-(DAY('Loan maths'!$U$2)<(LM_anchor-(LM_anchor-DAY(EOMONTH('Loan maths'!$U$2,0)))*(LM_anchor>DAY(EOMONTH('Loan maths'!$U$2,0))))))/(LM_step+(LM_step=0)))+1))*((INT(((YEAR('Loan maths'!$U$2)-YEAR(LM_first))*12+MONTH('Loan maths'!$U$2)-MONTH(LM_first)-(DAY('Loan maths'!$U$2)<(LM_anchor-(LM_anchor-DAY(EOMONTH('Loan maths'!$U$2,0)))*(LM_anchor>DAY(EOMONTH('Loan maths'!$U$2,0))))))/(LM_step+(LM_step=0)))+1)>LM_cycles))+LM_stub*('Loan maths'!$U$2>=LN_maturity))-LM_paid)-LM_annuity*((1+LM_rate)^((('Loan maths'!$U$2>=LM_first)*((INT(((YEAR('Loan maths'!$U$2)-YEAR(LM_first))*12+MONTH('Loan maths'!$U$2)-MONTH(LM_first)-(DAY('Loan maths'!$U$2)<(LM_anchor-(LM_anchor-DAY(EOMONTH('Loan maths'!$U$2,0)))*(LM_anchor>DAY(EOMONTH('Loan maths'!$U$2,0))))))/(LM_step+(LM_step=0)))+1)+(LM_cycles-(INT(((YEAR('Loan maths'!$U$2)-YEAR(LM_first))*12+MONTH('Loan maths'!$U$2)-MONTH(LM_first)-(DAY('Loan maths'!$U$2)<(LM_anchor-(LM_anchor-DAY(EOMONTH('Loan maths'!$U$2,0)))*(LM_anchor>DAY(EOMONTH('Loan maths'!$U$2,0))))))/(LM_step+(LM_step=0)))+1))*((INT(((YEAR('Loan maths'!$U$2)-YEAR(LM_first))*12+MONTH('Loan maths'!$U$2)-MONTH(LM_first)-(DAY('Loan maths'!$U$2)<(LM_anchor-(LM_anchor-DAY(EOMONTH('Loan maths'!$U$2,0)))*(LM_anchor>DAY(EOMONTH('Loan maths'!$U$2,0))))))/(LM_step+(LM_step=0)))+1)>LM_cycles))+LM_stub*('Loan maths'!$U$2>=LN_maturity))-LM_paid)-1)/LM_safe)+(LM_rate=0)*(LM_out-LM_annuity*((('Loan maths'!$U$2>=LM_first)*((INT(((YEAR('Loan maths'!$U$2)-YEAR(LM_first))*12+MONTH('Loan maths'!$U$2)-MONTH(LM_first)-(DAY('Loan maths'!$U$2)<(LM_anchor-(LM_anchor-DAY(EOMONTH('Loan maths'!$U$2,0)))*(LM_anchor>DAY(EOMONTH('Loan maths'!$U$2,0))))))/(LM_step+(LM_step=0)))+1)+(LM_cycles-(INT(((YEAR('Loan maths'!$U$2)-YEAR(LM_first))*12+MONTH('Loan maths'!$U$2)-MONTH(LM_first)-(DAY('Loan maths'!$U$2)<(LM_anchor-(LM_anchor-DAY(EOMONTH('Loan maths'!$U$2,0)))*(LM_anchor>DAY(EOMONTH('Loan maths'!$U$2,0))))))/(LM_step+(LM_step=0)))+1))*((INT(((YEAR('Loan maths'!$U$2)-YEAR(LM_first))*12+MONTH('Loan maths'!$U$2)-MONTH(LM_first)-(DAY('Loan maths'!$U$2)<(LM_anchor-(LM_anchor-DAY(EOMONTH('Loan maths'!$U$2,0)))*(LM_anchor>DAY(EOMONTH('Loan maths'!$U$2,0))))))/(LM_step+(LM_step=0)))+1)>LM_cycles))+LM_stub*('Loan maths'!$U$2>=LN_maturity))-LM_paid)))-((LM_rate>0)*(LM_out*(1+LM_rate)^((('Loan maths'!$V$2>=LM_first)*((INT(((YEAR('Loan maths'!$V$2)-YEAR(LM_first))*12+MONTH('Loan maths'!$V$2)-MONTH(LM_first)-(DAY('Loan maths'!$V$2)<(LM_anchor-(LM_anchor-DAY(EOMONTH('Loan maths'!$V$2,0)))*(LM_anchor>DAY(EOMONTH('Loan maths'!$V$2,0))))))/(LM_step+(LM_step=0)))+1)+(LM_cycles-(INT(((YEAR('Loan maths'!$V$2)-YEAR(LM_first))*12+MONTH('Loan maths'!$V$2)-MONTH(LM_first)-(DAY('Loan maths'!$V$2)<(LM_anchor-(LM_anchor-DAY(EOMONTH('Loan maths'!$V$2,0)))*(LM_anchor>DAY(EOMONTH('Loan maths'!$V$2,0))))))/(LM_step+(LM_step=0)))+1))*((INT(((YEAR('Loan maths'!$V$2)-YEAR(LM_first))*12+MONTH('Loan maths'!$V$2)-MONTH(LM_first)-(DAY('Loan maths'!$V$2)<(LM_anchor-(LM_anchor-DAY(EOMONTH('Loan maths'!$V$2,0)))*(LM_anchor>DAY(EOMONTH('Loan maths'!$V$2,0))))))/(LM_step+(LM_step=0)))+1)>LM_cycles))+LM_stub*('Loan maths'!$V$2>=LN_maturity))-LM_paid)-LM_annuity*((1+LM_rate)^((('Loan maths'!$V$2>=LM_first)*((INT(((YEAR('Loan maths'!$V$2)-YEAR(LM_first))*12+MONTH('Loan maths'!$V$2)-MONTH(LM_first)-(DAY('Loan maths'!$V$2)<(LM_anchor-(LM_anchor-DAY(EOMONTH('Loan maths'!$V$2,0)))*(LM_anchor>DAY(EOMONTH('Loan maths'!$V$2,0))))))/(LM_step+(LM_step=0)))+1)+(LM_cycles-(INT(((YEAR('Loan maths'!$V$2)-YEAR(LM_first))*12+MONTH('Loan maths'!$V$2)-MONTH(LM_first)-(DAY('Loan maths'!$V$2)<(LM_anchor-(LM_anchor-DAY(EOMONTH('Loan maths'!$V$2,0)))*(LM_anchor>DAY(EOMONTH('Loan maths'!$V$2,0))))))/(LM_step+(LM_step=0)))+1))*((INT(((YEAR('Loan maths'!$V$2)-YEAR(LM_first))*12+MONTH('Loan maths'!$V$2)-MONTH(LM_first)-(DAY('Loan maths'!$V$2)<(LM_anchor-(LM_anchor-DAY(EOMONTH('Loan maths'!$V$2,0)))*(LM_anchor>DAY(EOMONTH('Loan maths'!$V$2,0))))))/(LM_step+(LM_step=0)))+1)>LM_cycles))+LM_stub*('Loan maths'!$V$2>=LN_maturity))-LM_paid)-1)/LM_safe)+(LM_rate=0)*(LM_out-LM_annuity*((('Loan maths'!$V$2>=LM_first)*((INT(((YEAR('Loan maths'!$V$2)-YEAR(LM_first))*12+MONTH('Loan maths'!$V$2)-MONTH(LM_first)-(DAY('Loan maths'!$V$2)<(LM_anchor-(LM_anchor-DAY(EOMONTH('Loan maths'!$V$2,0)))*(LM_anchor>DAY(EOMONTH('Loan maths'!$V$2,0))))))/(LM_step+(LM_step=0)))+1)+(LM_cycles-(INT(((YEAR('Loan maths'!$V$2)-YEAR(LM_first))*12+MONTH('Loan maths'!$V$2)-MONTH(LM_first)-(DAY('Loan maths'!$V$2)<(LM_anchor-(LM_anchor-DAY(EOMONTH('Loan maths'!$V$2,0)))*(LM_anchor>DAY(EOMONTH('Loan maths'!$V$2,0))))))/(LM_step+(LM_step=0)))+1))*((INT(((YEAR('Loan maths'!$V$2)-YEAR(LM_first))*12+MONTH('Loan maths'!$V$2)-MONTH(LM_first)-(DAY('Loan maths'!$V$2)<(LM_anchor-(LM_anchor-DAY(EOMONTH('Loan maths'!$V$2,0)))*(LM_anchor>DAY(EOMONTH('Loan maths'!$V$2,0))))))/(LM_step+(LM_step=0)))+1)>LM_cycles))+LM_stub*('Loan maths'!$V$2>=LN_maturity))-LM_paid)))))+SUMPRODUCT(LM_live*((LM_profile<>"EIP")*(LM_profile<>"Annuity"))*(LM_end>'Loan maths'!$U$2)*(LM_end<='Loan maths'!$V$2)*LN_principal) -> 0 | D54: =IFERROR(C54/C$62,0) -> 0
B55: 2 to 5 years | C55: =SUMPRODUCT(LM_live*(LM_profile="EIP")*LM_eip*((('Loan maths'!$W$2>=LM_first)*((INT(((YEAR('Loan maths'!$W$2)-YEAR(LM_first))*12+MONTH('Loan maths'!$W$2)-MONTH(LM_first)-(DAY('Loan maths'!$W$2)<(LM_anchor-(LM_anchor-DAY(EOMONTH('Loan maths'!$W$2,0)))*(LM_anchor>DAY(EOMONTH('Loan maths'!$W$2,0))))))/(LM_step+(LM_step=0)))+1)+(LM_cycles-(INT(((YEAR('Loan maths'!$W$2)-YEAR(LM_first))*12+MONTH('Loan maths'!$W$2)-MONTH(LM_first)-(DAY('Loan maths'!$W$2)<(LM_anchor-(LM_anchor-DAY(EOMONTH('Loan maths'!$W$2,0)))*(LM_anchor>DAY(EOMONTH('Loan maths'!$W$2,0))))))/(LM_step+(LM_step=0)))+1))*((INT(((YEAR('Loan maths'!$W$2)-YEAR(LM_first))*12+MONTH('Loan maths'!$W$2)-MONTH(LM_first)-(DAY('Loan maths'!$W$2)<(LM_anchor-(LM_anchor-DAY(EOMONTH('Loan maths'!$W$2,0)))*(LM_anchor>DAY(EOMONTH('Loan maths'!$W$2,0))))))/(LM_step+(LM_step=0)))+1)>LM_cycles))+LM_stub*('Loan maths'!$W$2>=LN_maturity))-(('Loan maths'!$V$2>=LM_first)*((INT(((YEAR('Loan maths'!$V$2)-YEAR(LM_first))*12+MONTH('Loan maths'!$V$2)-MONTH(LM_first)-(DAY('Loan maths'!$V$2)<(LM_anchor-(LM_anchor-DAY(EOMONTH('Loan maths'!$V$2,0)))*(LM_anchor>DAY(EOMONTH('Loan maths'!$V$2,0))))))/(LM_step+(LM_step=0)))+1)+(LM_cycles-(INT(((YEAR('Loan maths'!$V$2)-YEAR(LM_first))*12+MONTH('Loan maths'!$V$2)-MONTH(LM_first)-(DAY('Loan maths'!$V$2)<(LM_anchor-(LM_anchor-DAY(EOMONTH('Loan maths'!$V$2,0)))*(LM_anchor>DAY(EOMONTH('Loan maths'!$V$2,0))))))/(LM_step+(LM_step=0)))+1))*((INT(((YEAR('Loan maths'!$V$2)-YEAR(LM_first))*12+MONTH('Loan maths'!$V$2)-MONTH(LM_first)-(DAY('Loan maths'!$V$2)<(LM_anchor-(LM_anchor-DAY(EOMONTH('Loan maths'!$V$2,0)))*(LM_anchor>DAY(EOMONTH('Loan maths'!$V$2,0))))))/(LM_step+(LM_step=0)))+1)>LM_cycles))+LM_stub*('Loan maths'!$V$2>=LN_maturity))))+SUMPRODUCT(LM_live*(LM_profile="Annuity")*(((LM_rate>0)*(LM_out*(1+LM_rate)^((('Loan maths'!$V$2>=LM_first)*((INT(((YEAR('Loan maths'!$V$2)-YEAR(LM_first))*12+MONTH('Loan maths'!$V$2)-MONTH(LM_first)-(DAY('Loan maths'!$V$2)<(LM_anchor-(LM_anchor-DAY(EOMONTH('Loan maths'!$V$2,0)))*(LM_anchor>DAY(EOMONTH('Loan maths'!$V$2,0))))))/(LM_step+(LM_step=0)))+1)+(LM_cycles-(INT(((YEAR('Loan maths'!$V$2)-YEAR(LM_first))*12+MONTH('Loan maths'!$V$2)-MONTH(LM_first)-(DAY('Loan maths'!$V$2)<(LM_anchor-(LM_anchor-DAY(EOMONTH('Loan maths'!$V$2,0)))*(LM_anchor>DAY(EOMONTH('Loan maths'!$V$2,0))))))/(LM_step+(LM_step=0)))+1))*((INT(((YEAR('Loan maths'!$V$2)-YEAR(LM_first))*12+MONTH('Loan maths'!$V$2)-MONTH(LM_first)-(DAY('Loan maths'!$V$2)<(LM_anchor-(LM_anchor-DAY(EOMONTH('Loan maths'!$V$2,0)))*(LM_anchor>DAY(EOMONTH('Loan maths'!$V$2,0))))))/(LM_step+(LM_step=0)))+1)>LM_cycles))+LM_stub*('Loan maths'!$V$2>=LN_maturity))-LM_paid)-LM_annuity*((1+LM_rate)^((('Loan maths'!$V$2>=LM_first)*((INT(((YEAR('Loan maths'!$V$2)-YEAR(LM_first))*12+MONTH('Loan maths'!$V$2)-MONTH(LM_first)-(DAY('Loan maths'!$V$2)<(LM_anchor-(LM_anchor-DAY(EOMONTH('Loan maths'!$V$2,0)))*(LM_anchor>DAY(EOMONTH('Loan maths'!$V$2,0))))))/(LM_step+(LM_step=0)))+1)+(LM_cycles-(INT(((YEAR('Loan maths'!$V$2)-YEAR(LM_first))*12+MONTH('Loan maths'!$V$2)-MONTH(LM_first)-(DAY('Loan maths'!$V$2)<(LM_anchor-(LM_anchor-DAY(EOMONTH('Loan maths'!$V$2,0)))*(LM_anchor>DAY(EOMONTH('Loan maths'!$V$2,0))))))/(LM_step+(LM_step=0)))+1))*((INT(((YEAR('Loan maths'!$V$2)-YEAR(LM_first))*12+MONTH('Loan maths'!$V$2)-MONTH(LM_first)-(DAY('Loan maths'!$V$2)<(LM_anchor-(LM_anchor-DAY(EOMONTH('Loan maths'!$V$2,0)))*(LM_anchor>DAY(EOMONTH('Loan maths'!$V$2,0))))))/(LM_step+(LM_step=0)))+1)>LM_cycles))+LM_stub*('Loan maths'!$V$2>=LN_maturity))-LM_paid)-1)/LM_safe)+(LM_rate=0)*(LM_out-LM_annuity*((('Loan maths'!$V$2>=LM_first)*((INT(((YEAR('Loan maths'!$V$2)-YEAR(LM_first))*12+MONTH('Loan maths'!$V$2)-MONTH(LM_first)-(DAY('Loan maths'!$V$2)<(LM_anchor-(LM_anchor-DAY(EOMONTH('Loan maths'!$V$2,0)))*(LM_anchor>DAY(EOMONTH('Loan maths'!$V$2,0))))))/(LM_step+(LM_step=0)))+1)+(LM_cycles-(INT(((YEAR('Loan maths'!$V$2)-YEAR(LM_first))*12+MONTH('Loan maths'!$V$2)-MONTH(LM_first)-(DAY('Loan maths'!$V$2)<(LM_anchor-(LM_anchor-DAY(EOMONTH('Loan maths'!$V$2,0)))*(LM_anchor>DAY(EOMONTH('Loan maths'!$V$2,0))))))/(LM_step+(LM_step=0)))+1))*((INT(((YEAR('Loan maths'!$V$2)-YEAR(LM_first))*12+MONTH('Loan maths'!$V$2)-MONTH(LM_first)-(DAY('Loan maths'!$V$2)<(LM_anchor-(LM_anchor-DAY(EOMONTH('Loan maths'!$V$2,0)))*(LM_anchor>DAY(EOMONTH('Loan maths'!$V$2,0))))))/(LM_step+(LM_step=0)))+1)>LM_cycles))+LM_stub*('Loan maths'!$V$2>=LN_maturity))-LM_paid)))-((LM_rate>0)*(LM_out*(1+LM_rate)^((('Loan maths'!$W$2>=LM_first)*((INT(((YEAR('Loan maths'!$W$2)-YEAR(LM_first))*12+MONTH('Loan maths'!$W$2)-MONTH(LM_first)-(DAY('Loan maths'!$W$2)<(LM_anchor-(LM_anchor-DAY(EOMONTH('Loan maths'!$W$2,0)))*(LM_anchor>DAY(EOMONTH('Loan maths'!$W$2,0))))))/(LM_step+(LM_step=0)))+1)+(LM_cycles-(INT(((YEAR('Loan maths'!$W$2)-YEAR(LM_first))*12+MONTH('Loan maths'!$W$2)-MONTH(LM_first)-(DAY('Loan maths'!$W$2)<(LM_anchor-(LM_anchor-DAY(EOMONTH('Loan maths'!$W$2,0)))*(LM_anchor>DAY(EOMONTH('Loan maths'!$W$2,0))))))/(LM_step+(LM_step=0)))+1))*((INT(((YEAR('Loan maths'!$W$2)-YEAR(LM_first))*12+MONTH('Loan maths'!$W$2)-MONTH(LM_first)-(DAY('Loan maths'!$W$2)<(LM_anchor-(LM_anchor-DAY(EOMONTH('Loan maths'!$W$2,0)))*(LM_anchor>DAY(EOMONTH('Loan maths'!$W$2,0))))))/(LM_step+(LM_step=0)))+1)>LM_cycles))+LM_stub*('Loan maths'!$W$2>=LN_maturity))-LM_paid)-LM_annuity*((1+LM_rate)^((('Loan maths'!$W$2>=LM_first)*((INT(((YEAR('Loan maths'!$W$2)-YEAR(LM_first))*12+MONTH('Loan maths'!$W$2)-MONTH(LM_first)-(DAY('Loan maths'!$W$2)<(LM_anchor-(LM_anchor-DAY(EOMONTH('Loan maths'!$W$2,0)))*(LM_anchor>DAY(EOMONTH('Loan maths'!$W$2,0))))))/(LM_step+(LM_step=0)))+1)+(LM_cycles-(INT(((YEAR('Loan maths'!$W$2)-YEAR(LM_first))*12+MONTH('Loan maths'!$W$2)-MONTH(LM_first)-(DAY('Loan maths'!$W$2)<(LM_anchor-(LM_anchor-DAY(EOMONTH('Loan maths'!$W$2,0)))*(LM_anchor>DAY(EOMONTH('Loan maths'!$W$2,0))))))/(LM_step+(LM_step=0)))+1))*((INT(((YEAR('Loan maths'!$W$2)-YEAR(LM_first))*12+MONTH('Loan maths'!$W$2)-MONTH(LM_first)-(DAY('Loan maths'!$W$2)<(LM_anchor-(LM_anchor-DAY(EOMONTH('Loan maths'!$W$2,0)))*(LM_anchor>DAY(EOMONTH('Loan maths'!$W$2,0))))))/(LM_step+(LM_step=0)))+1)>LM_cycles))+LM_stub*('Loan maths'!$W$2>=LN_maturity))-LM_paid)-1)/LM_safe)+(LM_rate=0)*(LM_out-LM_annuity*((('Loan maths'!$W$2>=LM_first)*((INT(((YEAR('Loan maths'!$W$2)-YEAR(LM_first))*12+MONTH('Loan maths'!$W$2)-MONTH(LM_first)-(DAY('Loan maths'!$W$2)<(LM_anchor-(LM_anchor-DAY(EOMONTH('Loan maths'!$W$2,0)))*(LM_anchor>DAY(EOMONTH('Loan maths'!$W$2,0))))))/(LM_step+(LM_step=0)))+1)+(LM_cycles-(INT(((YEAR('Loan maths'!$W$2)-YEAR(LM_first))*12+MONTH('Loan maths'!$W$2)-MONTH(LM_first)-(DAY('Loan maths'!$W$2)<(LM_anchor-(LM_anchor-DAY(EOMONTH('Loan maths'!$W$2,0)))*(LM_anchor>DAY(EOMONTH('Loan maths'!$W$2,0))))))/(LM_step+(LM_step=0)))+1))*((INT(((YEAR('Loan maths'!$W$2)-YEAR(LM_first))*12+MONTH('Loan maths'!$W$2)-MONTH(LM_first)-(DAY('Loan maths'!$W$2)<(LM_anchor-(LM_anchor-DAY(EOMONTH('Loan maths'!$W$2,0)))*(LM_anchor>DAY(EOMONTH('Loan maths'!$W$2,0))))))/(LM_step+(LM_step=0)))+1)>LM_cycles))+LM_stub*('Loan maths'!$W$2>=LN_maturity))-LM_paid)))))+SUMPRODUCT(LM_live*((LM_profile<>"EIP")*(LM_profile<>"Annuity"))*(LM_end>'Loan maths'!$V$2)*(LM_end<='Loan maths'!$W$2)*LN_principal) -> 0 | D55: =IFERROR(C55/C$62,0) -> 0
B56: 5 to 10 years | C56: =SUMPRODUCT(LM_live*(LM_profile="EIP")*LM_eip*((('Loan maths'!$X$2>=LM_first)*((INT(((YEAR('Loan maths'!$X$2)-YEAR(LM_first))*12+MONTH('Loan maths'!$X$2)-MONTH(LM_first)-(DAY('Loan maths'!$X$2)<(LM_anchor-(LM_anchor-DAY(EOMONTH('Loan maths'!$X$2,0)))*(LM_anchor>DAY(EOMONTH('Loan maths'!$X$2,0))))))/(LM_step+(LM_step=0)))+1)+(LM_cycles-(INT(((YEAR('Loan maths'!$X$2)-YEAR(LM_first))*12+MONTH('Loan maths'!$X$2)-MONTH(LM_first)-(DAY('Loan maths'!$X$2)<(LM_anchor-(LM_anchor-DAY(EOMONTH('Loan maths'!$X$2,0)))*(LM_anchor>DAY(EOMONTH('Loan maths'!$X$2,0))))))/(LM_step+(LM_step=0)))+1))*((INT(((YEAR('Loan maths'!$X$2)-YEAR(LM_first))*12+MONTH('Loan maths'!$X$2)-MONTH(LM_first)-(DAY('Loan maths'!$X$2)<(LM_anchor-(LM_anchor-DAY(EOMONTH('Loan maths'!$X$2,0)))*(LM_anchor>DAY(EOMONTH('Loan maths'!$X$2,0))))))/(LM_step+(LM_step=0)))+1)>LM_cycles))+LM_stub*('Loan maths'!$X$2>=LN_maturity))-(('Loan maths'!$W$2>=LM_first)*((INT(((YEAR('Loan maths'!$W$2)-YEAR(LM_first))*12+MONTH('Loan maths'!$W$2)-MONTH(LM_first)-(DAY('Loan maths'!$W$2)<(LM_anchor-(LM_anchor-DAY(EOMONTH('Loan maths'!$W$2,0)))*(LM_anchor>DAY(EOMONTH('Loan maths'!$W$2,0))))))/(LM_step+(LM_step=0)))+1)+(LM_cycles-(INT(((YEAR('Loan maths'!$W$2)-YEAR(LM_first))*12+MONTH('Loan maths'!$W$2)-MONTH(LM_first)-(DAY('Loan maths'!$W$2)<(LM_anchor-(LM_anchor-DAY(EOMONTH('Loan maths'!$W$2,0)))*(LM_anchor>DAY(EOMONTH('Loan maths'!$W$2,0))))))/(LM_step+(LM_step=0)))+1))*((INT(((YEAR('Loan maths'!$W$2)-YEAR(LM_first))*12+MONTH('Loan maths'!$W$2)-MONTH(LM_first)-(DAY('Loan maths'!$W$2)<(LM_anchor-(LM_anchor-DAY(EOMONTH('Loan maths'!$W$2,0)))*(LM_anchor>DAY(EOMONTH('Loan maths'!$W$2,0))))))/(LM_step+(LM_step=0)))+1)>LM_cycles))+LM_stub*('Loan maths'!$W$2>=LN_maturity))))+SUMPRODUCT(LM_live*(LM_profile="Annuity")*(((LM_rate>0)*(LM_out*(1+LM_rate)^((('Loan maths'!$W$2>=LM_first)*((INT(((YEAR('Loan maths'!$W$2)-YEAR(LM_first))*12+MONTH('Loan maths'!$W$2)-MONTH(LM_first)-(DAY('Loan maths'!$W$2)<(LM_anchor-(LM_anchor-DAY(EOMONTH('Loan maths'!$W$2,0)))*(LM_anchor>DAY(EOMONTH('Loan maths'!$W$2,0))))))/(LM_step+(LM_step=0)))+1)+(LM_cycles-(INT(((YEAR('Loan maths'!$W$2)-YEAR(LM_first))*12+MONTH('Loan maths'!$W$2)-MONTH(LM_first)-(DAY('Loan maths'!$W$2)<(LM_anchor-(LM_anchor-DAY(EOMONTH('Loan maths'!$W$2,0)))*(LM_anchor>DAY(EOMONTH('Loan maths'!$W$2,0))))))/(LM_step+(LM_step=0)))+1))*((INT(((YEAR('Loan maths'!$W$2)-YEAR(LM_first))*12+MONTH('Loan maths'!$W$2)-MONTH(LM_first)-(DAY('Loan maths'!$W$2)<(LM_anchor-(LM_anchor-DAY(EOMONTH('Loan maths'!$W$2,0)))*(LM_anchor>DAY(EOMONTH('Loan maths'!$W$2,0))))))/(LM_step+(LM_step=0)))+1)>LM_cycles))+LM_stub*('Loan maths'!$W$2>=LN_maturity))-LM_paid)-LM_annuity*((1+LM_rate)^((('Loan maths'!$W$2>=LM_first)*((INT(((YEAR('Loan maths'!$W$2)-YEAR(LM_first))*12+MONTH('Loan maths'!$W$2)-MONTH(LM_first)-(DAY('Loan maths'!$W$2)<(LM_anchor-(LM_anchor-DAY(EOMONTH('Loan maths'!$W$2,0)))*(LM_anchor>DAY(EOMONTH('Loan maths'!$W$2,0))))))/(LM_step+(LM_step=0)))+1)+(LM_cycles-(INT(((YEAR('Loan maths'!$W$2)-YEAR(LM_first))*12+MONTH('Loan maths'!$W$2)-MONTH(LM_first)-(DAY('Loan maths'!$W$2)<(LM_anchor-(LM_anchor-DAY(EOMONTH('Loan maths'!$W$2,0)))*(LM_anchor>DAY(EOMONTH('Loan maths'!$W$2,0))))))/(LM_step+(LM_step=0)))+1))*((INT(((YEAR('Loan maths'!$W$2)-YEAR(LM_first))*12+MONTH('Loan maths'!$W$2)-MONTH(LM_first)-(DAY('Loan maths'!$W$2)<(LM_anchor-(LM_anchor-DAY(EOMONTH('Loan maths'!$W$2,0)))*(LM_anchor>DAY(EOMONTH('Loan maths'!$W$2,0))))))/(LM_step+(LM_step=0)))+1)>LM_cycles))+LM_stub*('Loan maths'!$W$2>=LN_maturity))-LM_paid)-1)/LM_safe)+(LM_rate=0)*(LM_out-LM_annuity*((('Loan maths'!$W$2>=LM_first)*((INT(((YEAR('Loan maths'!$W$2)-YEAR(LM_first))*12+MONTH('Loan maths'!$W$2)-MONTH(LM_first)-(DAY('Loan maths'!$W$2)<(LM_anchor-(LM_anchor-DAY(EOMONTH('Loan maths'!$W$2,0)))*(LM_anchor>DAY(EOMONTH('Loan maths'!$W$2,0))))))/(LM_step+(LM_step=0)))+1)+(LM_cycles-(INT(((YEAR('Loan maths'!$W$2)-YEAR(LM_first))*12+MONTH('Loan maths'!$W$2)-MONTH(LM_first)-(DAY('Loan maths'!$W$2)<(LM_anchor-(LM_anchor-DAY(EOMONTH('Loan maths'!$W$2,0)))*(LM_anchor>DAY(EOMONTH('Loan maths'!$W$2,0))))))/(LM_step+(LM_step=0)))+1))*((INT(((YEAR('Loan maths'!$W$2)-YEAR(LM_first))*12+MONTH('Loan maths'!$W$2)-MONTH(LM_first)-(DAY('Loan maths'!$W$2)<(LM_anchor-(LM_anchor-DAY(EOMONTH('Loan maths'!$W$2,0)))*(LM_anchor>DAY(EOMONTH('Loan maths'!$W$2,0))))))/(LM_step+(LM_step=0)))+1)>LM_cycles))+LM_stub*('Loan maths'!$W$2>=LN_maturity))-LM_paid)))-((LM_rate>0)*(LM_out*(1+LM_rate)^((('Loan maths'!$X$2>=LM_first)*((INT(((YEAR('Loan maths'!$X$2)-YEAR(LM_first))*12+MONTH('Loan maths'!$X$2)-MONTH(LM_first)-(DAY('Loan maths'!$X$2)<(LM_anchor-(LM_anchor-DAY(EOMONTH('Loan maths'!$X$2,0)))*(LM_anchor>DAY(EOMONTH('Loan maths'!$X$2,0))))))/(LM_step+(LM_step=0)))+1)+(LM_cycles-(INT(((YEAR('Loan maths'!$X$2)-YEAR(LM_first))*12+MONTH('Loan maths'!$X$2)-MONTH(LM_first)-(DAY('Loan maths'!$X$2)<(LM_anchor-(LM_anchor-DAY(EOMONTH('Loan maths'!$X$2,0)))*(LM_anchor>DAY(EOMONTH('Loan maths'!$X$2,0))))))/(LM_step+(LM_step=0)))+1))*((INT(((YEAR('Loan maths'!$X$2)-YEAR(LM_first))*12+MONTH('Loan maths'!$X$2)-MONTH(LM_first)-(DAY('Loan maths'!$X$2)<(LM_anchor-(LM_anchor-DAY(EOMONTH('Loan maths'!$X$2,0)))*(LM_anchor>DAY(EOMONTH('Loan maths'!$X$2,0))))))/(LM_step+(LM_step=0)))+1)>LM_cycles))+LM_stub*('Loan maths'!$X$2>=LN_maturity))-LM_paid)-LM_annuity*((1+LM_rate)^((('Loan maths'!$X$2>=LM_first)*((INT(((YEAR('Loan maths'!$X$2)-YEAR(LM_first))*12+MONTH('Loan maths'!$X$2)-MONTH(LM_first)-(DAY('Loan maths'!$X$2)<(LM_anchor-(LM_anchor-DAY(EOMONTH('Loan maths'!$X$2,0)))*(LM_anchor>DAY(EOMONTH('Loan maths'!$X$2,0))))))/(LM_step+(LM_step=0)))+1)+(LM_cycles-(INT(((YEAR('Loan maths'!$X$2)-YEAR(LM_first))*12+MONTH('Loan maths'!$X$2)-MONTH(LM_first)-(DAY('Loan maths'!$X$2)<(LM_anchor-(LM_anchor-DAY(EOMONTH('Loan maths'!$X$2,0)))*(LM_anchor>DAY(EOMONTH('Loan maths'!$X$2,0))))))/(LM_step+(LM_step=0)))+1))*((INT(((YEAR('Loan maths'!$X$2)-YEAR(LM_first))*12+MONTH('Loan maths'!$X$2)-MONTH(LM_first)-(DAY('Loan maths'!$X$2)<(LM_anchor-(LM_anchor-DAY(EOMONTH('Loan maths'!$X$2,0)))*(LM_anchor>DAY(EOMONTH('Loan maths'!$X$2,0))))))/(LM_step+(LM_step=0)))+1)>LM_cycles))+LM_stub*('Loan maths'!$X$2>=LN_maturity))-LM_paid)-1)/LM_safe)+(LM_rate=0)*(LM_out-LM_annuity*((('Loan maths'!$X$2>=LM_first)*((INT(((YEAR('Loan maths'!$X$2)-YEAR(LM_first))*12+MONTH('Loan maths'!$X$2)-MONTH(LM_first)-(DAY('Loan maths'!$X$2)<(LM_anchor-(LM_anchor-DAY(EOMONTH('Loan maths'!$X$2,0)))*(LM_anchor>DAY(EOMONTH('Loan maths'!$X$2,0))))))/(LM_step+(LM_step=0)))+1)+(LM_cycles-(INT(((YEAR('Loan maths'!$X$2)-YEAR(LM_first))*12+MONTH('Loan maths'!$X$2)-MONTH(LM_first)-(DAY('Loan maths'!$X$2)<(LM_anchor-(LM_anchor-DAY(EOMONTH('Loan maths'!$X$2,0)))*(LM_anchor>DAY(EOMONTH('Loan maths'!$X$2,0))))))/(LM_step+(LM_step=0)))+1))*((INT(((YEAR('Loan maths'!$X$2)-YEAR(LM_first))*12+MONTH('Loan maths'!$X$2)-MONTH(LM_first)-(DAY('Loan maths'!$X$2)<(LM_anchor-(LM_anchor-DAY(EOMONTH('Loan maths'!$X$2,0)))*(LM_anchor>DAY(EOMONTH('Loan maths'!$X$2,0))))))/(LM_step+(LM_step=0)))+1)>LM_cycles))+LM_stub*('Loan maths'!$X$2>=LN_maturity))-LM_paid)))))+SUMPRODUCT(LM_live*((LM_profile<>"EIP")*(LM_profile<>"Annuity"))*(LM_end>'Loan maths'!$W$2)*(LM_end<='Loan maths'!$X$2)*LN_principal) -> 0 | D56: =IFERROR(C56/C$62,0) -> 0
B57: 10 to 20 years | C57: =SUMPRODUCT(LM_live*(LM_profile="EIP")*LM_eip*((('Loan maths'!$Y$2>=LM_first)*((INT(((YEAR('Loan maths'!$Y$2)-YEAR(LM_first))*12+MONTH('Loan maths'!$Y$2)-MONTH(LM_first)-(DAY('Loan maths'!$Y$2)<(LM_anchor-(LM_anchor-DAY(EOMONTH('Loan maths'!$Y$2,0)))*(LM_anchor>DAY(EOMONTH('Loan maths'!$Y$2,0))))))/(LM_step+(LM_step=0)))+1)+(LM_cycles-(INT(((YEAR('Loan maths'!$Y$2)-YEAR(LM_first))*12+MONTH('Loan maths'!$Y$2)-MONTH(LM_first)-(DAY('Loan maths'!$Y$2)<(LM_anchor-(LM_anchor-DAY(EOMONTH('Loan maths'!$Y$2,0)))*(LM_anchor>DAY(EOMONTH('Loan maths'!$Y$2,0))))))/(LM_step+(LM_step=0)))+1))*((INT(((YEAR('Loan maths'!$Y$2)-YEAR(LM_first))*12+MONTH('Loan maths'!$Y$2)-MONTH(LM_first)-(DAY('Loan maths'!$Y$2)<(LM_anchor-(LM_anchor-DAY(EOMONTH('Loan maths'!$Y$2,0)))*(LM_anchor>DAY(EOMONTH('Loan maths'!$Y$2,0))))))/(LM_step+(LM_step=0)))+1)>LM_cycles))+LM_stub*('Loan maths'!$Y$2>=LN_maturity))-(('Loan maths'!$X$2>=LM_first)*((INT(((YEAR('Loan maths'!$X$2)-YEAR(LM_first))*12+MONTH('Loan maths'!$X$2)-MONTH(LM_first)-(DAY('Loan maths'!$X$2)<(LM_anchor-(LM_anchor-DAY(EOMONTH('Loan maths'!$X$2,0)))*(LM_anchor>DAY(EOMONTH('Loan maths'!$X$2,0))))))/(LM_step+(LM_step=0)))+1)+(LM_cycles-(INT(((YEAR('Loan maths'!$X$2)-YEAR(LM_first))*12+MONTH('Loan maths'!$X$2)-MONTH(LM_first)-(DAY('Loan maths'!$X$2)<(LM_anchor-(LM_anchor-DAY(EOMONTH('Loan maths'!$X$2,0)))*(LM_anchor>DAY(EOMONTH('Loan maths'!$X$2,0))))))/(LM_step+(LM_step=0)))+1))*((INT(((YEAR('Loan maths'!$X$2)-YEAR(LM_first))*12+MONTH('Loan maths'!$X$2)-MONTH(LM_first)-(DAY('Loan maths'!$X$2)<(LM_anchor-(LM_anchor-DAY(EOMONTH('Loan maths'!$X$2,0)))*(LM_anchor>DAY(EOMONTH('Loan maths'!$X$2,0))))))/(LM_step+(LM_step=0)))+1)>LM_cycles))+LM_stub*('Loan maths'!$X$2>=LN_maturity))))+SUMPRODUCT(LM_live*(LM_profile="Annuity")*(((LM_rate>0)*(LM_out*(1+LM_rate)^((('Loan maths'!$X$2>=LM_first)*((INT(((YEAR('Loan maths'!$X$2)-YEAR(LM_first))*12+MONTH('Loan maths'!$X$2)-MONTH(LM_first)-(DAY('Loan maths'!$X$2)<(LM_anchor-(LM_anchor-DAY(EOMONTH('Loan maths'!$X$2,0)))*(LM_anchor>DAY(EOMONTH('Loan maths'!$X$2,0))))))/(LM_step+(LM_step=0)))+1)+(LM_cycles-(INT(((YEAR('Loan maths'!$X$2)-YEAR(LM_first))*12+MONTH('Loan maths'!$X$2)-MONTH(LM_first)-(DAY('Loan maths'!$X$2)<(LM_anchor-(LM_anchor-DAY(EOMONTH('Loan maths'!$X$2,0)))*(LM_anchor>DAY(EOMONTH('Loan maths'!$X$2,0))))))/(LM_step+(LM_step=0)))+1))*((INT(((YEAR('Loan maths'!$X$2)-YEAR(LM_first))*12+MONTH('Loan maths'!$X$2)-MONTH(LM_first)-(DAY('Loan maths'!$X$2)<(LM_anchor-(LM_anchor-DAY(EOMONTH('Loan maths'!$X$2,0)))*(LM_anchor>DAY(EOMONTH('Loan maths'!$X$2,0))))))/(LM_step+(LM_step=0)))+1)>LM_cycles))+LM_stub*('Loan maths'!$X$2>=LN_maturity))-LM_paid)-LM_annuity*((1+LM_rate)^((('Loan maths'!$X$2>=LM_first)*((INT(((YEAR('Loan maths'!$X$2)-YEAR(LM_first))*12+MONTH('Loan maths'!$X$2)-MONTH(LM_first)-(DAY('Loan maths'!$X$2)<(LM_anchor-(LM_anchor-DAY(EOMONTH('Loan maths'!$X$2,0)))*(LM_anchor>DAY(EOMONTH('Loan maths'!$X$2,0))))))/(LM_step+(LM_step=0)))+1)+(LM_cycles-(INT(((YEAR('Loan maths'!$X$2)-YEAR(LM_first))*12+MONTH('Loan maths'!$X$2)-MONTH(LM_first)-(DAY('Loan maths'!$X$2)<(LM_anchor-(LM_anchor-DAY(EOMONTH('Loan maths'!$X$2,0)))*(LM_anchor>DAY(EOMONTH('Loan maths'!$X$2,0))))))/(LM_step+(LM_step=0)))+1))*((INT(((YEAR('Loan maths'!$X$2)-YEAR(LM_first))*12+MONTH('Loan maths'!$X$2)-MONTH(LM_first)-(DAY('Loan maths'!$X$2)<(LM_anchor-(LM_anchor-DAY(EOMONTH('Loan maths'!$X$2,0)))*(LM_anchor>DAY(EOMONTH('Loan maths'!$X$2,0))))))/(LM_step+(LM_step=0)))+1)>LM_cycles))+LM_stub*('Loan maths'!$X$2>=LN_maturity))-LM_paid)-1)/LM_safe)+(LM_rate=0)*(LM_out-LM_annuity*((('Loan maths'!$X$2>=LM_first)*((INT(((YEAR('Loan maths'!$X$2)-YEAR(LM_first))*12+MONTH('Loan maths'!$X$2)-MONTH(LM_first)-(DAY('Loan maths'!$X$2)<(LM_anchor-(LM_anchor-DAY(EOMONTH('Loan maths'!$X$2,0)))*(LM_anchor>DAY(EOMONTH('Loan maths'!$X$2,0))))))/(LM_step+(LM_step=0)))+1)+(LM_cycles-(INT(((YEAR('Loan maths'!$X$2)-YEAR(LM_first))*12+MONTH('Loan maths'!$X$2)-MONTH(LM_first)-(DAY('Loan maths'!$X$2)<(LM_anchor-(LM_anchor-DAY(EOMONTH('Loan maths'!$X$2,0)))*(LM_anchor>DAY(EOMONTH('Loan maths'!$X$2,0))))))/(LM_step+(LM_step=0)))+1))*((INT(((YEAR('Loan maths'!$X$2)-YEAR(LM_first))*12+MONTH('Loan maths'!$X$2)-MONTH(LM_first)-(DAY('Loan maths'!$X$2)<(LM_anchor-(LM_anchor-DAY(EOMONTH('Loan maths'!$X$2,0)))*(LM_anchor>DAY(EOMONTH('Loan maths'!$X$2,0))))))/(LM_step+(LM_step=0)))+1)>LM_cycles))+LM_stub*('Loan maths'!$X$2>=LN_maturity))-LM_paid)))-((LM_rate>0)*(LM_out*(1+LM_rate)^((('Loan maths'!$Y$2>=LM_first)*((INT(((YEAR('Loan maths'!$Y$2)-YEAR(LM_first))*12+MONTH('Loan maths'!$Y$2)-MONTH(LM_first)-(DAY('Loan maths'!$Y$2)<(LM_anchor-(LM_anchor-DAY(EOMONTH('Loan maths'!$Y$2,0)))*(LM_anchor>DAY(EOMONTH('Loan maths'!$Y$2,0))))))/(LM_step+(LM_step=0)))+1)+(LM_cycles-(INT(((YEAR('Loan maths'!$Y$2)-YEAR(LM_first))*12+MONTH('Loan maths'!$Y$2)-MONTH(LM_first)-(DAY('Loan maths'!$Y$2)<(LM_anchor-(LM_anchor-DAY(EOMONTH('Loan maths'!$Y$2,0)))*(LM_anchor>DAY(EOMONTH('Loan maths'!$Y$2,0))))))/(LM_step+(LM_step=0)))+1))*((INT(((YEAR('Loan maths'!$Y$2)-YEAR(LM_first))*12+MONTH('Loan maths'!$Y$2)-MONTH(LM_first)-(DAY('Loan maths'!$Y$2)<(LM_anchor-(LM_anchor-DAY(EOMONTH('Loan maths'!$Y$2,0)))*(LM_anchor>DAY(EOMONTH('Loan maths'!$Y$2,0))))))/(LM_step+(LM_step=0)))+1)>LM_cycles))+LM_stub*('Loan maths'!$Y$2>=LN_maturity))-LM_paid)-LM_annuity*((1+LM_rate)^((('Loan maths'!$Y$2>=LM_first)*((INT(((YEAR('Loan maths'!$Y$2)-YEAR(LM_first))*12+MONTH('Loan maths'!$Y$2)-MONTH(LM_first)-(DAY('Loan maths'!$Y$2)<(LM_anchor-(LM_anchor-DAY(EOMONTH('Loan maths'!$Y$2,0)))*(LM_anchor>DAY(EOMONTH('Loan maths'!$Y$2,0))))))/(LM_step+(LM_step=0)))+1)+(LM_cycles-(INT(((YEAR('Loan maths'!$Y$2)-YEAR(LM_first))*12+MONTH('Loan maths'!$Y$2)-MONTH(LM_first)-(DAY('Loan maths'!$Y$2)<(LM_anchor-(LM_anchor-DAY(EOMONTH('Loan maths'!$Y$2,0)))*(LM_anchor>DAY(EOMONTH('Loan maths'!$Y$2,0))))))/(LM_step+(LM_step=0)))+1))*((INT(((YEAR('Loan maths'!$Y$2)-YEAR(LM_first))*12+MONTH('Loan maths'!$Y$2)-MONTH(LM_first)-(DAY('Loan maths'!$Y$2)<(LM_anchor-(LM_anchor-DAY(EOMONTH('Loan maths'!$Y$2,0)))*(LM_anchor>DAY(EOMONTH('Loan maths'!$Y$2,0))))))/(LM_step+(LM_step=0)))+1)>LM_cycles))+LM_stub*('Loan maths'!$Y$2>=LN_maturity))-LM_paid)-1)/LM_safe)+(LM_rate=0)*(LM_out-LM_annuity*((('Loan maths'!$Y$2>=LM_first)*((INT(((YEAR('Loan maths'!$Y$2)-YEAR(LM_first))*12+MONTH('Loan maths'!$Y$2)-MONTH(LM_first)-(DAY('Loan maths'!$Y$2)<(LM_anchor-(LM_anchor-DAY(EOMONTH('Loan maths'!$Y$2,0)))*(LM_anchor>DAY(EOMONTH('Loan maths'!$Y$2,0))))))/(LM_step+(LM_step=0)))+1)+(LM_cycles-(INT(((YEAR('Loan maths'!$Y$2)-YEAR(LM_first))*12+MONTH('Loan maths'!$Y$2)-MONTH(LM_first)-(DAY('Loan maths'!$Y$2)<(LM_anchor-(LM_anchor-DAY(EOMONTH('Loan maths'!$Y$2,0)))*(LM_anchor>DAY(EOMONTH('Loan maths'!$Y$2,0))))))/(LM_step+(LM_step=0)))+1))*((INT(((YEAR('Loan maths'!$Y$2)-YEAR(LM_first))*12+MONTH('Loan maths'!$Y$2)-MONTH(LM_first)-(DAY('Loan maths'!$Y$2)<(LM_anchor-(LM_anchor-DAY(EOMONTH('Loan maths'!$Y$2,0)))*(LM_anchor>DAY(EOMONTH('Loan maths'!$Y$2,0))))))/(LM_step+(LM_step=0)))+1)>LM_cycles))+LM_stub*('Loan maths'!$Y$2>=LN_maturity))-LM_paid)))))+SUMPRODUCT(LM_live*((LM_profile<>"EIP")*(LM_profile<>"Annuity"))*(LM_end>'Loan maths'!$X$2)*(LM_end<='Loan maths'!$Y$2)*LN_principal) -> 0 | D57: =IFERROR(C57/C$62,0) -> 0
B58: 20 to 30 years | C58: =SUMPRODUCT(LM_live*(LM_profile="EIP")*LM_eip*((('Loan maths'!$Z$2>=LM_first)*((INT(((YEAR('Loan maths'!$Z$2)-YEAR(LM_first))*12+MONTH('Loan maths'!$Z$2)-MONTH(LM_first)-(DAY('Loan maths'!$Z$2)<(LM_anchor-(LM_anchor-DAY(EOMONTH('Loan maths'!$Z$2,0)))*(LM_anchor>DAY(EOMONTH('Loan maths'!$Z$2,0))))))/(LM_step+(LM_step=0)))+1)+(LM_cycles-(INT(((YEAR('Loan maths'!$Z$2)-YEAR(LM_first))*12+MONTH('Loan maths'!$Z$2)-MONTH(LM_first)-(DAY('Loan maths'!$Z$2)<(LM_anchor-(LM_anchor-DAY(EOMONTH('Loan maths'!$Z$2,0)))*(LM_anchor>DAY(EOMONTH('Loan maths'!$Z$2,0))))))/(LM_step+(LM_step=0)))+1))*((INT(((YEAR('Loan maths'!$Z$2)-YEAR(LM_first))*12+MONTH('Loan maths'!$Z$2)-MONTH(LM_first)-(DAY('Loan maths'!$Z$2)<(LM_anchor-(LM_anchor-DAY(EOMONTH('Loan maths'!$Z$2,0)))*(LM_anchor>DAY(EOMONTH('Loan maths'!$Z$2,0))))))/(LM_step+(LM_step=0)))+1)>LM_cycles))+LM_stub*('Loan maths'!$Z$2>=LN_maturity))-(('Loan maths'!$Y$2>=LM_first)*((INT(((YEAR('Loan maths'!$Y$2)-YEAR(LM_first))*12+MONTH('Loan maths'!$Y$2)-MONTH(LM_first)-(DAY('Loan maths'!$Y$2)<(LM_anchor-(LM_anchor-DAY(EOMONTH('Loan maths'!$Y$2,0)))*(LM_anchor>DAY(EOMONTH('Loan maths'!$Y$2,0))))))/(LM_step+(LM_step=0)))+1)+(LM_cycles-(INT(((YEAR('Loan maths'!$Y$2)-YEAR(LM_first))*12+MONTH('Loan maths'!$Y$2)-MONTH(LM_first)-(DAY('Loan maths'!$Y$2)<(LM_anchor-(LM_anchor-DAY(EOMONTH('Loan maths'!$Y$2,0)))*(LM_anchor>DAY(EOMONTH('Loan maths'!$Y$2,0))))))/(LM_step+(LM_step=0)))+1))*((INT(((YEAR('Loan maths'!$Y$2)-YEAR(LM_first))*12+MONTH('Loan maths'!$Y$2)-MONTH(LM_first)-(DAY('Loan maths'!$Y$2)<(LM_anchor-(LM_anchor-DAY(EOMONTH('Loan maths'!$Y$2,0)))*(LM_anchor>DAY(EOMONTH('Loan maths'!$Y$2,0))))))/(LM_step+(LM_step=0)))+1)>LM_cycles))+LM_stub*('Loan maths'!$Y$2>=LN_maturity))))+SUMPRODUCT(LM_live*(LM_profile="Annuity")*(((LM_rate>0)*(LM_out*(1+LM_rate)^((('Loan maths'!$Y$2>=LM_first)*((INT(((YEAR('Loan maths'!$Y$2)-YEAR(LM_first))*12+MONTH('Loan maths'!$Y$2)-MONTH(LM_first)-(DAY('Loan maths'!$Y$2)<(LM_anchor-(LM_anchor-DAY(EOMONTH('Loan maths'!$Y$2,0)))*(LM_anchor>DAY(EOMONTH('Loan maths'!$Y$2,0))))))/(LM_step+(LM_step=0)))+1)+(LM_cycles-(INT(((YEAR('Loan maths'!$Y$2)-YEAR(LM_first))*12+MONTH('Loan maths'!$Y$2)-MONTH(LM_first)-(DAY('Loan maths'!$Y$2)<(LM_anchor-(LM_anchor-DAY(EOMONTH('Loan maths'!$Y$2,0)))*(LM_anchor>DAY(EOMONTH('Loan maths'!$Y$2,0))))))/(LM_step+(LM_step=0)))+1))*((INT(((YEAR('Loan maths'!$Y$2)-YEAR(LM_first))*12+MONTH('Loan maths'!$Y$2)-MONTH(LM_first)-(DAY('Loan maths'!$Y$2)<(LM_anchor-(LM_anchor-DAY(EOMONTH('Loan maths'!$Y$2,0)))*(LM_anchor>DAY(EOMONTH('Loan maths'!$Y$2,0))))))/(LM_step+(LM_step=0)))+1)>LM_cycles))+LM_stub*('Loan maths'!$Y$2>=LN_maturity))-LM_paid)-LM_annuity*((1+LM_rate)^((('Loan maths'!$Y$2>=LM_first)*((INT(((YEAR('Loan maths'!$Y$2)-YEAR(LM_first))*12+MONTH('Loan maths'!$Y$2)-MONTH(LM_first)-(DAY('Loan maths'!$Y$2)<(LM_anchor-(LM_anchor-DAY(EOMONTH('Loan maths'!$Y$2,0)))*(LM_anchor>DAY(EOMONTH('Loan maths'!$Y$2,0))))))/(LM_step+(LM_step=0)))+1)+(LM_cycles-(INT(((YEAR('Loan maths'!$Y$2)-YEAR(LM_first))*12+MONTH('Loan maths'!$Y$2)-MONTH(LM_first)-(DAY('Loan maths'!$Y$2)<(LM_anchor-(LM_anchor-DAY(EOMONTH('Loan maths'!$Y$2,0)))*(LM_anchor>DAY(EOMONTH('Loan maths'!$Y$2,0))))))/(LM_step+(LM_step=0)))+1))*((INT(((YEAR('Loan maths'!$Y$2)-YEAR(LM_first))*12+MONTH('Loan maths'!$Y$2)-MONTH(LM_first)-(DAY('Loan maths'!$Y$2)<(LM_anchor-(LM_anchor-DAY(EOMONTH('Loan maths'!$Y$2,0)))*(LM_anchor>DAY(EOMONTH('Loan maths'!$Y$2,0))))))/(LM_step+(LM_step=0)))+1)>LM_cycles))+LM_stub*('Loan maths'!$Y$2>=LN_maturity))-LM_paid)-1)/LM_safe)+(LM_rate=0)*(LM_out-LM_annuity*((('Loan maths'!$Y$2>=LM_first)*((INT(((YEAR('Loan maths'!$Y$2)-YEAR(LM_first))*12+MONTH('Loan maths'!$Y$2)-MONTH(LM_first)-(DAY('Loan maths'!$Y$2)<(LM_anchor-(LM_anchor-DAY(EOMONTH('Loan maths'!$Y$2,0)))*(LM_anchor>DAY(EOMONTH('Loan maths'!$Y$2,0))))))/(LM_step+(LM_step=0)))+1)+(LM_cycles-(INT(((YEAR('Loan maths'!$Y$2)-YEAR(LM_first))*12+MONTH('Loan maths'!$Y$2)-MONTH(LM_first)-(DAY('Loan maths'!$Y$2)<(LM_anchor-(LM_anchor-DAY(EOMONTH('Loan maths'!$Y$2,0)))*(LM_anchor>DAY(EOMONTH('Loan maths'!$Y$2,0))))))/(LM_step+(LM_step=0)))+1))*((INT(((YEAR('Loan maths'!$Y$2)-YEAR(LM_first))*12+MONTH('Loan maths'!$Y$2)-MONTH(LM_first)-(DAY('Loan maths'!$Y$2)<(LM_anchor-(LM_anchor-DAY(EOMONTH('Loan maths'!$Y$2,0)))*(LM_anchor>DAY(EOMONTH('Loan maths'!$Y$2,0))))))/(LM_step+(LM_step=0)))+1)>LM_cycles))+LM_stub*('Loan maths'!$Y$2>=LN_maturity))-LM_paid)))-((LM_rate>0)*(LM_out*(1+LM_rate)^((('Loan maths'!$Z$2>=LM_first)*((INT(((YEAR('Loan maths'!$Z$2)-YEAR(LM_first))*12+MONTH('Loan maths'!$Z$2)-MONTH(LM_first)-(DAY('Loan maths'!$Z$2)<(LM_anchor-(LM_anchor-DAY(EOMONTH('Loan maths'!$Z$2,0)))*(LM_anchor>DAY(EOMONTH('Loan maths'!$Z$2,0))))))/(LM_step+(LM_step=0)))+1)+(LM_cycles-(INT(((YEAR('Loan maths'!$Z$2)-YEAR(LM_first))*12+MONTH('Loan maths'!$Z$2)-MONTH(LM_first)-(DAY('Loan maths'!$Z$2)<(LM_anchor-(LM_anchor-DAY(EOMONTH('Loan maths'!$Z$2,0)))*(LM_anchor>DAY(EOMONTH('Loan maths'!$Z$2,0))))))/(LM_step+(LM_step=0)))+1))*((INT(((YEAR('Loan maths'!$Z$2)-YEAR(LM_first))*12+MONTH('Loan maths'!$Z$2)-MONTH(LM_first)-(DAY('Loan maths'!$Z$2)<(LM_anchor-(LM_anchor-DAY(EOMONTH('Loan maths'!$Z$2,0)))*(LM_anchor>DAY(EOMONTH('Loan maths'!$Z$2,0))))))/(LM_step+(LM_step=0)))+1)>LM_cycles))+LM_stub*('Loan maths'!$Z$2>=LN_maturity))-LM_paid)-LM_annuity*((1+LM_rate)^((('Loan maths'!$Z$2>=LM_first)*((INT(((YEAR('Loan maths'!$Z$2)-YEAR(LM_first))*12+MONTH('Loan maths'!$Z$2)-MONTH(LM_first)-(DAY('Loan maths'!$Z$2)<(LM_anchor-(LM_anchor-DAY(EOMONTH('Loan maths'!$Z$2,0)))*(LM_anchor>DAY(EOMONTH('Loan maths'!$Z$2,0))))))/(LM_step+(LM_step=0)))+1)+(LM_cycles-(INT(((YEAR('Loan maths'!$Z$2)-YEAR(LM_first))*12+MONTH('Loan maths'!$Z$2)-MONTH(LM_first)-(DAY('Loan maths'!$Z$2)<(LM_anchor-(LM_anchor-DAY(EOMONTH('Loan maths'!$Z$2,0)))*(LM_anchor>DAY(EOMONTH('Loan maths'!$Z$2,0))))))/(LM_step+(LM_step=0)))+1))*((INT(((YEAR('Loan maths'!$Z$2)-YEAR(LM_first))*12+MONTH('Loan maths'!$Z$2)-MONTH(LM_first)-(DAY('Loan maths'!$Z$2)<(LM_anchor-(LM_anchor-DAY(EOMONTH('Loan maths'!$Z$2,0)))*(LM_anchor>DAY(EOMONTH('Loan maths'!$Z$2,0))))))/(LM_step+(LM_step=0)))+1)>LM_cycles))+LM_stub*('Loan maths'!$Z$2>=LN_maturity))-LM_paid)-1)/LM_safe)+(LM_rate=0)*(LM_out-LM_annuity*((('Loan maths'!$Z$2>=LM_first)*((INT(((YEAR('Loan maths'!$Z$2)-YEAR(LM_first))*12+MONTH('Loan maths'!$Z$2)-MONTH(LM_first)-(DAY('Loan maths'!$Z$2)<(LM_anchor-(LM_anchor-DAY(EOMONTH('Loan maths'!$Z$2,0)))*(LM_anchor>DAY(EOMONTH('Loan maths'!$Z$2,0))))))/(LM_step+(LM_step=0)))+1)+(LM_cycles-(INT(((YEAR('Loan maths'!$Z$2)-YEAR(LM_first))*12+MONTH('Loan maths'!$Z$2)-MONTH(LM_first)-(DAY('Loan maths'!$Z$2)<(LM_anchor-(LM_anchor-DAY(EOMONTH('Loan maths'!$Z$2,0)))*(LM_anchor>DAY(EOMONTH('Loan maths'!$Z$2,0))))))/(LM_step+(LM_step=0)))+1))*((INT(((YEAR('Loan maths'!$Z$2)-YEAR(LM_first))*12+MONTH('Loan maths'!$Z$2)-MONTH(LM_first)-(DAY('Loan maths'!$Z$2)<(LM_anchor-(LM_anchor-DAY(EOMONTH('Loan maths'!$Z$2,0)))*(LM_anchor>DAY(EOMONTH('Loan maths'!$Z$2,0))))))/(LM_step+(LM_step=0)))+1)>LM_cycles))+LM_stub*('Loan maths'!$Z$2>=LN_maturity))-LM_paid)))))+SUMPRODUCT(LM_live*((LM_profile<>"EIP")*(LM_profile<>"Annuity"))*(LM_end>'Loan maths'!$Y$2)*(LM_end<='Loan maths'!$Z$2)*LN_principal) -> 0 | D58: =IFERROR(C58/C$62,0) -> 0
B59: 30 to 40 years | C59: =SUMPRODUCT(LM_live*(LM_profile="EIP")*LM_eip*((('Loan maths'!$AA$2>=LM_first)*((INT(((YEAR('Loan maths'!$AA$2)-YEAR(LM_first))*12+MONTH('Loan maths'!$AA$2)-MONTH(LM_first)-(DAY('Loan maths'!$AA$2)<(LM_anchor-(LM_anchor-DAY(EOMONTH('Loan maths'!$AA$2,0)))*(LM_anchor>DAY(EOMONTH('Loan maths'!$AA$2,0))))))/(LM_step+(LM_step=0)))+1)+(LM_cycles-(INT(((YEAR('Loan maths'!$AA$2)-YEAR(LM_first))*12+MONTH('Loan maths'!$AA$2)-MONTH(LM_first)-(DAY('Loan maths'!$AA$2)<(LM_anchor-(LM_anchor-DAY(EOMONTH('Loan maths'!$AA$2,0)))*(LM_anchor>DAY(EOMONTH('Loan maths'!$AA$2,0))))))/(LM_step+(LM_step=0)))+1))*((INT(((YEAR('Loan maths'!$AA$2)-YEAR(LM_first))*12+MONTH('Loan maths'!$AA$2)-MONTH(LM_first)-(DAY('Loan maths'!$AA$2)<(LM_anchor-(LM_anchor-DAY(EOMONTH('Loan maths'!$AA$2,0)))*(LM_anchor>DAY(EOMONTH('Loan maths'!$AA$2,0))))))/(LM_step+(LM_step=0)))+1)>LM_cycles))+LM_stub*('Loan maths'!$AA$2>=LN_maturity))-(('Loan maths'!$Z$2>=LM_first)*((INT(((YEAR('Loan maths'!$Z$2)-YEAR(LM_first))*12+MONTH('Loan maths'!$Z$2)-MONTH(LM_first)-(DAY('Loan maths'!$Z$2)<(LM_anchor-(LM_anchor-DAY(EOMONTH('Loan maths'!$Z$2,0)))*(LM_anchor>DAY(EOMONTH('Loan maths'!$Z$2,0))))))/(LM_step+(LM_step=0)))+1)+(LM_cycles-(INT(((YEAR('Loan maths'!$Z$2)-YEAR(LM_first))*12+MONTH('Loan maths'!$Z$2)-MONTH(LM_first)-(DAY('Loan maths'!$Z$2)<(LM_anchor-(LM_anchor-DAY(EOMONTH('Loan maths'!$Z$2,0)))*(LM_anchor>DAY(EOMONTH('Loan maths'!$Z$2,0))))))/(LM_step+(LM_step=0)))+1))*((INT(((YEAR('Loan maths'!$Z$2)-YEAR(LM_first))*12+MONTH('Loan maths'!$Z$2)-MONTH(LM_first)-(DAY('Loan maths'!$Z$2)<(LM_anchor-(LM_anchor-DAY(EOMONTH('Loan maths'!$Z$2,0)))*(LM_anchor>DAY(EOMONTH('Loan maths'!$Z$2,0))))))/(LM_step+(LM_step=0)))+1)>LM_cycles))+LM_stub*('Loan maths'!$Z$2>=LN_maturity))))+SUMPRODUCT(LM_live*(LM_profile="Annuity")*(((LM_rate>0)*(LM_out*(1+LM_rate)^((('Loan maths'!$Z$2>=LM_first)*((INT(((YEAR('Loan maths'!$Z$2)-YEAR(LM_first))*12+MONTH('Loan maths'!$Z$2)-MONTH(LM_first)-(DAY('Loan maths'!$Z$2)<(LM_anchor-(LM_anchor-DAY(EOMONTH('Loan maths'!$Z$2,0)))*(LM_anchor>DAY(EOMONTH('Loan maths'!$Z$2,0))))))/(LM_step+(LM_step=0)))+1)+(LM_cycles-(INT(((YEAR('Loan maths'!$Z$2)-YEAR(LM_first))*12+MONTH('Loan maths'!$Z$2)-MONTH(LM_first)-(DAY('Loan maths'!$Z$2)<(LM_anchor-(LM_anchor-DAY(EOMONTH('Loan maths'!$Z$2,0)))*(LM_anchor>DAY(EOMONTH('Loan maths'!$Z$2,0))))))/(LM_step+(LM_step=0)))+1))*((INT(((YEAR('Loan maths'!$Z$2)-YEAR(LM_first))*12+MONTH('Loan maths'!$Z$2)-MONTH(LM_first)-(DAY('Loan maths'!$Z$2)<(LM_anchor-(LM_anchor-DAY(EOMONTH('Loan maths'!$Z$2,0)))*(LM_anchor>DAY(EOMONTH('Loan maths'!$Z$2,0))))))/(LM_step+(LM_step=0)))+1)>LM_cycles))+LM_stub*('Loan maths'!$Z$2>=LN_maturity))-LM_paid)-LM_annuity*((1+LM_rate)^((('Loan maths'!$Z$2>=LM_first)*((INT(((YEAR('Loan maths'!$Z$2)-YEAR(LM_first))*12+MONTH('Loan maths'!$Z$2)-MONTH(LM_first)-(DAY('Loan maths'!$Z$2)<(LM_anchor-(LM_anchor-DAY(EOMONTH('Loan maths'!$Z$2,0)))*(LM_anchor>DAY(EOMONTH('Loan maths'!$Z$2,0))))))/(LM_step+(LM_step=0)))+1)+(LM_cycles-(INT(((YEAR('Loan maths'!$Z$2)-YEAR(LM_first))*12+MONTH('Loan maths'!$Z$2)-MONTH(LM_first)-(DAY('Loan maths'!$Z$2)<(LM_anchor-(LM_anchor-DAY(EOMONTH('Loan maths'!$Z$2,0)))*(LM_anchor>DAY(EOMONTH('Loan maths'!$Z$2,0))))))/(LM_step+(LM_step=0)))+1))*((INT(((YEAR('Loan maths'!$Z$2)-YEAR(LM_first))*12+MONTH('Loan maths'!$Z$2)-MONTH(LM_first)-(DAY('Loan maths'!$Z$2)<(LM_anchor-(LM_anchor-DAY(EOMONTH('Loan maths'!$Z$2,0)))*(LM_anchor>DAY(EOMONTH('Loan maths'!$Z$2,0))))))/(LM_step+(LM_step=0)))+1)>LM_cycles))+LM_stub*('Loan maths'!$Z$2>=LN_maturity))-LM_paid)-1)/LM_safe)+(LM_rate=0)*(LM_out-LM_annuity*((('Loan maths'!$Z$2>=LM_first)*((INT(((YEAR('Loan maths'!$Z$2)-YEAR(LM_first))*12+MONTH('Loan maths'!$Z$2)-MONTH(LM_first)-(DAY('Loan maths'!$Z$2)<(LM_anchor-(LM_anchor-DAY(EOMONTH('Loan maths'!$Z$2,0)))*(LM_anchor>DAY(EOMONTH('Loan maths'!$Z$2,0))))))/(LM_step+(LM_step=0)))+1)+(LM_cycles-(INT(((YEAR('Loan maths'!$Z$2)-YEAR(LM_first))*12+MONTH('Loan maths'!$Z$2)-MONTH(LM_first)-(DAY('Loan maths'!$Z$2)<(LM_anchor-(LM_anchor-DAY(EOMONTH('Loan maths'!$Z$2,0)))*(LM_anchor>DAY(EOMONTH('Loan maths'!$Z$2,0))))))/(LM_step+(LM_step=0)))+1))*((INT(((YEAR('Loan maths'!$Z$2)-YEAR(LM_first))*12+MONTH('Loan maths'!$Z$2)-MONTH(LM_first)-(DAY('Loan maths'!$Z$2)<(LM_anchor-(LM_anchor-DAY(EOMONTH('Loan maths'!$Z$2,0)))*(LM_anchor>DAY(EOMONTH('Loan maths'!$Z$2,0))))))/(LM_step+(LM_step=0)))+1)>LM_cycles))+LM_stub*('Loan maths'!$Z$2>=LN_maturity))-LM_paid)))-((LM_rate>0)*(LM_out*(1+LM_rate)^((('Loan maths'!$AA$2>=LM_first)*((INT(((YEAR('Loan maths'!$AA$2)-YEAR(LM_first))*12+MONTH('Loan maths'!$AA$2)-MONTH(LM_first)-(DAY('Loan maths'!$AA$2)<(LM_anchor-(LM_anchor-DAY(EOMONTH('Loan maths'!$AA$2,0)))*(LM_anchor>DAY(EOMONTH('Loan maths'!$AA$2,0))))))/(LM_step+(LM_step=0)))+1)+(LM_cycles-(INT(((YEAR('Loan maths'!$AA$2)-YEAR(LM_first))*12+MONTH('Loan maths'!$AA$2)-MONTH(LM_first)-(DAY('Loan maths'!$AA$2)<(LM_anchor-(LM_anchor-DAY(EOMONTH('Loan maths'!$AA$2,0)))*(LM_anchor>DAY(EOMONTH('Loan maths'!$AA$2,0))))))/(LM_step+(LM_step=0)))+1))*((INT(((YEAR('Loan maths'!$AA$2)-YEAR(LM_first))*12+MONTH('Loan maths'!$AA$2)-MONTH(LM_first)-(DAY('Loan maths'!$AA$2)<(LM_anchor-(LM_anchor-DAY(EOMONTH('Loan maths'!$AA$2,0)))*(LM_anchor>DAY(EOMONTH('Loan maths'!$AA$2,0))))))/(LM_step+(LM_step=0)))+1)>LM_cycles))+LM_stub*('Loan maths'!$AA$2>=LN_maturity))-LM_paid)-LM_annuity*((1+LM_rate)^((('Loan maths'!$AA$2>=LM_first)*((INT(((YEAR('Loan maths'!$AA$2)-YEAR(LM_first))*12+MONTH('Loan maths'!$AA$2)-MONTH(LM_first)-(DAY('Loan maths'!$AA$2)<(LM_anchor-(LM_anchor-DAY(EOMONTH('Loan maths'!$AA$2,0)))*(LM_anchor>DAY(EOMONTH('Loan maths'!$AA$2,0))))))/(LM_step+(LM_step=0)))+1)+(LM_cycles-(INT(((YEAR('Loan maths'!$AA$2)-YEAR(LM_first))*12+MONTH('Loan maths'!$AA$2)-MONTH(LM_first)-(DAY('Loan maths'!$AA$2)<(LM_anchor-(LM_anchor-DAY(EOMONTH('Loan maths'!$AA$2,0)))*(LM_anchor>DAY(EOMONTH('Loan maths'!$AA$2,0))))))/(LM_step+(LM_step=0)))+1))*((INT(((YEAR('Loan maths'!$AA$2)-YEAR(LM_first))*12+MONTH('Loan maths'!$AA$2)-MONTH(LM_first)-(DAY('Loan maths'!$AA$2)<(LM_anchor-(LM_anchor-DAY(EOMONTH('Loan maths'!$AA$2,0)))*(LM_anchor>DAY(EOMONTH('Loan maths'!$AA$2,0))))))/(LM_step+(LM_step=0)))+1)>LM_cycles))+LM_stub*('Loan maths'!$AA$2>=LN_maturity))-LM_paid)-1)/LM_safe)+(LM_rate=0)*(LM_out-LM_annuity*((('Loan maths'!$AA$2>=LM_first)*((INT(((YEAR('Loan maths'!$AA$2)-YEAR(LM_first))*12+MONTH('Loan maths'!$AA$2)-MONTH(LM_first)-(DAY('Loan maths'!$AA$2)<(LM_anchor-(LM_anchor-DAY(EOMONTH('Loan maths'!$AA$2,0)))*(LM_anchor>DAY(EOMONTH('Loan maths'!$AA$2,0))))))/(LM_step+(LM_step=0)))+1)+(LM_cycles-(INT(((YEAR('Loan maths'!$AA$2)-YEAR(LM_first))*12+MONTH('Loan maths'!$AA$2)-MONTH(LM_first)-(DAY('Loan maths'!$AA$2)<(LM_anchor-(LM_anchor-DAY(EOMONTH('Loan maths'!$AA$2,0)))*(LM_anchor>DAY(EOMONTH('Loan maths'!$AA$2,0))))))/(LM_step+(LM_step=0)))+1))*((INT(((YEAR('Loan maths'!$AA$2)-YEAR(LM_first))*12+MONTH('Loan maths'!$AA$2)-MONTH(LM_first)-(DAY('Loan maths'!$AA$2)<(LM_anchor-(LM_anchor-DAY(EOMONTH('Loan maths'!$AA$2,0)))*(LM_anchor>DAY(EOMONTH('Loan maths'!$AA$2,0))))))/(LM_step+(LM_step=0)))+1)>LM_cycles))+LM_stub*('Loan maths'!$AA$2>=LN_maturity))-LM_paid)))))+SUMPRODUCT(LM_live*((LM_profile<>"EIP")*(LM_profile<>"Annuity"))*(LM_end>'Loan maths'!$Z$2)*(LM_end<='Loan maths'!$AA$2)*LN_principal) -> 0 | D59: =IFERROR(C59/C$62,0) -> 0
B60: 40 to 50 years | C60: =SUMPRODUCT(LM_live*(LM_profile="EIP")*LM_eip*((('Loan maths'!$AB$2>=LM_first)*((INT(((YEAR('Loan maths'!$AB$2)-YEAR(LM_first))*12+MONTH('Loan maths'!$AB$2)-MONTH(LM_first)-(DAY('Loan maths'!$AB$2)<(LM_anchor-(LM_anchor-DAY(EOMONTH('Loan maths'!$AB$2,0)))*(LM_anchor>DAY(EOMONTH('Loan maths'!$AB$2,0))))))/(LM_step+(LM_step=0)))+1)+(LM_cycles-(INT(((YEAR('Loan maths'!$AB$2)-YEAR(LM_first))*12+MONTH('Loan maths'!$AB$2)-MONTH(LM_first)-(DAY('Loan maths'!$AB$2)<(LM_anchor-(LM_anchor-DAY(EOMONTH('Loan maths'!$AB$2,0)))*(LM_anchor>DAY(EOMONTH('Loan maths'!$AB$2,0))))))/(LM_step+(LM_step=0)))+1))*((INT(((YEAR('Loan maths'!$AB$2)-YEAR(LM_first))*12+MONTH('Loan maths'!$AB$2)-MONTH(LM_first)-(DAY('Loan maths'!$AB$2)<(LM_anchor-(LM_anchor-DAY(EOMONTH('Loan maths'!$AB$2,0)))*(LM_anchor>DAY(EOMONTH('Loan maths'!$AB$2,0))))))/(LM_step+(LM_step=0)))+1)>LM_cycles))+LM_stub*('Loan maths'!$AB$2>=LN_maturity))-(('Loan maths'!$AA$2>=LM_first)*((INT(((YEAR('Loan maths'!$AA$2)-YEAR(LM_first))*12+MONTH('Loan maths'!$AA$2)-MONTH(LM_first)-(DAY('Loan maths'!$AA$2)<(LM_anchor-(LM_anchor-DAY(EOMONTH('Loan maths'!$AA$2,0)))*(LM_anchor>DAY(EOMONTH('Loan maths'!$AA$2,0))))))/(LM_step+(LM_step=0)))+1)+(LM_cycles-(INT(((YEAR('Loan maths'!$AA$2)-YEAR(LM_first))*12+MONTH('Loan maths'!$AA$2)-MONTH(LM_first)-(DAY('Loan maths'!$AA$2)<(LM_anchor-(LM_anchor-DAY(EOMONTH('Loan maths'!$AA$2,0)))*(LM_anchor>DAY(EOMONTH('Loan maths'!$AA$2,0))))))/(LM_step+(LM_step=0)))+1))*((INT(((YEAR('Loan maths'!$AA$2)-YEAR(LM_first))*12+MONTH('Loan maths'!$AA$2)-MONTH(LM_first)-(DAY('Loan maths'!$AA$2)<(LM_anchor-(LM_anchor-DAY(EOMONTH('Loan maths'!$AA$2,0)))*(LM_anchor>DAY(EOMONTH('Loan maths'!$AA$2,0))))))/(LM_step+(LM_step=0)))+1)>LM_cycles))+LM_stub*('Loan maths'!$AA$2>=LN_maturity))))+SUMPRODUCT(LM_live*(LM_profile="Annuity")*(((LM_rate>0)*(LM_out*(1+LM_rate)^((('Loan maths'!$AA$2>=LM_first)*((INT(((YEAR('Loan maths'!$AA$2)-YEAR(LM_first))*12+MONTH('Loan maths'!$AA$2)-MONTH(LM_first)-(DAY('Loan maths'!$AA$2)<(LM_anchor-(LM_anchor-DAY(EOMONTH('Loan maths'!$AA$2,0)))*(LM_anchor>DAY(EOMONTH('Loan maths'!$AA$2,0))))))/(LM_step+(LM_step=0)))+1)+(LM_cycles-(INT(((YEAR('Loan maths'!$AA$2)-YEAR(LM_first))*12+MONTH('Loan maths'!$AA$2)-MONTH(LM_first)-(DAY('Loan maths'!$AA$2)<(LM_anchor-(LM_anchor-DAY(EOMONTH('Loan maths'!$AA$2,0)))*(LM_anchor>DAY(EOMONTH('Loan maths'!$AA$2,0))))))/(LM_step+(LM_step=0)))+1))*((INT(((YEAR('Loan maths'!$AA$2)-YEAR(LM_first))*12+MONTH('Loan maths'!$AA$2)-MONTH(LM_first)-(DAY('Loan maths'!$AA$2)<(LM_anchor-(LM_anchor-DAY(EOMONTH('Loan maths'!$AA$2,0)))*(LM_anchor>DAY(EOMONTH('Loan maths'!$AA$2,0))))))/(LM_step+(LM_step=0)))+1)>LM_cycles))+LM_stub*('Loan maths'!$AA$2>=LN_maturity))-LM_paid)-LM_annuity*((1+LM_rate)^((('Loan maths'!$AA$2>=LM_first)*((INT(((YEAR('Loan maths'!$AA$2)-YEAR(LM_first))*12+MONTH('Loan maths'!$AA$2)-MONTH(LM_first)-(DAY('Loan maths'!$AA$2)<(LM_anchor-(LM_anchor-DAY(EOMONTH('Loan maths'!$AA$2,0)))*(LM_anchor>DAY(EOMONTH('Loan maths'!$AA$2,0))))))/(LM_step+(LM_step=0)))+1)+(LM_cycles-(INT(((YEAR('Loan maths'!$AA$2)-YEAR(LM_first))*12+MONTH('Loan maths'!$AA$2)-MONTH(LM_first)-(DAY('Loan maths'!$AA$2)<(LM_anchor-(LM_anchor-DAY(EOMONTH('Loan maths'!$AA$2,0)))*(LM_anchor>DAY(EOMONTH('Loan maths'!$AA$2,0))))))/(LM_step+(LM_step=0)))+1))*((INT(((YEAR('Loan maths'!$AA$2)-YEAR(LM_first))*12+MONTH('Loan maths'!$AA$2)-MONTH(LM_first)-(DAY('Loan maths'!$AA$2)<(LM_anchor-(LM_anchor-DAY(EOMONTH('Loan maths'!$AA$2,0)))*(LM_anchor>DAY(EOMONTH('Loan maths'!$AA$2,0))))))/(LM_step+(LM_step=0)))+1)>LM_cycles))+LM_stub*('Loan maths'!$AA$2>=LN_maturity))-LM_paid)-1)/LM_safe)+(LM_rate=0)*(LM_out-LM_annuity*((('Loan maths'!$AA$2>=LM_first)*((INT(((YEAR('Loan maths'!$AA$2)-YEAR(LM_first))*12+MONTH('Loan maths'!$AA$2)-MONTH(LM_first)-(DAY('Loan maths'!$AA$2)<(LM_anchor-(LM_anchor-DAY(EOMONTH('Loan maths'!$AA$2,0)))*(LM_anchor>DAY(EOMONTH('Loan maths'!$AA$2,0))))))/(LM_step+(LM_step=0)))+1)+(LM_cycles-(INT(((YEAR('Loan maths'!$AA$2)-YEAR(LM_first))*12+MONTH('Loan maths'!$AA$2)-MONTH(LM_first)-(DAY('Loan maths'!$AA$2)<(LM_anchor-(LM_anchor-DAY(EOMONTH('Loan maths'!$AA$2,0)))*(LM_anchor>DAY(EOMONTH('Loan maths'!$AA$2,0))))))/(LM_step+(LM_step=0)))+1))*((INT(((YEAR('Loan maths'!$AA$2)-YEAR(LM_first))*12+MONTH('Loan maths'!$AA$2)-MONTH(LM_first)-(DAY('Loan maths'!$AA$2)<(LM_anchor-(LM_anchor-DAY(EOMONTH('Loan maths'!$AA$2,0)))*(LM_anchor>DAY(EOMONTH('Loan maths'!$AA$2,0))))))/(LM_step+(LM_step=0)))+1)>LM_cycles))+LM_stub*('Loan maths'!$AA$2>=LN_maturity))-LM_paid)))-((LM_rate>0)*(LM_out*(1+LM_rate)^((('Loan maths'!$AB$2>=LM_first)*((INT(((YEAR('Loan maths'!$AB$2)-YEAR(LM_first))*12+MONTH('Loan maths'!$AB$2)-MONTH(LM_first)-(DAY('Loan maths'!$AB$2)<(LM_anchor-(LM_anchor-DAY(EOMONTH('Loan maths'!$AB$2,0)))*(LM_anchor>DAY(EOMONTH('Loan maths'!$AB$2,0))))))/(LM_step+(LM_step=0)))+1)+(LM_cycles-(INT(((YEAR('Loan maths'!$AB$2)-YEAR(LM_first))*12+MONTH('Loan maths'!$AB$2)-MONTH(LM_first)-(DAY('Loan maths'!$AB$2)<(LM_anchor-(LM_anchor-DAY(EOMONTH('Loan maths'!$AB$2,0)))*(LM_anchor>DAY(EOMONTH('Loan maths'!$AB$2,0))))))/(LM_step+(LM_step=0)))+1))*((INT(((YEAR('Loan maths'!$AB$2)-YEAR(LM_first))*12+MONTH('Loan maths'!$AB$2)-MONTH(LM_first)-(DAY('Loan maths'!$AB$2)<(LM_anchor-(LM_anchor-DAY(EOMONTH('Loan maths'!$AB$2,0)))*(LM_anchor>DAY(EOMONTH('Loan maths'!$AB$2,0))))))/(LM_step+(LM_step=0)))+1)>LM_cycles))+LM_stub*('Loan maths'!$AB$2>=LN_maturity))-LM_paid)-LM_annuity*((1+LM_rate)^((('Loan maths'!$AB$2>=LM_first)*((INT(((YEAR('Loan maths'!$AB$2)-YEAR(LM_first))*12+MONTH('Loan maths'!$AB$2)-MONTH(LM_first)-(DAY('Loan maths'!$AB$2)<(LM_anchor-(LM_anchor-DAY(EOMONTH('Loan maths'!$AB$2,0)))*(LM_anchor>DAY(EOMONTH('Loan maths'!$AB$2,0))))))/(LM_step+(LM_step=0)))+1)+(LM_cycles-(INT(((YEAR('Loan maths'!$AB$2)-YEAR(LM_first))*12+MONTH('Loan maths'!$AB$2)-MONTH(LM_first)-(DAY('Loan maths'!$AB$2)<(LM_anchor-(LM_anchor-DAY(EOMONTH('Loan maths'!$AB$2,0)))*(LM_anchor>DAY(EOMONTH('Loan maths'!$AB$2,0))))))/(LM_step+(LM_step=0)))+1))*((INT(((YEAR('Loan maths'!$AB$2)-YEAR(LM_first))*12+MONTH('Loan maths'!$AB$2)-MONTH(LM_first)-(DAY('Loan maths'!$AB$2)<(LM_anchor-(LM_anchor-DAY(EOMONTH('Loan maths'!$AB$2,0)))*(LM_anchor>DAY(EOMONTH('Loan maths'!$AB$2,0))))))/(LM_step+(LM_step=0)))+1)>LM_cycles))+LM_stub*('Loan maths'!$AB$2>=LN_maturity))-LM_paid)-1)/LM_safe)+(LM_rate=0)*(LM_out-LM_annuity*((('Loan maths'!$AB$2>=LM_first)*((INT(((YEAR('Loan maths'!$AB$2)-YEAR(LM_first))*12+MONTH('Loan maths'!$AB$2)-MONTH(LM_first)-(DAY('Loan maths'!$AB$2)<(LM_anchor-(LM_anchor-DAY(EOMONTH('Loan maths'!$AB$2,0)))*(LM_anchor>DAY(EOMONTH('Loan maths'!$AB$2,0))))))/(LM_step+(LM_step=0)))+1)+(LM_cycles-(INT(((YEAR('Loan maths'!$AB$2)-YEAR(LM_first))*12+MONTH('Loan maths'!$AB$2)-MONTH(LM_first)-(DAY('Loan maths'!$AB$2)<(LM_anchor-(LM_anchor-DAY(EOMONTH('Loan maths'!$AB$2,0)))*(LM_anchor>DAY(EOMONTH('Loan maths'!$AB$2,0))))))/(LM_step+(LM_step=0)))+1))*((INT(((YEAR('Loan maths'!$AB$2)-YEAR(LM_first))*12+MONTH('Loan maths'!$AB$2)-MONTH(LM_first)-(DAY('Loan maths'!$AB$2)<(LM_anchor-(LM_anchor-DAY(EOMONTH('Loan maths'!$AB$2,0)))*(LM_anchor>DAY(EOMONTH('Loan maths'!$AB$2,0))))))/(LM_step+(LM_step=0)))+1)>LM_cycles))+LM_stub*('Loan maths'!$AB$2>=LN_maturity))-LM_paid)))))+SUMPRODUCT(LM_live*((LM_profile<>"EIP")*(LM_profile<>"Annuity"))*(LM_end>'Loan maths'!$AA$2)*(LM_end<='Loan maths'!$AB$2)*LN_principal) -> 0 | D60: =IFERROR(C60/C$62,0) -> 0
B61: Over 50 years | C61: =SUMPRODUCT(LM_live*(LM_profile="EIP")*LM_eip*((('Loan maths'!$AC$2>=LM_first)*((INT(((YEAR('Loan maths'!$AC$2)-YEAR(LM_first))*12+MONTH('Loan maths'!$AC$2)-MONTH(LM_first)-(DAY('Loan maths'!$AC$2)<(LM_anchor-(LM_anchor-DAY(EOMONTH('Loan maths'!$AC$2,0)))*(LM_anchor>DAY(EOMONTH('Loan maths'!$AC$2,0))))))/(LM_step+(LM_step=0)))+1)+(LM_cycles-(INT(((YEAR('Loan maths'!$AC$2)-YEAR(LM_first))*12+MONTH('Loan maths'!$AC$2)-MONTH(LM_first)-(DAY('Loan maths'!$AC$2)<(LM_anchor-(LM_anchor-DAY(EOMONTH('Loan maths'!$AC$2,0)))*(LM_anchor>DAY(EOMONTH('Loan maths'!$AC$2,0))))))/(LM_step+(LM_step=0)))+1))*((INT(((YEAR('Loan maths'!$AC$2)-YEAR(LM_first))*12+MONTH('Loan maths'!$AC$2)-MONTH(LM_first)-(DAY('Loan maths'!$AC$2)<(LM_anchor-(LM_anchor-DAY(EOMONTH('Loan maths'!$AC$2,0)))*(LM_anchor>DAY(EOMONTH('Loan maths'!$AC$2,0))))))/(LM_step+(LM_step=0)))+1)>LM_cycles))+LM_stub*('Loan maths'!$AC$2>=LN_maturity))-(('Loan maths'!$AB$2>=LM_first)*((INT(((YEAR('Loan maths'!$AB$2)-YEAR(LM_first))*12+MONTH('Loan maths'!$AB$2)-MONTH(LM_first)-(DAY('Loan maths'!$AB$2)<(LM_anchor-(LM_anchor-DAY(EOMONTH('Loan maths'!$AB$2,0)))*(LM_anchor>DAY(EOMONTH('Loan maths'!$AB$2,0))))))/(LM_step+(LM_step=0)))+1)+(LM_cycles-(INT(((YEAR('Loan maths'!$AB$2)-YEAR(LM_first))*12+MONTH('Loan maths'!$AB$2)-MONTH(LM_first)-(DAY('Loan maths'!$AB$2)<(LM_anchor-(LM_anchor-DAY(EOMONTH('Loan maths'!$AB$2,0)))*(LM_anchor>DAY(EOMONTH('Loan maths'!$AB$2,0))))))/(LM_step+(LM_step=0)))+1))*((INT(((YEAR('Loan maths'!$AB$2)-YEAR(LM_first))*12+MONTH('Loan maths'!$AB$2)-MONTH(LM_first)-(DAY('Loan maths'!$AB$2)<(LM_anchor-(LM_anchor-DAY(EOMONTH('Loan maths'!$AB$2,0)))*(LM_anchor>DAY(EOMONTH('Loan maths'!$AB$2,0))))))/(LM_step+(LM_step=0)))+1)>LM_cycles))+LM_stub*('Loan maths'!$AB$2>=LN_maturity))))+SUMPRODUCT(LM_live*(LM_profile="Annuity")*(((LM_rate>0)*(LM_out*(1+LM_rate)^((('Loan maths'!$AB$2>=LM_first)*((INT(((YEAR('Loan maths'!$AB$2)-YEAR(LM_first))*12+MONTH('Loan maths'!$AB$2)-MONTH(LM_first)-(DAY('Loan maths'!$AB$2)<(LM_anchor-(LM_anchor-DAY(EOMONTH('Loan maths'!$AB$2,0)))*(LM_anchor>DAY(EOMONTH('Loan maths'!$AB$2,0))))))/(LM_step+(LM_step=0)))+1)+(LM_cycles-(INT(((YEAR('Loan maths'!$AB$2)-YEAR(LM_first))*12+MONTH('Loan maths'!$AB$2)-MONTH(LM_first)-(DAY('Loan maths'!$AB$2)<(LM_anchor-(LM_anchor-DAY(EOMONTH('Loan maths'!$AB$2,0)))*(LM_anchor>DAY(EOMONTH('Loan maths'!$AB$2,0))))))/(LM_step+(LM_step=0)))+1))*((INT(((YEAR('Loan maths'!$AB$2)-YEAR(LM_first))*12+MONTH('Loan maths'!$AB$2)-MONTH(LM_first)-(DAY('Loan maths'!$AB$2)<(LM_anchor-(LM_anchor-DAY(EOMONTH('Loan maths'!$AB$2,0)))*(LM_anchor>DAY(EOMONTH('Loan maths'!$AB$2,0))))))/(LM_step+(LM_step=0)))+1)>LM_cycles))+LM_stub*('Loan maths'!$AB$2>=LN_maturity))-LM_paid)-LM_annuity*((1+LM_rate)^((('Loan maths'!$AB$2>=LM_first)*((INT(((YEAR('Loan maths'!$AB$2)-YEAR(LM_first))*12+MONTH('Loan maths'!$AB$2)-MONTH(LM_first)-(DAY('Loan maths'!$AB$2)<(LM_anchor-(LM_anchor-DAY(EOMONTH('Loan maths'!$AB$2,0)))*(LM_anchor>DAY(EOMONTH('Loan maths'!$AB$2,0))))))/(LM_step+(LM_step=0)))+1)+(LM_cycles-(INT(((YEAR('Loan maths'!$AB$2)-YEAR(LM_first))*12+MONTH('Loan maths'!$AB$2)-MONTH(LM_first)-(DAY('Loan maths'!$AB$2)<(LM_anchor-(LM_anchor-DAY(EOMONTH('Loan maths'!$AB$2,0)))*(LM_anchor>DAY(EOMONTH('Loan maths'!$AB$2,0))))))/(LM_step+(LM_step=0)))+1))*((INT(((YEAR('Loan maths'!$AB$2)-YEAR(LM_first))*12+MONTH('Loan maths'!$AB$2)-MONTH(LM_first)-(DAY('Loan maths'!$AB$2)<(LM_anchor-(LM_anchor-DAY(EOMONTH('Loan maths'!$AB$2,0)))*(LM_anchor>DAY(EOMONTH('Loan maths'!$AB$2,0))))))/(LM_step+(LM_step=0)))+1)>LM_cycles))+LM_stub*('Loan maths'!$AB$2>=LN_maturity))-LM_paid)-1)/LM_safe)+(LM_rate=0)*(LM_out-LM_annuity*((('Loan maths'!$AB$2>=LM_first)*((INT(((YEAR('Loan maths'!$AB$2)-YEAR(LM_first))*12+MONTH('Loan maths'!$AB$2)-MONTH(LM_first)-(DAY('Loan maths'!$AB$2)<(LM_anchor-(LM_anchor-DAY(EOMONTH('Loan maths'!$AB$2,0)))*(LM_anchor>DAY(EOMONTH('Loan maths'!$AB$2,0))))))/(LM_step+(LM_step=0)))+1)+(LM_cycles-(INT(((YEAR('Loan maths'!$AB$2)-YEAR(LM_first))*12+MONTH('Loan maths'!$AB$2)-MONTH(LM_first)-(DAY('Loan maths'!$AB$2)<(LM_anchor-(LM_anchor-DAY(EOMONTH('Loan maths'!$AB$2,0)))*(LM_anchor>DAY(EOMONTH('Loan maths'!$AB$2,0))))))/(LM_step+(LM_step=0)))+1))*((INT(((YEAR('Loan maths'!$AB$2)-YEAR(LM_first))*12+MONTH('Loan maths'!$AB$2)-MONTH(LM_first)-(DAY('Loan maths'!$AB$2)<(LM_anchor-(LM_anchor-DAY(EOMONTH('Loan maths'!$AB$2,0)))*(LM_anchor>DAY(EOMONTH('Loan maths'!$AB$2,0))))))/(LM_step+(LM_step=0)))+1)>LM_cycles))+LM_stub*('Loan maths'!$AB$2>=LN_maturity))-LM_paid)))-((LM_rate>0)*(LM_out*(1+LM_rate)^((('Loan maths'!$AC$2>=LM_first)*((INT(((YEAR('Loan maths'!$AC$2)-YEAR(LM_first))*12+MONTH('Loan maths'!$AC$2)-MONTH(LM_first)-(DAY('Loan maths'!$AC$2)<(LM_anchor-(LM_anchor-DAY(EOMONTH('Loan maths'!$AC$2,0)))*(LM_anchor>DAY(EOMONTH('Loan maths'!$AC$2,0))))))/(LM_step+(LM_step=0)))+1)+(LM_cycles-(INT(((YEAR('Loan maths'!$AC$2)-YEAR(LM_first))*12+MONTH('Loan maths'!$AC$2)-MONTH(LM_first)-(DAY('Loan maths'!$AC$2)<(LM_anchor-(LM_anchor-DAY(EOMONTH('Loan maths'!$AC$2,0)))*(LM_anchor>DAY(EOMONTH('Loan maths'!$AC$2,0))))))/(LM_step+(LM_step=0)))+1))*((INT(((YEAR('Loan maths'!$AC$2)-YEAR(LM_first))*12+MONTH('Loan maths'!$AC$2)-MONTH(LM_first)-(DAY('Loan maths'!$AC$2)<(LM_anchor-(LM_anchor-DAY(EOMONTH('Loan maths'!$AC$2,0)))*(LM_anchor>DAY(EOMONTH('Loan maths'!$AC$2,0))))))/(LM_step+(LM_step=0)))+1)>LM_cycles))+LM_stub*('Loan maths'!$AC$2>=LN_maturity))-LM_paid)-LM_annuity*((1+LM_rate)^((('Loan maths'!$AC$2>=LM_first)*((INT(((YEAR('Loan maths'!$AC$2)-YEAR(LM_first))*12+MONTH('Loan maths'!$AC$2)-MONTH(LM_first)-(DAY('Loan maths'!$AC$2)<(LM_anchor-(LM_anchor-DAY(EOMONTH('Loan maths'!$AC$2,0)))*(LM_anchor>DAY(EOMONTH('Loan maths'!$AC$2,0))))))/(LM_step+(LM_step=0)))+1)+(LM_cycles-(INT(((YEAR('Loan maths'!$AC$2)-YEAR(LM_first))*12+MONTH('Loan maths'!$AC$2)-MONTH(LM_first)-(DAY('Loan maths'!$AC$2)<(LM_anchor-(LM_anchor-DAY(EOMONTH('Loan maths'!$AC$2,0)))*(LM_anchor>DAY(EOMONTH('Loan maths'!$AC$2,0))))))/(LM_step+(LM_step=0)))+1))*((INT(((YEAR('Loan maths'!$AC$2)-YEAR(LM_first))*12+MONTH('Loan maths'!$AC$2)-MONTH(LM_first)-(DAY('Loan maths'!$AC$2)<(LM_anchor-(LM_anchor-DAY(EOMONTH('Loan maths'!$AC$2,0)))*(LM_anchor>DAY(EOMONTH('Loan maths'!$AC$2,0))))))/(LM_step+(LM_step=0)))+1)>LM_cycles))+LM_stub*('Loan maths'!$AC$2>=LN_maturity))-LM_paid)-1)/LM_safe)+(LM_rate=0)*(LM_out-LM_annuity*((('Loan maths'!$AC$2>=LM_first)*((INT(((YEAR('Loan maths'!$AC$2)-YEAR(LM_first))*12+MONTH('Loan maths'!$AC$2)-MONTH(LM_first)-(DAY('Loan maths'!$AC$2)<(LM_anchor-(LM_anchor-DAY(EOMONTH('Loan maths'!$AC$2,0)))*(LM_anchor>DAY(EOMONTH('Loan maths'!$AC$2,0))))))/(LM_step+(LM_step=0)))+1)+(LM_cycles-(INT(((YEAR('Loan maths'!$AC$2)-YEAR(LM_first))*12+MONTH('Loan maths'!$AC$2)-MONTH(LM_first)-(DAY('Loan maths'!$AC$2)<(LM_anchor-(LM_anchor-DAY(EOMONTH('Loan maths'!$AC$2,0)))*(LM_anchor>DAY(EOMONTH('Loan maths'!$AC$2,0))))))/(LM_step+(LM_step=0)))+1))*((INT(((YEAR('Loan maths'!$AC$2)-YEAR(LM_first))*12+MONTH('Loan maths'!$AC$2)-MONTH(LM_first)-(DAY('Loan maths'!$AC$2)<(LM_anchor-(LM_anchor-DAY(EOMONTH('Loan maths'!$AC$2,0)))*(LM_anchor>DAY(EOMONTH('Loan maths'!$AC$2,0))))))/(LM_step+(LM_step=0)))+1)>LM_cycles))+LM_stub*('Loan maths'!$AC$2>=LN_maturity))-LM_paid)))))+SUMPRODUCT(LM_live*((LM_profile<>"EIP")*(LM_profile<>"Annuity"))*(LM_end>'Loan maths'!$AB$2)*(LM_end<='Loan maths'!$AC$2)*LN_principal) -> 0 | D61: =IFERROR(C61/C$62,0) -> 0
B62: Total | C62: =SUM(C53:C61) -> 0 | D62: =IFERROR(SUM(D53:D61),0) -> 0
B63: Principal due in each period: a maturity loan at its end, a LOBO at its next call, an EIP loan's equal instalments and an annuity loan's growing principal parts on their payment dates.
B65: The next twelve months
B66: Month | C66: Investments maturing | D66: Loan repayments due | N66: Repayments, negated for the chart
B67: =IF(DAY(AsAt+1)=1,TEXT(IF(DAY(AsAt+1)=1,EOMONTH(AsAt,1),EDATE(AsAt,1)),"mmm yy"),"to "&TEXT(IF(DAY(AsAt+1)=1,EOMONTH(AsAt,1),EDATE(AsAt,1)),"d mmm yy")) -> Oct 26 | C67: =SUMPRODUCT(('Deal maths'!$F$4:$F$2000>AsAt)*('Deal maths'!$E$4:$E$2000<=AsAt)*('Deal maths'!$F$4:$F$2000>IF(DAY(AsAt+1)=1,EOMONTH(AsAt,0),EDATE(AsAt,0)))*('Deal maths'!$F$4:$F$2000<=IF(DAY(AsAt+1)=1,EOMONTH(AsAt,1),EDATE(AsAt,1)))*('Deal maths'!$H$4:$H$2000+('Deal maths'!$H$4:$H$2000=0)*'Deal maths'!$D$4:$D$2000)) -> 0 | D67: =SUMPRODUCT(LM_live*(LM_profile="EIP")*LM_eip*((('Loan maths'!$AE$2>=LM_first)*((INT(((YEAR('Loan maths'!$AE$2)-YEAR(LM_first))*12+MONTH('Loan maths'!$AE$2)-MONTH(LM_first)-(DAY('Loan maths'!$AE$2)<(LM_anchor-(LM_anchor-DAY(EOMONTH('Loan maths'!$AE$2,0)))*(LM_anchor>DAY(EOMONTH('Loan maths'!$AE$2,0))))))/(LM_step+(LM_step=0)))+1)+(LM_cycles-(INT(((YEAR('Loan maths'!$AE$2)-YEAR(LM_first))*12+MONTH('Loan maths'!$AE$2)-MONTH(LM_first)-(DAY('Loan maths'!$AE$2)<(LM_anchor-(LM_anchor-DAY(EOMONTH('Loan maths'!$AE$2,0)))*(LM_anchor>DAY(EOMONTH('Loan maths'!$AE$2,0))))))/(LM_step+(LM_step=0)))+1))*((INT(((YEAR('Loan maths'!$AE$2)-YEAR(LM_first))*12+MONTH('Loan maths'!$AE$2)-MONTH(LM_first)-(DAY('Loan maths'!$AE$2)<(LM_anchor-(LM_anchor-DAY(EOMONTH('Loan maths'!$AE$2,0)))*(LM_anchor>DAY(EOMONTH('Loan maths'!$AE$2,0))))))/(LM_step+(LM_step=0)))+1)>LM_cycles))+LM_stub*('Loan maths'!$AE$2>=LN_maturity))-(('Loan maths'!$AD$2>=LM_first)*((INT(((YEAR('Loan maths'!$AD$2)-YEAR(LM_first))*12+MONTH('Loan maths'!$AD$2)-MONTH(LM_first)-(DAY('Loan maths'!$AD$2)<(LM_anchor-(LM_anchor-DAY(EOMONTH('Loan maths'!$AD$2,0)))*(LM_anchor>DAY(EOMONTH('Loan maths'!$AD$2,0))))))/(LM_step+(LM_step=0)))+1)+(LM_cycles-(INT(((YEAR('Loan maths'!$AD$2)-YEAR(LM_first))*12+MONTH('Loan maths'!$AD$2)-MONTH(LM_first)-(DAY('Loan maths'!$AD$2)<(LM_anchor-(LM_anchor-DAY(EOMONTH('Loan maths'!$AD$2,0)))*(LM_anchor>DAY(EOMONTH('Loan maths'!$AD$2,0))))))/(LM_step+(LM_step=0)))+1))*((INT(((YEAR('Loan maths'!$AD$2)-YEAR(LM_first))*12+MONTH('Loan maths'!$AD$2)-MONTH(LM_first)-(DAY('Loan maths'!$AD$2)<(LM_anchor-(LM_anchor-DAY(EOMONTH('Loan maths'!$AD$2,0)))*(LM_anchor>DAY(EOMONTH('Loan maths'!$AD$2,0))))))/(LM_step+(LM_step=0)))+1)>LM_cycles))+LM_stub*('Loan maths'!$AD$2>=LN_maturity))))+SUMPRODUCT(LM_live*(LM_profile="Annuity")*(((LM_rate>0)*(LM_out*(1+LM_rate)^((('Loan maths'!$AD$2>=LM_first)*((INT(((YEAR('Loan maths'!$AD$2)-YEAR(LM_first))*12+MONTH('Loan maths'!$AD$2)-MONTH(LM_first)-(DAY('Loan maths'!$AD$2)<(LM_anchor-(LM_anchor-DAY(EOMONTH('Loan maths'!$AD$2,0)))*(LM_anchor>DAY(EOMONTH('Loan maths'!$AD$2,0))))))/(LM_step+(LM_step=0)))+1)+(LM_cycles-(INT(((YEAR('Loan maths'!$AD$2)-YEAR(LM_first))*12+MONTH('Loan maths'!$AD$2)-MONTH(LM_first)-(DAY('Loan maths'!$AD$2)<(LM_anchor-(LM_anchor-DAY(EOMONTH('Loan maths'!$AD$2,0)))*(LM_anchor>DAY(EOMONTH('Loan maths'!$AD$2,0))))))/(LM_step+(LM_step=0)))+1))*((INT(((YEAR('Loan maths'!$AD$2)-YEAR(LM_first))*12+MONTH('Loan maths'!$AD$2)-MONTH(LM_first)-(DAY('Loan maths'!$AD$2)<(LM_anchor-(LM_anchor-DAY(EOMONTH('Loan maths'!$AD$2,0)))*(LM_anchor>DAY(EOMONTH('Loan maths'!$AD$2,0))))))/(LM_step+(LM_step=0)))+1)>LM_cycles))+LM_stub*('Loan maths'!$AD$2>=LN_maturity))-LM_paid)-LM_annuity*((1+LM_rate)^((('Loan maths'!$AD$2>=LM_first)*((INT(((YEAR('Loan maths'!$AD$2)-YEAR(LM_first))*12+MONTH('Loan maths'!$AD$2)-MONTH(LM_first)-(DAY('Loan maths'!$AD$2)<(LM_anchor-(LM_anchor-DAY(EOMONTH('Loan maths'!$AD$2,0)))*(LM_anchor>DAY(EOMONTH('Loan maths'!$AD$2,0))))))/(LM_step+(LM_step=0)))+1)+(LM_cycles-(INT(((YEAR('Loan maths'!$AD$2)-YEAR(LM_first))*12+MONTH('Loan maths'!$AD$2)-MONTH(LM_first)-(DAY('Loan maths'!$AD$2)<(LM_anchor-(LM_anchor-DAY(EOMONTH('Loan maths'!$AD$2,0)))*(LM_anchor>DAY(EOMONTH('Loan maths'!$AD$2,0))))))/(LM_step+(LM_step=0)))+1))*((INT(((YEAR('Loan maths'!$AD$2)-YEAR(LM_first))*12+MONTH('Loan maths'!$AD$2)-MONTH(LM_first)-(DAY('Loan maths'!$AD$2)<(LM_anchor-(LM_anchor-DAY(EOMONTH('Loan maths'!$AD$2,0)))*(LM_anchor>DAY(EOMONTH('Loan maths'!$AD$2,0))))))/(LM_step+(LM_step=0)))+1)>LM_cycles))+LM_stub*('Loan maths'!$AD$2>=LN_maturity))-LM_paid)-1)/LM_safe)+(LM_rate=0)*(LM_out-LM_annuity*((('Loan maths'!$AD$2>=LM_first)*((INT(((YEAR('Loan maths'!$AD$2)-YEAR(LM_first))*12+MONTH('Loan maths'!$AD$2)-MONTH(LM_first)-(DAY('Loan maths'!$AD$2)<(LM_anchor-(LM_anchor-DAY(EOMONTH('Loan maths'!$AD$2,0)))*(LM_anchor>DAY(EOMONTH('Loan maths'!$AD$2,0))))))/(LM_step+(LM_step=0)))+1)+(LM_cycles-(INT(((YEAR('Loan maths'!$AD$2)-YEAR(LM_first))*12+MONTH('Loan maths'!$AD$2)-MONTH(LM_first)-(DAY('Loan maths'!$AD$2)<(LM_anchor-(LM_anchor-DAY(EOMONTH('Loan maths'!$AD$2,0)))*(LM_anchor>DAY(EOMONTH('Loan maths'!$AD$2,0))))))/(LM_step+(LM_step=0)))+1))*((INT(((YEAR('Loan maths'!$AD$2)-YEAR(LM_first))*12+MONTH('Loan maths'!$AD$2)-MONTH(LM_first)-(DAY('Loan maths'!$AD$2)<(LM_anchor-(LM_anchor-DAY(EOMONTH('Loan maths'!$AD$2,0)))*(LM_anchor>DAY(EOMONTH('Loan maths'!$AD$2,0))))))/(LM_step+(LM_step=0)))+1)>LM_cycles))+LM_stub*('Loan maths'!$AD$2>=LN_maturity))-LM_paid)))-((LM_rate>0)*(LM_out*(1+LM_rate)^((('Loan maths'!$AE$2>=LM_first)*((INT(((YEAR('Loan maths'!$AE$2)-YEAR(LM_first))*12+MONTH('Loan maths'!$AE$2)-MONTH(LM_first)-(DAY('Loan maths'!$AE$2)<(LM_anchor-(LM_anchor-DAY(EOMONTH('Loan maths'!$AE$2,0)))*(LM_anchor>DAY(EOMONTH('Loan maths'!$AE$2,0))))))/(LM_step+(LM_step=0)))+1)+(LM_cycles-(INT(((YEAR('Loan maths'!$AE$2)-YEAR(LM_first))*12+MONTH('Loan maths'!$AE$2)-MONTH(LM_first)-(DAY('Loan maths'!$AE$2)<(LM_anchor-(LM_anchor-DAY(EOMONTH('Loan maths'!$AE$2,0)))*(LM_anchor>DAY(EOMONTH('Loan maths'!$AE$2,0))))))/(LM_step+(LM_step=0)))+1))*((INT(((YEAR('Loan maths'!$AE$2)-YEAR(LM_first))*12+MONTH('Loan maths'!$AE$2)-MONTH(LM_first)-(DAY('Loan maths'!$AE$2)<(LM_anchor-(LM_anchor-DAY(EOMONTH('Loan maths'!$AE$2,0)))*(LM_anchor>DAY(EOMONTH('Loan maths'!$AE$2,0))))))/(LM_step+(LM_step=0)))+1)>LM_cycles))+LM_stub*('Loan maths'!$AE$2>=LN_maturity))-LM_paid)-LM_annuity*((1+LM_rate)^((('Loan maths'!$AE$2>=LM_first)*((INT(((YEAR('Loan maths'!$AE$2)-YEAR(LM_first))*12+MONTH('Loan maths'!$AE$2)-MONTH(LM_first)-(DAY('Loan maths'!$AE$2)<(LM_anchor-(LM_anchor-DAY(EOMONTH('Loan maths'!$AE$2,0)))*(LM_anchor>DAY(EOMONTH('Loan maths'!$AE$2,0))))))/(LM_step+(LM_step=0)))+1)+(LM_cycles-(INT(((YEAR('Loan maths'!$AE$2)-YEAR(LM_first))*12+MONTH('Loan maths'!$AE$2)-MONTH(LM_first)-(DAY('Loan maths'!$AE$2)<(LM_anchor-(LM_anchor-DAY(EOMONTH('Loan maths'!$AE$2,0)))*(LM_anchor>DAY(EOMONTH('Loan maths'!$AE$2,0))))))/(LM_step+(LM_step=0)))+1))*((INT(((YEAR('Loan maths'!$AE$2)-YEAR(LM_first))*12+MONTH('Loan maths'!$AE$2)-MONTH(LM_first)-(DAY('Loan maths'!$AE$2)<(LM_anchor-(LM_anchor-DAY(EOMONTH('Loan maths'!$AE$2,0)))*(LM_anchor>DAY(EOMONTH('Loan maths'!$AE$2,0))))))/(LM_step+(LM_step=0)))+1)>LM_cycles))+LM_stub*('Loan maths'!$AE$2>=LN_maturity))-LM_paid)-1)/LM_safe)+(LM_rate=0)*(LM_out-LM_annuity*((('Loan maths'!$AE$2>=LM_first)*((INT(((YEAR('Loan maths'!$AE$2)-YEAR(LM_first))*12+MONTH('Loan maths'!$AE$2)-MONTH(LM_first)-(DAY('Loan maths'!$AE$2)<(LM_anchor-(LM_anchor-DAY(EOMONTH('Loan maths'!$AE$2,0)))*(LM_anchor>DAY(EOMONTH('Loan maths'!$AE$2,0))))))/(LM_step+(LM_step=0)))+1)+(LM_cycles-(INT(((YEAR('Loan maths'!$AE$2)-YEAR(LM_first))*12+MONTH('Loan maths'!$AE$2)-MONTH(LM_first)-(DAY('Loan maths'!$AE$2)<(LM_anchor-(LM_anchor-DAY(EOMONTH('Loan maths'!$AE$2,0)))*(LM_anchor>DAY(EOMONTH('Loan maths'!$AE$2,0))))))/(LM_step+(LM_step=0)))+1))*((INT(((YEAR('Loan maths'!$AE$2)-YEAR(LM_first))*12+MONTH('Loan maths'!$AE$2)-MONTH(LM_first)-(DAY('Loan maths'!$AE$2)<(LM_anchor-(LM_anchor-DAY(EOMONTH('Loan maths'!$AE$2,0)))*(LM_anchor>DAY(EOMONTH('Loan maths'!$AE$2,0))))))/(LM_step+(LM_step=0)))+1)>LM_cycles))+LM_stub*('Loan maths'!$AE$2>=LN_maturity))-LM_paid)))))+SUMPRODUCT(LM_live*((LM_profile<>"EIP")*(LM_profile<>"Annuity"))*(LM_end>'Loan maths'!$AD$2)*(LM_end<='Loan maths'!$AE$2)*LN_principal) -> 0 | N67: =-D67 -> 0
B68: =IF(DAY(AsAt+1)=1,TEXT(IF(DAY(AsAt+1)=1,EOMONTH(AsAt,2),EDATE(AsAt,2)),"mmm yy"),"to "&TEXT(IF(DAY(AsAt+1)=1,EOMONTH(AsAt,2),EDATE(AsAt,2)),"d mmm yy")) -> Nov 26 | C68: =SUMPRODUCT(('Deal maths'!$F$4:$F$2000>AsAt)*('Deal maths'!$E$4:$E$2000<=AsAt)*('Deal maths'!$F$4:$F$2000>IF(DAY(AsAt+1)=1,EOMONTH(AsAt,1),EDATE(AsAt,1)))*('Deal maths'!$F$4:$F$2000<=IF(DAY(AsAt+1)=1,EOMONTH(AsAt,2),EDATE(AsAt,2)))*('Deal maths'!$H$4:$H$2000+('Deal maths'!$H$4:$H$2000=0)*'Deal maths'!$D$4:$D$2000)) -> 0 | D68: =SUMPRODUCT(LM_live*(LM_profile="EIP")*LM_eip*((('Loan maths'!$AF$2>=LM_first)*((INT(((YEAR('Loan maths'!$AF$2)-YEAR(LM_first))*12+MONTH('Loan maths'!$AF$2)-MONTH(LM_first)-(DAY('Loan maths'!$AF$2)<(LM_anchor-(LM_anchor-DAY(EOMONTH('Loan maths'!$AF$2,0)))*(LM_anchor>DAY(EOMONTH('Loan maths'!$AF$2,0))))))/(LM_step+(LM_step=0)))+1)+(LM_cycles-(INT(((YEAR('Loan maths'!$AF$2)-YEAR(LM_first))*12+MONTH('Loan maths'!$AF$2)-MONTH(LM_first)-(DAY('Loan maths'!$AF$2)<(LM_anchor-(LM_anchor-DAY(EOMONTH('Loan maths'!$AF$2,0)))*(LM_anchor>DAY(EOMONTH('Loan maths'!$AF$2,0))))))/(LM_step+(LM_step=0)))+1))*((INT(((YEAR('Loan maths'!$AF$2)-YEAR(LM_first))*12+MONTH('Loan maths'!$AF$2)-MONTH(LM_first)-(DAY('Loan maths'!$AF$2)<(LM_anchor-(LM_anchor-DAY(EOMONTH('Loan maths'!$AF$2,0)))*(LM_anchor>DAY(EOMONTH('Loan maths'!$AF$2,0))))))/(LM_step+(LM_step=0)))+1)>LM_cycles))+LM_stub*('Loan maths'!$AF$2>=LN_maturity))-(('Loan maths'!$AE$2>=LM_first)*((INT(((YEAR('Loan maths'!$AE$2)-YEAR(LM_first))*12+MONTH('Loan maths'!$AE$2)-MONTH(LM_first)-(DAY('Loan maths'!$AE$2)<(LM_anchor-(LM_anchor-DAY(EOMONTH('Loan maths'!$AE$2,0)))*(LM_anchor>DAY(EOMONTH('Loan maths'!$AE$2,0))))))/(LM_step+(LM_step=0)))+1)+(LM_cycles-(INT(((YEAR('Loan maths'!$AE$2)-YEAR(LM_first))*12+MONTH('Loan maths'!$AE$2)-MONTH(LM_first)-(DAY('Loan maths'!$AE$2)<(LM_anchor-(LM_anchor-DAY(EOMONTH('Loan maths'!$AE$2,0)))*(LM_anchor>DAY(EOMONTH('Loan maths'!$AE$2,0))))))/(LM_step+(LM_step=0)))+1))*((INT(((YEAR('Loan maths'!$AE$2)-YEAR(LM_first))*12+MONTH('Loan maths'!$AE$2)-MONTH(LM_first)-(DAY('Loan maths'!$AE$2)<(LM_anchor-(LM_anchor-DAY(EOMONTH('Loan maths'!$AE$2,0)))*(LM_anchor>DAY(EOMONTH('Loan maths'!$AE$2,0))))))/(LM_step+(LM_step=0)))+1)>LM_cycles))+LM_stub*('Loan maths'!$AE$2>=LN_maturity))))+SUMPRODUCT(LM_live*(LM_profile="Annuity")*(((LM_rate>0)*(LM_out*(1+LM_rate)^((('Loan maths'!$AE$2>=LM_first)*((INT(((YEAR('Loan maths'!$AE$2)-YEAR(LM_first))*12+MONTH('Loan maths'!$AE$2)-MONTH(LM_first)-(DAY('Loan maths'!$AE$2)<(LM_anchor-(LM_anchor-DAY(EOMONTH('Loan maths'!$AE$2,0)))*(LM_anchor>DAY(EOMONTH('Loan maths'!$AE$2,0))))))/(LM_step+(LM_step=0)))+1)+(LM_cycles-(INT(((YEAR('Loan maths'!$AE$2)-YEAR(LM_first))*12+MONTH('Loan maths'!$AE$2)-MONTH(LM_first)-(DAY('Loan maths'!$AE$2)<(LM_anchor-(LM_anchor-DAY(EOMONTH('Loan maths'!$AE$2,0)))*(LM_anchor>DAY(EOMONTH('Loan maths'!$AE$2,0))))))/(LM_step+(LM_step=0)))+1))*((INT(((YEAR('Loan maths'!$AE$2)-YEAR(LM_first))*12+MONTH('Loan maths'!$AE$2)-MONTH(LM_first)-(DAY('Loan maths'!$AE$2)<(LM_anchor-(LM_anchor-DAY(EOMONTH('Loan maths'!$AE$2,0)))*(LM_anchor>DAY(EOMONTH('Loan maths'!$AE$2,0))))))/(LM_step+(LM_step=0)))+1)>LM_cycles))+LM_stub*('Loan maths'!$AE$2>=LN_maturity))-LM_paid)-LM_annuity*((1+LM_rate)^((('Loan maths'!$AE$2>=LM_first)*((INT(((YEAR('Loan maths'!$AE$2)-YEAR(LM_first))*12+MONTH('Loan maths'!$AE$2)-MONTH(LM_first)-(DAY('Loan maths'!$AE$2)<(LM_anchor-(LM_anchor-DAY(EOMONTH('Loan maths'!$AE$2,0)))*(LM_anchor>DAY(EOMONTH('Loan maths'!$AE$2,0))))))/(LM_step+(LM_step=0)))+1)+(LM_cycles-(INT(((YEAR('Loan maths'!$AE$2)-YEAR(LM_first))*12+MONTH('Loan maths'!$AE$2)-MONTH(LM_first)-(DAY('Loan maths'!$AE$2)<(LM_anchor-(LM_anchor-DAY(EOMONTH('Loan maths'!$AE$2,0)))*(LM_anchor>DAY(EOMONTH('Loan maths'!$AE$2,0))))))/(LM_step+(LM_step=0)))+1))*((INT(((YEAR('Loan maths'!$AE$2)-YEAR(LM_first))*12+MONTH('Loan maths'!$AE$2)-MONTH(LM_first)-(DAY('Loan maths'!$AE$2)<(LM_anchor-(LM_anchor-DAY(EOMONTH('Loan maths'!$AE$2,0)))*(LM_anchor>DAY(EOMONTH('Loan maths'!$AE$2,0))))))/(LM_step+(LM_step=0)))+1)>LM_cycles))+LM_stub*('Loan maths'!$AE$2>=LN_maturity))-LM_paid)-1)/LM_safe)+(LM_rate=0)*(LM_out-LM_annuity*((('Loan maths'!$AE$2>=LM_first)*((INT(((YEAR('Loan maths'!$AE$2)-YEAR(LM_first))*12+MONTH('Loan maths'!$AE$2)-MONTH(LM_first)-(DAY('Loan maths'!$AE$2)<(LM_anchor-(LM_anchor-DAY(EOMONTH('Loan maths'!$AE$2,0)))*(LM_anchor>DAY(EOMONTH('Loan maths'!$AE$2,0))))))/(LM_step+(LM_step=0)))+1)+(LM_cycles-(INT(((YEAR('Loan maths'!$AE$2)-YEAR(LM_first))*12+MONTH('Loan maths'!$AE$2)-MONTH(LM_first)-(DAY('Loan maths'!$AE$2)<(LM_anchor-(LM_anchor-DAY(EOMONTH('Loan maths'!$AE$2,0)))*(LM_anchor>DAY(EOMONTH('Loan maths'!$AE$2,0))))))/(LM_step+(LM_step=0)))+1))*((INT(((YEAR('Loan maths'!$AE$2)-YEAR(LM_first))*12+MONTH('Loan maths'!$AE$2)-MONTH(LM_first)-(DAY('Loan maths'!$AE$2)<(LM_anchor-(LM_anchor-DAY(EOMONTH('Loan maths'!$AE$2,0)))*(LM_anchor>DAY(EOMONTH('Loan maths'!$AE$2,0))))))/(LM_step+(LM_step=0)))+1)>LM_cycles))+LM_stub*('Loan maths'!$AE$2>=LN_maturity))-LM_paid)))-((LM_rate>0)*(LM_out*(1+LM_rate)^((('Loan maths'!$AF$2>=LM_first)*((INT(((YEAR('Loan maths'!$AF$2)-YEAR(LM_first))*12+MONTH('Loan maths'!$AF$2)-MONTH(LM_first)-(DAY('Loan maths'!$AF$2)<(LM_anchor-(LM_anchor-DAY(EOMONTH('Loan maths'!$AF$2,0)))*(LM_anchor>DAY(EOMONTH('Loan maths'!$AF$2,0))))))/(LM_step+(LM_step=0)))+1)+(LM_cycles-(INT(((YEAR('Loan maths'!$AF$2)-YEAR(LM_first))*12+MONTH('Loan maths'!$AF$2)-MONTH(LM_first)-(DAY('Loan maths'!$AF$2)<(LM_anchor-(LM_anchor-DAY(EOMONTH('Loan maths'!$AF$2,0)))*(LM_anchor>DAY(EOMONTH('Loan maths'!$AF$2,0))))))/(LM_step+(LM_step=0)))+1))*((INT(((YEAR('Loan maths'!$AF$2)-YEAR(LM_first))*12+MONTH('Loan maths'!$AF$2)-MONTH(LM_first)-(DAY('Loan maths'!$AF$2)<(LM_anchor-(LM_anchor-DAY(EOMONTH('Loan maths'!$AF$2,0)))*(LM_anchor>DAY(EOMONTH('Loan maths'!$AF$2,0))))))/(LM_step+(LM_step=0)))+1)>LM_cycles))+LM_stub*('Loan maths'!$AF$2>=LN_maturity))-LM_paid)-LM_annuity*((1+LM_rate)^((('Loan maths'!$AF$2>=LM_first)*((INT(((YEAR('Loan maths'!$AF$2)-YEAR(LM_first))*12+MONTH('Loan maths'!$AF$2)-MONTH(LM_first)-(DAY('Loan maths'!$AF$2)<(LM_anchor-(LM_anchor-DAY(EOMONTH('Loan maths'!$AF$2,0)))*(LM_anchor>DAY(EOMONTH('Loan maths'!$AF$2,0))))))/(LM_step+(LM_step=0)))+1)+(LM_cycles-(INT(((YEAR('Loan maths'!$AF$2)-YEAR(LM_first))*12+MONTH('Loan maths'!$AF$2)-MONTH(LM_first)-(DAY('Loan maths'!$AF$2)<(LM_anchor-(LM_anchor-DAY(EOMONTH('Loan maths'!$AF$2,0)))*(LM_anchor>DAY(EOMONTH('Loan maths'!$AF$2,0))))))/(LM_step+(LM_step=0)))+1))*((INT(((YEAR('Loan maths'!$AF$2)-YEAR(LM_first))*12+MONTH('Loan maths'!$AF$2)-MONTH(LM_first)-(DAY('Loan maths'!$AF$2)<(LM_anchor-(LM_anchor-DAY(EOMONTH('Loan maths'!$AF$2,0)))*(LM_anchor>DAY(EOMONTH('Loan maths'!$AF$2,0))))))/(LM_step+(LM_step=0)))+1)>LM_cycles))+LM_stub*('Loan maths'!$AF$2>=LN_maturity))-LM_paid)-1)/LM_safe)+(LM_rate=0)*(LM_out-LM_annuity*((('Loan maths'!$AF$2>=LM_first)*((INT(((YEAR('Loan maths'!$AF$2)-YEAR(LM_first))*12+MONTH('Loan maths'!$AF$2)-MONTH(LM_first)-(DAY('Loan maths'!$AF$2)<(LM_anchor-(LM_anchor-DAY(EOMONTH('Loan maths'!$AF$2,0)))*(LM_anchor>DAY(EOMONTH('Loan maths'!$AF$2,0))))))/(LM_step+(LM_step=0)))+1)+(LM_cycles-(INT(((YEAR('Loan maths'!$AF$2)-YEAR(LM_first))*12+MONTH('Loan maths'!$AF$2)-MONTH(LM_first)-(DAY('Loan maths'!$AF$2)<(LM_anchor-(LM_anchor-DAY(EOMONTH('Loan maths'!$AF$2,0)))*(LM_anchor>DAY(EOMONTH('Loan maths'!$AF$2,0))))))/(LM_step+(LM_step=0)))+1))*((INT(((YEAR('Loan maths'!$AF$2)-YEAR(LM_first))*12+MONTH('Loan maths'!$AF$2)-MONTH(LM_first)-(DAY('Loan maths'!$AF$2)<(LM_anchor-(LM_anchor-DAY(EOMONTH('Loan maths'!$AF$2,0)))*(LM_anchor>DAY(EOMONTH('Loan maths'!$AF$2,0))))))/(LM_step+(LM_step=0)))+1)>LM_cycles))+LM_stub*('Loan maths'!$AF$2>=LN_maturity))-LM_paid)))))+SUMPRODUCT(LM_live*((LM_profile<>"EIP")*(LM_profile<>"Annuity"))*(LM_end>'Loan maths'!$AE$2)*(LM_end<='Loan maths'!$AF$2)*LN_principal) -> 0 | N68: =-D68 -> 0
B69: =IF(DAY(AsAt+1)=1,TEXT(IF(DAY(AsAt+1)=1,EOMONTH(AsAt,3),EDATE(AsAt,3)),"mmm yy"),"to "&TEXT(IF(DAY(AsAt+1)=1,EOMONTH(AsAt,3),EDATE(AsAt,3)),"d mmm yy")) -> Dec 26 | C69: =SUMPRODUCT(('Deal maths'!$F$4:$F$2000>AsAt)*('Deal maths'!$E$4:$E$2000<=AsAt)*('Deal maths'!$F$4:$F$2000>IF(DAY(AsAt+1)=1,EOMONTH(AsAt,2),EDATE(AsAt,2)))*('Deal maths'!$F$4:$F$2000<=IF(DAY(AsAt+1)=1,EOMONTH(AsAt,3),EDATE(AsAt,3)))*('Deal maths'!$H$4:$H$2000+('Deal maths'!$H$4:$H$2000=0)*'Deal maths'!$D$4:$D$2000)) -> 0 | D69: =SUMPRODUCT(LM_live*(LM_profile="EIP")*LM_eip*((('Loan maths'!$AG$2>=LM_first)*((INT(((YEAR('Loan maths'!$AG$2)-YEAR(LM_first))*12+MONTH('Loan maths'!$AG$2)-MONTH(LM_first)-(DAY('Loan maths'!$AG$2)<(LM_anchor-(LM_anchor-DAY(EOMONTH('Loan maths'!$AG$2,0)))*(LM_anchor>DAY(EOMONTH('Loan maths'!$AG$2,0))))))/(LM_step+(LM_step=0)))+1)+(LM_cycles-(INT(((YEAR('Loan maths'!$AG$2)-YEAR(LM_first))*12+MONTH('Loan maths'!$AG$2)-MONTH(LM_first)-(DAY('Loan maths'!$AG$2)<(LM_anchor-(LM_anchor-DAY(EOMONTH('Loan maths'!$AG$2,0)))*(LM_anchor>DAY(EOMONTH('Loan maths'!$AG$2,0))))))/(LM_step+(LM_step=0)))+1))*((INT(((YEAR('Loan maths'!$AG$2)-YEAR(LM_first))*12+MONTH('Loan maths'!$AG$2)-MONTH(LM_first)-(DAY('Loan maths'!$AG$2)<(LM_anchor-(LM_anchor-DAY(EOMONTH('Loan maths'!$AG$2,0)))*(LM_anchor>DAY(EOMONTH('Loan maths'!$AG$2,0))))))/(LM_step+(LM_step=0)))+1)>LM_cycles))+LM_stub*('Loan maths'!$AG$2>=LN_maturity))-(('Loan maths'!$AF$2>=LM_first)*((INT(((YEAR('Loan maths'!$AF$2)-YEAR(LM_first))*12+MONTH('Loan maths'!$AF$2)-MONTH(LM_first)-(DAY('Loan maths'!$AF$2)<(LM_anchor-(LM_anchor-DAY(EOMONTH('Loan maths'!$AF$2,0)))*(LM_anchor>DAY(EOMONTH('Loan maths'!$AF$2,0))))))/(LM_step+(LM_step=0)))+1)+(LM_cycles-(INT(((YEAR('Loan maths'!$AF$2)-YEAR(LM_first))*12+MONTH('Loan maths'!$AF$2)-MONTH(LM_first)-(DAY('Loan maths'!$AF$2)<(LM_anchor-(LM_anchor-DAY(EOMONTH('Loan maths'!$AF$2,0)))*(LM_anchor>DAY(EOMONTH('Loan maths'!$AF$2,0))))))/(LM_step+(LM_step=0)))+1))*((INT(((YEAR('Loan maths'!$AF$2)-YEAR(LM_first))*12+MONTH('Loan maths'!$AF$2)-MONTH(LM_first)-(DAY('Loan maths'!$AF$2)<(LM_anchor-(LM_anchor-DAY(EOMONTH('Loan maths'!$AF$2,0)))*(LM_anchor>DAY(EOMONTH('Loan maths'!$AF$2,0))))))/(LM_step+(LM_step=0)))+1)>LM_cycles))+LM_stub*('Loan maths'!$AF$2>=LN_maturity))))+SUMPRODUCT(LM_live*(LM_profile="Annuity")*(((LM_rate>0)*(LM_out*(1+LM_rate)^((('Loan maths'!$AF$2>=LM_first)*((INT(((YEAR('Loan maths'!$AF$2)-YEAR(LM_first))*12+MONTH('Loan maths'!$AF$2)-MONTH(LM_first)-(DAY('Loan maths'!$AF$2)<(LM_anchor-(LM_anchor-DAY(EOMONTH('Loan maths'!$AF$2,0)))*(LM_anchor>DAY(EOMONTH('Loan maths'!$AF$2,0))))))/(LM_step+(LM_step=0)))+1)+(LM_cycles-(INT(((YEAR('Loan maths'!$AF$2)-YEAR(LM_first))*12+MONTH('Loan maths'!$AF$2)-MONTH(LM_first)-(DAY('Loan maths'!$AF$2)<(LM_anchor-(LM_anchor-DAY(EOMONTH('Loan maths'!$AF$2,0)))*(LM_anchor>DAY(EOMONTH('Loan maths'!$AF$2,0))))))/(LM_step+(LM_step=0)))+1))*((INT(((YEAR('Loan maths'!$AF$2)-YEAR(LM_first))*12+MONTH('Loan maths'!$AF$2)-MONTH(LM_first)-(DAY('Loan maths'!$AF$2)<(LM_anchor-(LM_anchor-DAY(EOMONTH('Loan maths'!$AF$2,0)))*(LM_anchor>DAY(EOMONTH('Loan maths'!$AF$2,0))))))/(LM_step+(LM_step=0)))+1)>LM_cycles))+LM_stub*('Loan maths'!$AF$2>=LN_maturity))-LM_paid)-LM_annuity*((1+LM_rate)^((('Loan maths'!$AF$2>=LM_first)*((INT(((YEAR('Loan maths'!$AF$2)-YEAR(LM_first))*12+MONTH('Loan maths'!$AF$2)-MONTH(LM_first)-(DAY('Loan maths'!$AF$2)<(LM_anchor-(LM_anchor-DAY(EOMONTH('Loan maths'!$AF$2,0)))*(LM_anchor>DAY(EOMONTH('Loan maths'!$AF$2,0))))))/(LM_step+(LM_step=0)))+1)+(LM_cycles-(INT(((YEAR('Loan maths'!$AF$2)-YEAR(LM_first))*12+MONTH('Loan maths'!$AF$2)-MONTH(LM_first)-(DAY('Loan maths'!$AF$2)<(LM_anchor-(LM_anchor-DAY(EOMONTH('Loan maths'!$AF$2,0)))*(LM_anchor>DAY(EOMONTH('Loan maths'!$AF$2,0))))))/(LM_step+(LM_step=0)))+1))*((INT(((YEAR('Loan maths'!$AF$2)-YEAR(LM_first))*12+MONTH('Loan maths'!$AF$2)-MONTH(LM_first)-(DAY('Loan maths'!$AF$2)<(LM_anchor-(LM_anchor-DAY(EOMONTH('Loan maths'!$AF$2,0)))*(LM_anchor>DAY(EOMONTH('Loan maths'!$AF$2,0))))))/(LM_step+(LM_step=0)))+1)>LM_cycles))+LM_stub*('Loan maths'!$AF$2>=LN_maturity))-LM_paid)-1)/LM_safe)+(LM_rate=0)*(LM_out-LM_annuity*((('Loan maths'!$AF$2>=LM_first)*((INT(((YEAR('Loan maths'!$AF$2)-YEAR(LM_first))*12+MONTH('Loan maths'!$AF$2)-MONTH(LM_first)-(DAY('Loan maths'!$AF$2)<(LM_anchor-(LM_anchor-DAY(EOMONTH('Loan maths'!$AF$2,0)))*(LM_anchor>DAY(EOMONTH('Loan maths'!$AF$2,0))))))/(LM_step+(LM_step=0)))+1)+(LM_cycles-(INT(((YEAR('Loan maths'!$AF$2)-YEAR(LM_first))*12+MONTH('Loan maths'!$AF$2)-MONTH(LM_first)-(DAY('Loan maths'!$AF$2)<(LM_anchor-(LM_anchor-DAY(EOMONTH('Loan maths'!$AF$2,0)))*(LM_anchor>DAY(EOMONTH('Loan maths'!$AF$2,0))))))/(LM_step+(LM_step=0)))+1))*((INT(((YEAR('Loan maths'!$AF$2)-YEAR(LM_first))*12+MONTH('Loan maths'!$AF$2)-MONTH(LM_first)-(DAY('Loan maths'!$AF$2)<(LM_anchor-(LM_anchor-DAY(EOMONTH('Loan maths'!$AF$2,0)))*(LM_anchor>DAY(EOMONTH('Loan maths'!$AF$2,0))))))/(LM_step+(LM_step=0)))+1)>LM_cycles))+LM_stub*('Loan maths'!$AF$2>=LN_maturity))-LM_paid)))-((LM_rate>0)*(LM_out*(1+LM_rate)^((('Loan maths'!$AG$2>=LM_first)*((INT(((YEAR('Loan maths'!$AG$2)-YEAR(LM_first))*12+MONTH('Loan maths'!$AG$2)-MONTH(LM_first)-(DAY('Loan maths'!$AG$2)<(LM_anchor-(LM_anchor-DAY(EOMONTH('Loan maths'!$AG$2,0)))*(LM_anchor>DAY(EOMONTH('Loan maths'!$AG$2,0))))))/(LM_step+(LM_step=0)))+1)+(LM_cycles-(INT(((YEAR('Loan maths'!$AG$2)-YEAR(LM_first))*12+MONTH('Loan maths'!$AG$2)-MONTH(LM_first)-(DAY('Loan maths'!$AG$2)<(LM_anchor-(LM_anchor-DAY(EOMONTH('Loan maths'!$AG$2,0)))*(LM_anchor>DAY(EOMONTH('Loan maths'!$AG$2,0))))))/(LM_step+(LM_step=0)))+1))*((INT(((YEAR('Loan maths'!$AG$2)-YEAR(LM_first))*12+MONTH('Loan maths'!$AG$2)-MONTH(LM_first)-(DAY('Loan maths'!$AG$2)<(LM_anchor-(LM_anchor-DAY(EOMONTH('Loan maths'!$AG$2,0)))*(LM_anchor>DAY(EOMONTH('Loan maths'!$AG$2,0))))))/(LM_step+(LM_step=0)))+1)>LM_cycles))+LM_stub*('Loan maths'!$AG$2>=LN_maturity))-LM_paid)-LM_annuity*((1+LM_rate)^((('Loan maths'!$AG$2>=LM_first)*((INT(((YEAR('Loan maths'!$AG$2)-YEAR(LM_first))*12+MONTH('Loan maths'!$AG$2)-MONTH(LM_first)-(DAY('Loan maths'!$AG$2)<(LM_anchor-(LM_anchor-DAY(EOMONTH('Loan maths'!$AG$2,0)))*(LM_anchor>DAY(EOMONTH('Loan maths'!$AG$2,0))))))/(LM_step+(LM_step=0)))+1)+(LM_cycles-(INT(((YEAR('Loan maths'!$AG$2)-YEAR(LM_first))*12+MONTH('Loan maths'!$AG$2)-MONTH(LM_first)-(DAY('Loan maths'!$AG$2)<(LM_anchor-(LM_anchor-DAY(EOMONTH('Loan maths'!$AG$2,0)))*(LM_anchor>DAY(EOMONTH('Loan maths'!$AG$2,0))))))/(LM_step+(LM_step=0)))+1))*((INT(((YEAR('Loan maths'!$AG$2)-YEAR(LM_first))*12+MONTH('Loan maths'!$AG$2)-MONTH(LM_first)-(DAY('Loan maths'!$AG$2)<(LM_anchor-(LM_anchor-DAY(EOMONTH('Loan maths'!$AG$2,0)))*(LM_anchor>DAY(EOMONTH('Loan maths'!$AG$2,0))))))/(LM_step+(LM_step=0)))+1)>LM_cycles))+LM_stub*('Loan maths'!$AG$2>=LN_maturity))-LM_paid)-1)/LM_safe)+(LM_rate=0)*(LM_out-LM_annuity*((('Loan maths'!$AG$2>=LM_first)*((INT(((YEAR('Loan maths'!$AG$2)-YEAR(LM_first))*12+MONTH('Loan maths'!$AG$2)-MONTH(LM_first)-(DAY('Loan maths'!$AG$2)<(LM_anchor-(LM_anchor-DAY(EOMONTH('Loan maths'!$AG$2,0)))*(LM_anchor>DAY(EOMONTH('Loan maths'!$AG$2,0))))))/(LM_step+(LM_step=0)))+1)+(LM_cycles-(INT(((YEAR('Loan maths'!$AG$2)-YEAR(LM_first))*12+MONTH('Loan maths'!$AG$2)-MONTH(LM_first)-(DAY('Loan maths'!$AG$2)<(LM_anchor-(LM_anchor-DAY(EOMONTH('Loan maths'!$AG$2,0)))*(LM_anchor>DAY(EOMONTH('Loan maths'!$AG$2,0))))))/(LM_step+(LM_step=0)))+1))*((INT(((YEAR('Loan maths'!$AG$2)-YEAR(LM_first))*12+MONTH('Loan maths'!$AG$2)-MONTH(LM_first)-(DAY('Loan maths'!$AG$2)<(LM_anchor-(LM_anchor-DAY(EOMONTH('Loan maths'!$AG$2,0)))*(LM_anchor>DAY(EOMONTH('Loan maths'!$AG$2,0))))))/(LM_step+(LM_step=0)))+1)>LM_cycles))+LM_stub*('Loan maths'!$AG$2>=LN_maturity))-LM_paid)))))+SUMPRODUCT(LM_live*((LM_profile<>"EIP")*(LM_profile<>"Annuity"))*(LM_end>'Loan maths'!$AF$2)*(LM_end<='Loan maths'!$AG$2)*LN_principal) -> 0 | N69: =-D69 -> 0
B70: =IF(DAY(AsAt+1)=1,TEXT(IF(DAY(AsAt+1)=1,EOMONTH(AsAt,4),EDATE(AsAt,4)),"mmm yy"),"to "&TEXT(IF(DAY(AsAt+1)=1,EOMONTH(AsAt,4),EDATE(AsAt,4)),"d mmm yy")) -> Jan 27 | C70: =SUMPRODUCT(('Deal maths'!$F$4:$F$2000>AsAt)*('Deal maths'!$E$4:$E$2000<=AsAt)*('Deal maths'!$F$4:$F$2000>IF(DAY(AsAt+1)=1,EOMONTH(AsAt,3),EDATE(AsAt,3)))*('Deal maths'!$F$4:$F$2000<=IF(DAY(AsAt+1)=1,EOMONTH(AsAt,4),EDATE(AsAt,4)))*('Deal maths'!$H$4:$H$2000+('Deal maths'!$H$4:$H$2000=0)*'Deal maths'!$D$4:$D$2000)) -> 0 | D70: =SUMPRODUCT(LM_live*(LM_profile="EIP")*LM_eip*((('Loan maths'!$AH$2>=LM_first)*((INT(((YEAR('Loan maths'!$AH$2)-YEAR(LM_first))*12+MONTH('Loan maths'!$AH$2)-MONTH(LM_first)-(DAY('Loan maths'!$AH$2)<(LM_anchor-(LM_anchor-DAY(EOMONTH('Loan maths'!$AH$2,0)))*(LM_anchor>DAY(EOMONTH('Loan maths'!$AH$2,0))))))/(LM_step+(LM_step=0)))+1)+(LM_cycles-(INT(((YEAR('Loan maths'!$AH$2)-YEAR(LM_first))*12+MONTH('Loan maths'!$AH$2)-MONTH(LM_first)-(DAY('Loan maths'!$AH$2)<(LM_anchor-(LM_anchor-DAY(EOMONTH('Loan maths'!$AH$2,0)))*(LM_anchor>DAY(EOMONTH('Loan maths'!$AH$2,0))))))/(LM_step+(LM_step=0)))+1))*((INT(((YEAR('Loan maths'!$AH$2)-YEAR(LM_first))*12+MONTH('Loan maths'!$AH$2)-MONTH(LM_first)-(DAY('Loan maths'!$AH$2)<(LM_anchor-(LM_anchor-DAY(EOMONTH('Loan maths'!$AH$2,0)))*(LM_anchor>DAY(EOMONTH('Loan maths'!$AH$2,0))))))/(LM_step+(LM_step=0)))+1)>LM_cycles))+LM_stub*('Loan maths'!$AH$2>=LN_maturity))-(('Loan maths'!$AG$2>=LM_first)*((INT(((YEAR('Loan maths'!$AG$2)-YEAR(LM_first))*12+MONTH('Loan maths'!$AG$2)-MONTH(LM_first)-(DAY('Loan maths'!$AG$2)<(LM_anchor-(LM_anchor-DAY(EOMONTH('Loan maths'!$AG$2,0)))*(LM_anchor>DAY(EOMONTH('Loan maths'!$AG$2,0))))))/(LM_step+(LM_step=0)))+1)+(LM_cycles-(INT(((YEAR('Loan maths'!$AG$2)-YEAR(LM_first))*12+MONTH('Loan maths'!$AG$2)-MONTH(LM_first)-(DAY('Loan maths'!$AG$2)<(LM_anchor-(LM_anchor-DAY(EOMONTH('Loan maths'!$AG$2,0)))*(LM_anchor>DAY(EOMONTH('Loan maths'!$AG$2,0))))))/(LM_step+(LM_step=0)))+1))*((INT(((YEAR('Loan maths'!$AG$2)-YEAR(LM_first))*12+MONTH('Loan maths'!$AG$2)-MONTH(LM_first)-(DAY('Loan maths'!$AG$2)<(LM_anchor-(LM_anchor-DAY(EOMONTH('Loan maths'!$AG$2,0)))*(LM_anchor>DAY(EOMONTH('Loan maths'!$AG$2,0))))))/(LM_step+(LM_step=0)))+1)>LM_cycles))+LM_stub*('Loan maths'!$AG$2>=LN_maturity))))+SUMPRODUCT(LM_live*(LM_profile="Annuity")*(((LM_rate>0)*(LM_out*(1+LM_rate)^((('Loan maths'!$AG$2>=LM_first)*((INT(((YEAR('Loan maths'!$AG$2)-YEAR(LM_first))*12+MONTH('Loan maths'!$AG$2)-MONTH(LM_first)-(DAY('Loan maths'!$AG$2)<(LM_anchor-(LM_anchor-DAY(EOMONTH('Loan maths'!$AG$2,0)))*(LM_anchor>DAY(EOMONTH('Loan maths'!$AG$2,0))))))/(LM_step+(LM_step=0)))+1)+(LM_cycles-(INT(((YEAR('Loan maths'!$AG$2)-YEAR(LM_first))*12+MONTH('Loan maths'!$AG$2)-MONTH(LM_first)-(DAY('Loan maths'!$AG$2)<(LM_anchor-(LM_anchor-DAY(EOMONTH('Loan maths'!$AG$2,0)))*(LM_anchor>DAY(EOMONTH('Loan maths'!$AG$2,0))))))/(LM_step+(LM_step=0)))+1))*((INT(((YEAR('Loan maths'!$AG$2)-YEAR(LM_first))*12+MONTH('Loan maths'!$AG$2)-MONTH(LM_first)-(DAY('Loan maths'!$AG$2)<(LM_anchor-(LM_anchor-DAY(EOMONTH('Loan maths'!$AG$2,0)))*(LM_anchor>DAY(EOMONTH('Loan maths'!$AG$2,0))))))/(LM_step+(LM_step=0)))+1)>LM_cycles))+LM_stub*('Loan maths'!$AG$2>=LN_maturity))-LM_paid)-LM_annuity*((1+LM_rate)^((('Loan maths'!$AG$2>=LM_first)*((INT(((YEAR('Loan maths'!$AG$2)-YEAR(LM_first))*12+MONTH('Loan maths'!$AG$2)-MONTH(LM_first)-(DAY('Loan maths'!$AG$2)<(LM_anchor-(LM_anchor-DAY(EOMONTH('Loan maths'!$AG$2,0)))*(LM_anchor>DAY(EOMONTH('Loan maths'!$AG$2,0))))))/(LM_step+(LM_step=0)))+1)+(LM_cycles-(INT(((YEAR('Loan maths'!$AG$2)-YEAR(LM_first))*12+MONTH('Loan maths'!$AG$2)-MONTH(LM_first)-(DAY('Loan maths'!$AG$2)<(LM_anchor-(LM_anchor-DAY(EOMONTH('Loan maths'!$AG$2,0)))*(LM_anchor>DAY(EOMONTH('Loan maths'!$AG$2,0))))))/(LM_step+(LM_step=0)))+1))*((INT(((YEAR('Loan maths'!$AG$2)-YEAR(LM_first))*12+MONTH('Loan maths'!$AG$2)-MONTH(LM_first)-(DAY('Loan maths'!$AG$2)<(LM_anchor-(LM_anchor-DAY(EOMONTH('Loan maths'!$AG$2,0)))*(LM_anchor>DAY(EOMONTH('Loan maths'!$AG$2,0))))))/(LM_step+(LM_step=0)))+1)>LM_cycles))+LM_stub*('Loan maths'!$AG$2>=LN_maturity))-LM_paid)-1)/LM_safe)+(LM_rate=0)*(LM_out-LM_annuity*((('Loan maths'!$AG$2>=LM_first)*((INT(((YEAR('Loan maths'!$AG$2)-YEAR(LM_first))*12+MONTH('Loan maths'!$AG$2)-MONTH(LM_first)-(DAY('Loan maths'!$AG$2)<(LM_anchor-(LM_anchor-DAY(EOMONTH('Loan maths'!$AG$2,0)))*(LM_anchor>DAY(EOMONTH('Loan maths'!$AG$2,0))))))/(LM_step+(LM_step=0)))+1)+(LM_cycles-(INT(((YEAR('Loan maths'!$AG$2)-YEAR(LM_first))*12+MONTH('Loan maths'!$AG$2)-MONTH(LM_first)-(DAY('Loan maths'!$AG$2)<(LM_anchor-(LM_anchor-DAY(EOMONTH('Loan maths'!$AG$2,0)))*(LM_anchor>DAY(EOMONTH('Loan maths'!$AG$2,0))))))/(LM_step+(LM_step=0)))+1))*((INT(((YEAR('Loan maths'!$AG$2)-YEAR(LM_first))*12+MONTH('Loan maths'!$AG$2)-MONTH(LM_first)-(DAY('Loan maths'!$AG$2)<(LM_anchor-(LM_anchor-DAY(EOMONTH('Loan maths'!$AG$2,0)))*(LM_anchor>DAY(EOMONTH('Loan maths'!$AG$2,0))))))/(LM_step+(LM_step=0)))+1)>LM_cycles))+LM_stub*('Loan maths'!$AG$2>=LN_maturity))-LM_paid)))-((LM_rate>0)*(LM_out*(1+LM_rate)^((('Loan maths'!$AH$2>=LM_first)*((INT(((YEAR('Loan maths'!$AH$2)-YEAR(LM_first))*12+MONTH('Loan maths'!$AH$2)-MONTH(LM_first)-(DAY('Loan maths'!$AH$2)<(LM_anchor-(LM_anchor-DAY(EOMONTH('Loan maths'!$AH$2,0)))*(LM_anchor>DAY(EOMONTH('Loan maths'!$AH$2,0))))))/(LM_step+(LM_step=0)))+1)+(LM_cycles-(INT(((YEAR('Loan maths'!$AH$2)-YEAR(LM_first))*12+MONTH('Loan maths'!$AH$2)-MONTH(LM_first)-(DAY('Loan maths'!$AH$2)<(LM_anchor-(LM_anchor-DAY(EOMONTH('Loan maths'!$AH$2,0)))*(LM_anchor>DAY(EOMONTH('Loan maths'!$AH$2,0))))))/(LM_step+(LM_step=0)))+1))*((INT(((YEAR('Loan maths'!$AH$2)-YEAR(LM_first))*12+MONTH('Loan maths'!$AH$2)-MONTH(LM_first)-(DAY('Loan maths'!$AH$2)<(LM_anchor-(LM_anchor-DAY(EOMONTH('Loan maths'!$AH$2,0)))*(LM_anchor>DAY(EOMONTH('Loan maths'!$AH$2,0))))))/(LM_step+(LM_step=0)))+1)>LM_cycles))+LM_stub*('Loan maths'!$AH$2>=LN_maturity))-LM_paid)-LM_annuity*((1+LM_rate)^((('Loan maths'!$AH$2>=LM_first)*((INT(((YEAR('Loan maths'!$AH$2)-YEAR(LM_first))*12+MONTH('Loan maths'!$AH$2)-MONTH(LM_first)-(DAY('Loan maths'!$AH$2)<(LM_anchor-(LM_anchor-DAY(EOMONTH('Loan maths'!$AH$2,0)))*(LM_anchor>DAY(EOMONTH('Loan maths'!$AH$2,0))))))/(LM_step+(LM_step=0)))+1)+(LM_cycles-(INT(((YEAR('Loan maths'!$AH$2)-YEAR(LM_first))*12+MONTH('Loan maths'!$AH$2)-MONTH(LM_first)-(DAY('Loan maths'!$AH$2)<(LM_anchor-(LM_anchor-DAY(EOMONTH('Loan maths'!$AH$2,0)))*(LM_anchor>DAY(EOMONTH('Loan maths'!$AH$2,0))))))/(LM_step+(LM_step=0)))+1))*((INT(((YEAR('Loan maths'!$AH$2)-YEAR(LM_first))*12+MONTH('Loan maths'!$AH$2)-MONTH(LM_first)-(DAY('Loan maths'!$AH$2)<(LM_anchor-(LM_anchor-DAY(EOMONTH('Loan maths'!$AH$2,0)))*(LM_anchor>DAY(EOMONTH('Loan maths'!$AH$2,0))))))/(LM_step+(LM_step=0)))+1)>LM_cycles))+LM_stub*('Loan maths'!$AH$2>=LN_maturity))-LM_paid)-1)/LM_safe)+(LM_rate=0)*(LM_out-LM_annuity*((('Loan maths'!$AH$2>=LM_first)*((INT(((YEAR('Loan maths'!$AH$2)-YEAR(LM_first))*12+MONTH('Loan maths'!$AH$2)-MONTH(LM_first)-(DAY('Loan maths'!$AH$2)<(LM_anchor-(LM_anchor-DAY(EOMONTH('Loan maths'!$AH$2,0)))*(LM_anchor>DAY(EOMONTH('Loan maths'!$AH$2,0))))))/(LM_step+(LM_step=0)))+1)+(LM_cycles-(INT(((YEAR('Loan maths'!$AH$2)-YEAR(LM_first))*12+MONTH('Loan maths'!$AH$2)-MONTH(LM_first)-(DAY('Loan maths'!$AH$2)<(LM_anchor-(LM_anchor-DAY(EOMONTH('Loan maths'!$AH$2,0)))*(LM_anchor>DAY(EOMONTH('Loan maths'!$AH$2,0))))))/(LM_step+(LM_step=0)))+1))*((INT(((YEAR('Loan maths'!$AH$2)-YEAR(LM_first))*12+MONTH('Loan maths'!$AH$2)-MONTH(LM_first)-(DAY('Loan maths'!$AH$2)<(LM_anchor-(LM_anchor-DAY(EOMONTH('Loan maths'!$AH$2,0)))*(LM_anchor>DAY(EOMONTH('Loan maths'!$AH$2,0))))))/(LM_step+(LM_step=0)))+1)>LM_cycles))+LM_stub*('Loan maths'!$AH$2>=LN_maturity))-LM_paid)))))+SUMPRODUCT(LM_live*((LM_profile<>"EIP")*(LM_profile<>"Annuity"))*(LM_end>'Loan maths'!$AG$2)*(LM_end<='Loan maths'!$AH$2)*LN_principal) -> 0 | N70: =-D70 -> 0
B71: =IF(DAY(AsAt+1)=1,TEXT(IF(DAY(AsAt+1)=1,EOMONTH(AsAt,5),EDATE(AsAt,5)),"mmm yy"),"to "&TEXT(IF(DAY(AsAt+1)=1,EOMONTH(AsAt,5),EDATE(AsAt,5)),"d mmm yy")) -> Feb 27 | C71: =SUMPRODUCT(('Deal maths'!$F$4:$F$2000>AsAt)*('Deal maths'!$E$4:$E$2000<=AsAt)*('Deal maths'!$F$4:$F$2000>IF(DAY(AsAt+1)=1,EOMONTH(AsAt,4),EDATE(AsAt,4)))*('Deal maths'!$F$4:$F$2000<=IF(DAY(AsAt+1)=1,EOMONTH(AsAt,5),EDATE(AsAt,5)))*('Deal maths'!$H$4:$H$2000+('Deal maths'!$H$4:$H$2000=0)*'Deal maths'!$D$4:$D$2000)) -> 0 | D71: =SUMPRODUCT(LM_live*(LM_profile="EIP")*LM_eip*((('Loan maths'!$AI$2>=LM_first)*((INT(((YEAR('Loan maths'!$AI$2)-YEAR(LM_first))*12+MONTH('Loan maths'!$AI$2)-MONTH(LM_first)-(DAY('Loan maths'!$AI$2)<(LM_anchor-(LM_anchor-DAY(EOMONTH('Loan maths'!$AI$2,0)))*(LM_anchor>DAY(EOMONTH('Loan maths'!$AI$2,0))))))/(LM_step+(LM_step=0)))+1)+(LM_cycles-(INT(((YEAR('Loan maths'!$AI$2)-YEAR(LM_first))*12+MONTH('Loan maths'!$AI$2)-MONTH(LM_first)-(DAY('Loan maths'!$AI$2)<(LM_anchor-(LM_anchor-DAY(EOMONTH('Loan maths'!$AI$2,0)))*(LM_anchor>DAY(EOMONTH('Loan maths'!$AI$2,0))))))/(LM_step+(LM_step=0)))+1))*((INT(((YEAR('Loan maths'!$AI$2)-YEAR(LM_first))*12+MONTH('Loan maths'!$AI$2)-MONTH(LM_first)-(DAY('Loan maths'!$AI$2)<(LM_anchor-(LM_anchor-DAY(EOMONTH('Loan maths'!$AI$2,0)))*(LM_anchor>DAY(EOMONTH('Loan maths'!$AI$2,0))))))/(LM_step+(LM_step=0)))+1)>LM_cycles))+LM_stub*('Loan maths'!$AI$2>=LN_maturity))-(('Loan maths'!$AH$2>=LM_first)*((INT(((YEAR('Loan maths'!$AH$2)-YEAR(LM_first))*12+MONTH('Loan maths'!$AH$2)-MONTH(LM_first)-(DAY('Loan maths'!$AH$2)<(LM_anchor-(LM_anchor-DAY(EOMONTH('Loan maths'!$AH$2,0)))*(LM_anchor>DAY(EOMONTH('Loan maths'!$AH$2,0))))))/(LM_step+(LM_step=0)))+1)+(LM_cycles-(INT(((YEAR('Loan maths'!$AH$2)-YEAR(LM_first))*12+MONTH('Loan maths'!$AH$2)-MONTH(LM_first)-(DAY('Loan maths'!$AH$2)<(LM_anchor-(LM_anchor-DAY(EOMONTH('Loan maths'!$AH$2,0)))*(LM_anchor>DAY(EOMONTH('Loan maths'!$AH$2,0))))))/(LM_step+(LM_step=0)))+1))*((INT(((YEAR('Loan maths'!$AH$2)-YEAR(LM_first))*12+MONTH('Loan maths'!$AH$2)-MONTH(LM_first)-(DAY('Loan maths'!$AH$2)<(LM_anchor-(LM_anchor-DAY(EOMONTH('Loan maths'!$AH$2,0)))*(LM_anchor>DAY(EOMONTH('Loan maths'!$AH$2,0))))))/(LM_step+(LM_step=0)))+1)>LM_cycles))+LM_stub*('Loan maths'!$AH$2>=LN_maturity))))+SUMPRODUCT(LM_live*(LM_profile="Annuity")*(((LM_rate>0)*(LM_out*(1+LM_rate)^((('Loan maths'!$AH$2>=LM_first)*((INT(((YEAR('Loan maths'!$AH$2)-YEAR(LM_first))*12+MONTH('Loan maths'!$AH$2)-MONTH(LM_first)-(DAY('Loan maths'!$AH$2)<(LM_anchor-(LM_anchor-DAY(EOMONTH('Loan maths'!$AH$2,0)))*(LM_anchor>DAY(EOMONTH('Loan maths'!$AH$2,0))))))/(LM_step+(LM_step=0)))+1)+(LM_cycles-(INT(((YEAR('Loan maths'!$AH$2)-YEAR(LM_first))*12+MONTH('Loan maths'!$AH$2)-MONTH(LM_first)-(DAY('Loan maths'!$AH$2)<(LM_anchor-(LM_anchor-DAY(EOMONTH('Loan maths'!$AH$2,0)))*(LM_anchor>DAY(EOMONTH('Loan maths'!$AH$2,0))))))/(LM_step+(LM_step=0)))+1))*((INT(((YEAR('Loan maths'!$AH$2)-YEAR(LM_first))*12+MONTH('Loan maths'!$AH$2)-MONTH(LM_first)-(DAY('Loan maths'!$AH$2)<(LM_anchor-(LM_anchor-DAY(EOMONTH('Loan maths'!$AH$2,0)))*(LM_anchor>DAY(EOMONTH('Loan maths'!$AH$2,0))))))/(LM_step+(LM_step=0)))+1)>LM_cycles))+LM_stub*('Loan maths'!$AH$2>=LN_maturity))-LM_paid)-LM_annuity*((1+LM_rate)^((('Loan maths'!$AH$2>=LM_first)*((INT(((YEAR('Loan maths'!$AH$2)-YEAR(LM_first))*12+MONTH('Loan maths'!$AH$2)-MONTH(LM_first)-(DAY('Loan maths'!$AH$2)<(LM_anchor-(LM_anchor-DAY(EOMONTH('Loan maths'!$AH$2,0)))*(LM_anchor>DAY(EOMONTH('Loan maths'!$AH$2,0))))))/(LM_step+(LM_step=0)))+1)+(LM_cycles-(INT(((YEAR('Loan maths'!$AH$2)-YEAR(LM_first))*12+MONTH('Loan maths'!$AH$2)-MONTH(LM_first)-(DAY('Loan maths'!$AH$2)<(LM_anchor-(LM_anchor-DAY(EOMONTH('Loan maths'!$AH$2,0)))*(LM_anchor>DAY(EOMONTH('Loan maths'!$AH$2,0))))))/(LM_step+(LM_step=0)))+1))*((INT(((YEAR('Loan maths'!$AH$2)-YEAR(LM_first))*12+MONTH('Loan maths'!$AH$2)-MONTH(LM_first)-(DAY('Loan maths'!$AH$2)<(LM_anchor-(LM_anchor-DAY(EOMONTH('Loan maths'!$AH$2,0)))*(LM_anchor>DAY(EOMONTH('Loan maths'!$AH$2,0))))))/(LM_step+(LM_step=0)))+1)>LM_cycles))+LM_stub*('Loan maths'!$AH$2>=LN_maturity))-LM_paid)-1)/LM_safe)+(LM_rate=0)*(LM_out-LM_annuity*((('Loan maths'!$AH$2>=LM_first)*((INT(((YEAR('Loan maths'!$AH$2)-YEAR(LM_first))*12+MONTH('Loan maths'!$AH$2)-MONTH(LM_first)-(DAY('Loan maths'!$AH$2)<(LM_anchor-(LM_anchor-DAY(EOMONTH('Loan maths'!$AH$2,0)))*(LM_anchor>DAY(EOMONTH('Loan maths'!$AH$2,0))))))/(LM_step+(LM_step=0)))+1)+(LM_cycles-(INT(((YEAR('Loan maths'!$AH$2)-YEAR(LM_first))*12+MONTH('Loan maths'!$AH$2)-MONTH(LM_first)-(DAY('Loan maths'!$AH$2)<(LM_anchor-(LM_anchor-DAY(EOMONTH('Loan maths'!$AH$2,0)))*(LM_anchor>DAY(EOMONTH('Loan maths'!$AH$2,0))))))/(LM_step+(LM_step=0)))+1))*((INT(((YEAR('Loan maths'!$AH$2)-YEAR(LM_first))*12+MONTH('Loan maths'!$AH$2)-MONTH(LM_first)-(DAY('Loan maths'!$AH$2)<(LM_anchor-(LM_anchor-DAY(EOMONTH('Loan maths'!$AH$2,0)))*(LM_anchor>DAY(EOMONTH('Loan maths'!$AH$2,0))))))/(LM_step+(LM_step=0)))+1)>LM_cycles))+LM_stub*('Loan maths'!$AH$2>=LN_maturity))-LM_paid)))-((LM_rate>0)*(LM_out*(1+LM_rate)^((('Loan maths'!$AI$2>=LM_first)*((INT(((YEAR('Loan maths'!$AI$2)-YEAR(LM_first))*12+MONTH('Loan maths'!$AI$2)-MONTH(LM_first)-(DAY('Loan maths'!$AI$2)<(LM_anchor-(LM_anchor-DAY(EOMONTH('Loan maths'!$AI$2,0)))*(LM_anchor>DAY(EOMONTH('Loan maths'!$AI$2,0))))))/(LM_step+(LM_step=0)))+1)+(LM_cycles-(INT(((YEAR('Loan maths'!$AI$2)-YEAR(LM_first))*12+MONTH('Loan maths'!$AI$2)-MONTH(LM_first)-(DAY('Loan maths'!$AI$2)<(LM_anchor-(LM_anchor-DAY(EOMONTH('Loan maths'!$AI$2,0)))*(LM_anchor>DAY(EOMONTH('Loan maths'!$AI$2,0))))))/(LM_step+(LM_step=0)))+1))*((INT(((YEAR('Loan maths'!$AI$2)-YEAR(LM_first))*12+MONTH('Loan maths'!$AI$2)-MONTH(LM_first)-(DAY('Loan maths'!$AI$2)<(LM_anchor-(LM_anchor-DAY(EOMONTH('Loan maths'!$AI$2,0)))*(LM_anchor>DAY(EOMONTH('Loan maths'!$AI$2,0))))))/(LM_step+(LM_step=0)))+1)>LM_cycles))+LM_stub*('Loan maths'!$AI$2>=LN_maturity))-LM_paid)-LM_annuity*((1+LM_rate)^((('Loan maths'!$AI$2>=LM_first)*((INT(((YEAR('Loan maths'!$AI$2)-YEAR(LM_first))*12+MONTH('Loan maths'!$AI$2)-MONTH(LM_first)-(DAY('Loan maths'!$AI$2)<(LM_anchor-(LM_anchor-DAY(EOMONTH('Loan maths'!$AI$2,0)))*(LM_anchor>DAY(EOMONTH('Loan maths'!$AI$2,0))))))/(LM_step+(LM_step=0)))+1)+(LM_cycles-(INT(((YEAR('Loan maths'!$AI$2)-YEAR(LM_first))*12+MONTH('Loan maths'!$AI$2)-MONTH(LM_first)-(DAY('Loan maths'!$AI$2)<(LM_anchor-(LM_anchor-DAY(EOMONTH('Loan maths'!$AI$2,0)))*(LM_anchor>DAY(EOMONTH('Loan maths'!$AI$2,0))))))/(LM_step+(LM_step=0)))+1))*((INT(((YEAR('Loan maths'!$AI$2)-YEAR(LM_first))*12+MONTH('Loan maths'!$AI$2)-MONTH(LM_first)-(DAY('Loan maths'!$AI$2)<(LM_anchor-(LM_anchor-DAY(EOMONTH('Loan maths'!$AI$2,0)))*(LM_anchor>DAY(EOMONTH('Loan maths'!$AI$2,0))))))/(LM_step+(LM_step=0)))+1)>LM_cycles))+LM_stub*('Loan maths'!$AI$2>=LN_maturity))-LM_paid)-1)/LM_safe)+(LM_rate=0)*(LM_out-LM_annuity*((('Loan maths'!$AI$2>=LM_first)*((INT(((YEAR('Loan maths'!$AI$2)-YEAR(LM_first))*12+MONTH('Loan maths'!$AI$2)-MONTH(LM_first)-(DAY('Loan maths'!$AI$2)<(LM_anchor-(LM_anchor-DAY(EOMONTH('Loan maths'!$AI$2,0)))*(LM_anchor>DAY(EOMONTH('Loan maths'!$AI$2,0))))))/(LM_step+(LM_step=0)))+1)+(LM_cycles-(INT(((YEAR('Loan maths'!$AI$2)-YEAR(LM_first))*12+MONTH('Loan maths'!$AI$2)-MONTH(LM_first)-(DAY('Loan maths'!$AI$2)<(LM_anchor-(LM_anchor-DAY(EOMONTH('Loan maths'!$AI$2,0)))*(LM_anchor>DAY(EOMONTH('Loan maths'!$AI$2,0))))))/(LM_step+(LM_step=0)))+1))*((INT(((YEAR('Loan maths'!$AI$2)-YEAR(LM_first))*12+MONTH('Loan maths'!$AI$2)-MONTH(LM_first)-(DAY('Loan maths'!$AI$2)<(LM_anchor-(LM_anchor-DAY(EOMONTH('Loan maths'!$AI$2,0)))*(LM_anchor>DAY(EOMONTH('Loan maths'!$AI$2,0))))))/(LM_step+(LM_step=0)))+1)>LM_cycles))+LM_stub*('Loan maths'!$AI$2>=LN_maturity))-LM_paid)))))+SUMPRODUCT(LM_live*((LM_profile<>"EIP")*(LM_profile<>"Annuity"))*(LM_end>'Loan maths'!$AH$2)*(LM_end<='Loan maths'!$AI$2)*LN_principal) -> 0 | N71: =-D71 -> 0
B72: =IF(DAY(AsAt+1)=1,TEXT(IF(DAY(AsAt+1)=1,EOMONTH(AsAt,6),EDATE(AsAt,6)),"mmm yy"),"to "&TEXT(IF(DAY(AsAt+1)=1,EOMONTH(AsAt,6),EDATE(AsAt,6)),"d mmm yy")) -> Mar 27 | C72: =SUMPRODUCT(('Deal maths'!$F$4:$F$2000>AsAt)*('Deal maths'!$E$4:$E$2000<=AsAt)*('Deal maths'!$F$4:$F$2000>IF(DAY(AsAt+1)=1,EOMONTH(AsAt,5),EDATE(AsAt,5)))*('Deal maths'!$F$4:$F$2000<=IF(DAY(AsAt+1)=1,EOMONTH(AsAt,6),EDATE(AsAt,6)))*('Deal maths'!$H$4:$H$2000+('Deal maths'!$H$4:$H$2000=0)*'Deal maths'!$D$4:$D$2000)) -> 0 | D72: =SUMPRODUCT(LM_live*(LM_profile="EIP")*LM_eip*((('Loan maths'!$AJ$2>=LM_first)*((INT(((YEAR('Loan maths'!$AJ$2)-YEAR(LM_first))*12+MONTH('Loan maths'!$AJ$2)-MONTH(LM_first)-(DAY('Loan maths'!$AJ$2)<(LM_anchor-(LM_anchor-DAY(EOMONTH('Loan maths'!$AJ$2,0)))*(LM_anchor>DAY(EOMONTH('Loan maths'!$AJ$2,0))))))/(LM_step+(LM_step=0)))+1)+(LM_cycles-(INT(((YEAR('Loan maths'!$AJ$2)-YEAR(LM_first))*12+MONTH('Loan maths'!$AJ$2)-MONTH(LM_first)-(DAY('Loan maths'!$AJ$2)<(LM_anchor-(LM_anchor-DAY(EOMONTH('Loan maths'!$AJ$2,0)))*(LM_anchor>DAY(EOMONTH('Loan maths'!$AJ$2,0))))))/(LM_step+(LM_step=0)))+1))*((INT(((YEAR('Loan maths'!$AJ$2)-YEAR(LM_first))*12+MONTH('Loan maths'!$AJ$2)-MONTH(LM_first)-(DAY('Loan maths'!$AJ$2)<(LM_anchor-(LM_anchor-DAY(EOMONTH('Loan maths'!$AJ$2,0)))*(LM_anchor>DAY(EOMONTH('Loan maths'!$AJ$2,0))))))/(LM_step+(LM_step=0)))+1)>LM_cycles))+LM_stub*('Loan maths'!$AJ$2>=LN_maturity))-(('Loan maths'!$AI$2>=LM_first)*((INT(((YEAR('Loan maths'!$AI$2)-YEAR(LM_first))*12+MONTH('Loan maths'!$AI$2)-MONTH(LM_first)-(DAY('Loan maths'!$AI$2)<(LM_anchor-(LM_anchor-DAY(EOMONTH('Loan maths'!$AI$2,0)))*(LM_anchor>DAY(EOMONTH('Loan maths'!$AI$2,0))))))/(LM_step+(LM_step=0)))+1)+(LM_cycles-(INT(((YEAR('Loan maths'!$AI$2)-YEAR(LM_first))*12+MONTH('Loan maths'!$AI$2)-MONTH(LM_first)-(DAY('Loan maths'!$AI$2)<(LM_anchor-(LM_anchor-DAY(EOMONTH('Loan maths'!$AI$2,0)))*(LM_anchor>DAY(EOMONTH('Loan maths'!$AI$2,0))))))/(LM_step+(LM_step=0)))+1))*((INT(((YEAR('Loan maths'!$AI$2)-YEAR(LM_first))*12+MONTH('Loan maths'!$AI$2)-MONTH(LM_first)-(DAY('Loan maths'!$AI$2)<(LM_anchor-(LM_anchor-DAY(EOMONTH('Loan maths'!$AI$2,0)))*(LM_anchor>DAY(EOMONTH('Loan maths'!$AI$2,0))))))/(LM_step+(LM_step=0)))+1)>LM_cycles))+LM_stub*('Loan maths'!$AI$2>=LN_maturity))))+SUMPRODUCT(LM_live*(LM_profile="Annuity")*(((LM_rate>0)*(LM_out*(1+LM_rate)^((('Loan maths'!$AI$2>=LM_first)*((INT(((YEAR('Loan maths'!$AI$2)-YEAR(LM_first))*12+MONTH('Loan maths'!$AI$2)-MONTH(LM_first)-(DAY('Loan maths'!$AI$2)<(LM_anchor-(LM_anchor-DAY(EOMONTH('Loan maths'!$AI$2,0)))*(LM_anchor>DAY(EOMONTH('Loan maths'!$AI$2,0))))))/(LM_step+(LM_step=0)))+1)+(LM_cycles-(INT(((YEAR('Loan maths'!$AI$2)-YEAR(LM_first))*12+MONTH('Loan maths'!$AI$2)-MONTH(LM_first)-(DAY('Loan maths'!$AI$2)<(LM_anchor-(LM_anchor-DAY(EOMONTH('Loan maths'!$AI$2,0)))*(LM_anchor>DAY(EOMONTH('Loan maths'!$AI$2,0))))))/(LM_step+(LM_step=0)))+1))*((INT(((YEAR('Loan maths'!$AI$2)-YEAR(LM_first))*12+MONTH('Loan maths'!$AI$2)-MONTH(LM_first)-(DAY('Loan maths'!$AI$2)<(LM_anchor-(LM_anchor-DAY(EOMONTH('Loan maths'!$AI$2,0)))*(LM_anchor>DAY(EOMONTH('Loan maths'!$AI$2,0))))))/(LM_step+(LM_step=0)))+1)>LM_cycles))+LM_stub*('Loan maths'!$AI$2>=LN_maturity))-LM_paid)-LM_annuity*((1+LM_rate)^((('Loan maths'!$AI$2>=LM_first)*((INT(((YEAR('Loan maths'!$AI$2)-YEAR(LM_first))*12+MONTH('Loan maths'!$AI$2)-MONTH(LM_first)-(DAY('Loan maths'!$AI$2)<(LM_anchor-(LM_anchor-DAY(EOMONTH('Loan maths'!$AI$2,0)))*(LM_anchor>DAY(EOMONTH('Loan maths'!$AI$2,0))))))/(LM_step+(LM_step=0)))+1)+(LM_cycles-(INT(((YEAR('Loan maths'!$AI$2)-YEAR(LM_first))*12+MONTH('Loan maths'!$AI$2)-MONTH(LM_first)-(DAY('Loan maths'!$AI$2)<(LM_anchor-(LM_anchor-DAY(EOMONTH('Loan maths'!$AI$2,0)))*(LM_anchor>DAY(EOMONTH('Loan maths'!$AI$2,0))))))/(LM_step+(LM_step=0)))+1))*((INT(((YEAR('Loan maths'!$AI$2)-YEAR(LM_first))*12+MONTH('Loan maths'!$AI$2)-MONTH(LM_first)-(DAY('Loan maths'!$AI$2)<(LM_anchor-(LM_anchor-DAY(EOMONTH('Loan maths'!$AI$2,0)))*(LM_anchor>DAY(EOMONTH('Loan maths'!$AI$2,0))))))/(LM_step+(LM_step=0)))+1)>LM_cycles))+LM_stub*('Loan maths'!$AI$2>=LN_maturity))-LM_paid)-1)/LM_safe)+(LM_rate=0)*(LM_out-LM_annuity*((('Loan maths'!$AI$2>=LM_first)*((INT(((YEAR('Loan maths'!$AI$2)-YEAR(LM_first))*12+MONTH('Loan maths'!$AI$2)-MONTH(LM_first)-(DAY('Loan maths'!$AI$2)<(LM_anchor-(LM_anchor-DAY(EOMONTH('Loan maths'!$AI$2,0)))*(LM_anchor>DAY(EOMONTH('Loan maths'!$AI$2,0))))))/(LM_step+(LM_step=0)))+1)+(LM_cycles-(INT(((YEAR('Loan maths'!$AI$2)-YEAR(LM_first))*12+MONTH('Loan maths'!$AI$2)-MONTH(LM_first)-(DAY('Loan maths'!$AI$2)<(LM_anchor-(LM_anchor-DAY(EOMONTH('Loan maths'!$AI$2,0)))*(LM_anchor>DAY(EOMONTH('Loan maths'!$AI$2,0))))))/(LM_step+(LM_step=0)))+1))*((INT(((YEAR('Loan maths'!$AI$2)-YEAR(LM_first))*12+MONTH('Loan maths'!$AI$2)-MONTH(LM_first)-(DAY('Loan maths'!$AI$2)<(LM_anchor-(LM_anchor-DAY(EOMONTH('Loan maths'!$AI$2,0)))*(LM_anchor>DAY(EOMONTH('Loan maths'!$AI$2,0))))))/(LM_step+(LM_step=0)))+1)>LM_cycles))+LM_stub*('Loan maths'!$AI$2>=LN_maturity))-LM_paid)))-((LM_rate>0)*(LM_out*(1+LM_rate)^((('Loan maths'!$AJ$2>=LM_first)*((INT(((YEAR('Loan maths'!$AJ$2)-YEAR(LM_first))*12+MONTH('Loan maths'!$AJ$2)-MONTH(LM_first)-(DAY('Loan maths'!$AJ$2)<(LM_anchor-(LM_anchor-DAY(EOMONTH('Loan maths'!$AJ$2,0)))*(LM_anchor>DAY(EOMONTH('Loan maths'!$AJ$2,0))))))/(LM_step+(LM_step=0)))+1)+(LM_cycles-(INT(((YEAR('Loan maths'!$AJ$2)-YEAR(LM_first))*12+MONTH('Loan maths'!$AJ$2)-MONTH(LM_first)-(DAY('Loan maths'!$AJ$2)<(LM_anchor-(LM_anchor-DAY(EOMONTH('Loan maths'!$AJ$2,0)))*(LM_anchor>DAY(EOMONTH('Loan maths'!$AJ$2,0))))))/(LM_step+(LM_step=0)))+1))*((INT(((YEAR('Loan maths'!$AJ$2)-YEAR(LM_first))*12+MONTH('Loan maths'!$AJ$2)-MONTH(LM_first)-(DAY('Loan maths'!$AJ$2)<(LM_anchor-(LM_anchor-DAY(EOMONTH('Loan maths'!$AJ$2,0)))*(LM_anchor>DAY(EOMONTH('Loan maths'!$AJ$2,0))))))/(LM_step+(LM_step=0)))+1)>LM_cycles))+LM_stub*('Loan maths'!$AJ$2>=LN_maturity))-LM_paid)-LM_annuity*((1+LM_rate)^((('Loan maths'!$AJ$2>=LM_first)*((INT(((YEAR('Loan maths'!$AJ$2)-YEAR(LM_first))*12+MONTH('Loan maths'!$AJ$2)-MONTH(LM_first)-(DAY('Loan maths'!$AJ$2)<(LM_anchor-(LM_anchor-DAY(EOMONTH('Loan maths'!$AJ$2,0)))*(LM_anchor>DAY(EOMONTH('Loan maths'!$AJ$2,0))))))/(LM_step+(LM_step=0)))+1)+(LM_cycles-(INT(((YEAR('Loan maths'!$AJ$2)-YEAR(LM_first))*12+MONTH('Loan maths'!$AJ$2)-MONTH(LM_first)-(DAY('Loan maths'!$AJ$2)<(LM_anchor-(LM_anchor-DAY(EOMONTH('Loan maths'!$AJ$2,0)))*(LM_anchor>DAY(EOMONTH('Loan maths'!$AJ$2,0))))))/(LM_step+(LM_step=0)))+1))*((INT(((YEAR('Loan maths'!$AJ$2)-YEAR(LM_first))*12+MONTH('Loan maths'!$AJ$2)-MONTH(LM_first)-(DAY('Loan maths'!$AJ$2)<(LM_anchor-(LM_anchor-DAY(EOMONTH('Loan maths'!$AJ$2,0)))*(LM_anchor>DAY(EOMONTH('Loan maths'!$AJ$2,0))))))/(LM_step+(LM_step=0)))+1)>LM_cycles))+LM_stub*('Loan maths'!$AJ$2>=LN_maturity))-LM_paid)-1)/LM_safe)+(LM_rate=0)*(LM_out-LM_annuity*((('Loan maths'!$AJ$2>=LM_first)*((INT(((YEAR('Loan maths'!$AJ$2)-YEAR(LM_first))*12+MONTH('Loan maths'!$AJ$2)-MONTH(LM_first)-(DAY('Loan maths'!$AJ$2)<(LM_anchor-(LM_anchor-DAY(EOMONTH('Loan maths'!$AJ$2,0)))*(LM_anchor>DAY(EOMONTH('Loan maths'!$AJ$2,0))))))/(LM_step+(LM_step=0)))+1)+(LM_cycles-(INT(((YEAR('Loan maths'!$AJ$2)-YEAR(LM_first))*12+MONTH('Loan maths'!$AJ$2)-MONTH(LM_first)-(DAY('Loan maths'!$AJ$2)<(LM_anchor-(LM_anchor-DAY(EOMONTH('Loan maths'!$AJ$2,0)))*(LM_anchor>DAY(EOMONTH('Loan maths'!$AJ$2,0))))))/(LM_step+(LM_step=0)))+1))*((INT(((YEAR('Loan maths'!$AJ$2)-YEAR(LM_first))*12+MONTH('Loan maths'!$AJ$2)-MONTH(LM_first)-(DAY('Loan maths'!$AJ$2)<(LM_anchor-(LM_anchor-DAY(EOMONTH('Loan maths'!$AJ$2,0)))*(LM_anchor>DAY(EOMONTH('Loan maths'!$AJ$2,0))))))/(LM_step+(LM_step=0)))+1)>LM_cycles))+LM_stub*('Loan maths'!$AJ$2>=LN_maturity))-LM_paid)))))+SUMPRODUCT(LM_live*((LM_profile<>"EIP")*(LM_profile<>"Annuity"))*(LM_end>'Loan maths'!$AI$2)*(LM_end<='Loan maths'!$AJ$2)*LN_principal) -> 0 | N72: =-D72 -> 0
B73: =IF(DAY(AsAt+1)=1,TEXT(IF(DAY(AsAt+1)=1,EOMONTH(AsAt,7),EDATE(AsAt,7)),"mmm yy"),"to "&TEXT(IF(DAY(AsAt+1)=1,EOMONTH(AsAt,7),EDATE(AsAt,7)),"d mmm yy")) -> Apr 27 | C73: =SUMPRODUCT(('Deal maths'!$F$4:$F$2000>AsAt)*('Deal maths'!$E$4:$E$2000<=AsAt)*('Deal maths'!$F$4:$F$2000>IF(DAY(AsAt+1)=1,EOMONTH(AsAt,6),EDATE(AsAt,6)))*('Deal maths'!$F$4:$F$2000<=IF(DAY(AsAt+1)=1,EOMONTH(AsAt,7),EDATE(AsAt,7)))*('Deal maths'!$H$4:$H$2000+('Deal maths'!$H$4:$H$2000=0)*'Deal maths'!$D$4:$D$2000)) -> 0 | D73: =SUMPRODUCT(LM_live*(LM_profile="EIP")*LM_eip*((('Loan maths'!$AK$2>=LM_first)*((INT(((YEAR('Loan maths'!$AK$2)-YEAR(LM_first))*12+MONTH('Loan maths'!$AK$2)-MONTH(LM_first)-(DAY('Loan maths'!$AK$2)<(LM_anchor-(LM_anchor-DAY(EOMONTH('Loan maths'!$AK$2,0)))*(LM_anchor>DAY(EOMONTH('Loan maths'!$AK$2,0))))))/(LM_step+(LM_step=0)))+1)+(LM_cycles-(INT(((YEAR('Loan maths'!$AK$2)-YEAR(LM_first))*12+MONTH('Loan maths'!$AK$2)-MONTH(LM_first)-(DAY('Loan maths'!$AK$2)<(LM_anchor-(LM_anchor-DAY(EOMONTH('Loan maths'!$AK$2,0)))*(LM_anchor>DAY(EOMONTH('Loan maths'!$AK$2,0))))))/(LM_step+(LM_step=0)))+1))*((INT(((YEAR('Loan maths'!$AK$2)-YEAR(LM_first))*12+MONTH('Loan maths'!$AK$2)-MONTH(LM_first)-(DAY('Loan maths'!$AK$2)<(LM_anchor-(LM_anchor-DAY(EOMONTH('Loan maths'!$AK$2,0)))*(LM_anchor>DAY(EOMONTH('Loan maths'!$AK$2,0))))))/(LM_step+(LM_step=0)))+1)>LM_cycles))+LM_stub*('Loan maths'!$AK$2>=LN_maturity))-(('Loan maths'!$AJ$2>=LM_first)*((INT(((YEAR('Loan maths'!$AJ$2)-YEAR(LM_first))*12+MONTH('Loan maths'!$AJ$2)-MONTH(LM_first)-(DAY('Loan maths'!$AJ$2)<(LM_anchor-(LM_anchor-DAY(EOMONTH('Loan maths'!$AJ$2,0)))*(LM_anchor>DAY(EOMONTH('Loan maths'!$AJ$2,0))))))/(LM_step+(LM_step=0)))+1)+(LM_cycles-(INT(((YEAR('Loan maths'!$AJ$2)-YEAR(LM_first))*12+MONTH('Loan maths'!$AJ$2)-MONTH(LM_first)-(DAY('Loan maths'!$AJ$2)<(LM_anchor-(LM_anchor-DAY(EOMONTH('Loan maths'!$AJ$2,0)))*(LM_anchor>DAY(EOMONTH('Loan maths'!$AJ$2,0))))))/(LM_step+(LM_step=0)))+1))*((INT(((YEAR('Loan maths'!$AJ$2)-YEAR(LM_first))*12+MONTH('Loan maths'!$AJ$2)-MONTH(LM_first)-(DAY('Loan maths'!$AJ$2)<(LM_anchor-(LM_anchor-DAY(EOMONTH('Loan maths'!$AJ$2,0)))*(LM_anchor>DAY(EOMONTH('Loan maths'!$AJ$2,0))))))/(LM_step+(LM_step=0)))+1)>LM_cycles))+LM_stub*('Loan maths'!$AJ$2>=LN_maturity))))+SUMPRODUCT(LM_live*(LM_profile="Annuity")*(((LM_rate>0)*(LM_out*(1+LM_rate)^((('Loan maths'!$AJ$2>=LM_first)*((INT(((YEAR('Loan maths'!$AJ$2)-YEAR(LM_first))*12+MONTH('Loan maths'!$AJ$2)-MONTH(LM_first)-(DAY('Loan maths'!$AJ$2)<(LM_anchor-(LM_anchor-DAY(EOMONTH('Loan maths'!$AJ$2,0)))*(LM_anchor>DAY(EOMONTH('Loan maths'!$AJ$2,0))))))/(LM_step+(LM_step=0)))+1)+(LM_cycles-(INT(((YEAR('Loan maths'!$AJ$2)-YEAR(LM_first))*12+MONTH('Loan maths'!$AJ$2)-MONTH(LM_first)-(DAY('Loan maths'!$AJ$2)<(LM_anchor-(LM_anchor-DAY(EOMONTH('Loan maths'!$AJ$2,0)))*(LM_anchor>DAY(EOMONTH('Loan maths'!$AJ$2,0))))))/(LM_step+(LM_step=0)))+1))*((INT(((YEAR('Loan maths'!$AJ$2)-YEAR(LM_first))*12+MONTH('Loan maths'!$AJ$2)-MONTH(LM_first)-(DAY('Loan maths'!$AJ$2)<(LM_anchor-(LM_anchor-DAY(EOMONTH('Loan maths'!$AJ$2,0)))*(LM_anchor>DAY(EOMONTH('Loan maths'!$AJ$2,0))))))/(LM_step+(LM_step=0)))+1)>LM_cycles))+LM_stub*('Loan maths'!$AJ$2>=LN_maturity))-LM_paid)-LM_annuity*((1+LM_rate)^((('Loan maths'!$AJ$2>=LM_first)*((INT(((YEAR('Loan maths'!$AJ$2)-YEAR(LM_first))*12+MONTH('Loan maths'!$AJ$2)-MONTH(LM_first)-(DAY('Loan maths'!$AJ$2)<(LM_anchor-(LM_anchor-DAY(EOMONTH('Loan maths'!$AJ$2,0)))*(LM_anchor>DAY(EOMONTH('Loan maths'!$AJ$2,0))))))/(LM_step+(LM_step=0)))+1)+(LM_cycles-(INT(((YEAR('Loan maths'!$AJ$2)-YEAR(LM_first))*12+MONTH('Loan maths'!$AJ$2)-MONTH(LM_first)-(DAY('Loan maths'!$AJ$2)<(LM_anchor-(LM_anchor-DAY(EOMONTH('Loan maths'!$AJ$2,0)))*(LM_anchor>DAY(EOMONTH('Loan maths'!$AJ$2,0))))))/(LM_step+(LM_step=0)))+1))*((INT(((YEAR('Loan maths'!$AJ$2)-YEAR(LM_first))*12+MONTH('Loan maths'!$AJ$2)-MONTH(LM_first)-(DAY('Loan maths'!$AJ$2)<(LM_anchor-(LM_anchor-DAY(EOMONTH('Loan maths'!$AJ$2,0)))*(LM_anchor>DAY(EOMONTH('Loan maths'!$AJ$2,0))))))/(LM_step+(LM_step=0)))+1)>LM_cycles))+LM_stub*('Loan maths'!$AJ$2>=LN_maturity))-LM_paid)-1)/LM_safe)+(LM_rate=0)*(LM_out-LM_annuity*((('Loan maths'!$AJ$2>=LM_first)*((INT(((YEAR('Loan maths'!$AJ$2)-YEAR(LM_first))*12+MONTH('Loan maths'!$AJ$2)-MONTH(LM_first)-(DAY('Loan maths'!$AJ$2)<(LM_anchor-(LM_anchor-DAY(EOMONTH('Loan maths'!$AJ$2,0)))*(LM_anchor>DAY(EOMONTH('Loan maths'!$AJ$2,0))))))/(LM_step+(LM_step=0)))+1)+(LM_cycles-(INT(((YEAR('Loan maths'!$AJ$2)-YEAR(LM_first))*12+MONTH('Loan maths'!$AJ$2)-MONTH(LM_first)-(DAY('Loan maths'!$AJ$2)<(LM_anchor-(LM_anchor-DAY(EOMONTH('Loan maths'!$AJ$2,0)))*(LM_anchor>DAY(EOMONTH('Loan maths'!$AJ$2,0))))))/(LM_step+(LM_step=0)))+1))*((INT(((YEAR('Loan maths'!$AJ$2)-YEAR(LM_first))*12+MONTH('Loan maths'!$AJ$2)-MONTH(LM_first)-(DAY('Loan maths'!$AJ$2)<(LM_anchor-(LM_anchor-DAY(EOMONTH('Loan maths'!$AJ$2,0)))*(LM_anchor>DAY(EOMONTH('Loan maths'!$AJ$2,0))))))/(LM_step+(LM_step=0)))+1)>LM_cycles))+LM_stub*('Loan maths'!$AJ$2>=LN_maturity))-LM_paid)))-((LM_rate>0)*(LM_out*(1+LM_rate)^((('Loan maths'!$AK$2>=LM_first)*((INT(((YEAR('Loan maths'!$AK$2)-YEAR(LM_first))*12+MONTH('Loan maths'!$AK$2)-MONTH(LM_first)-(DAY('Loan maths'!$AK$2)<(LM_anchor-(LM_anchor-DAY(EOMONTH('Loan maths'!$AK$2,0)))*(LM_anchor>DAY(EOMONTH('Loan maths'!$AK$2,0))))))/(LM_step+(LM_step=0)))+1)+(LM_cycles-(INT(((YEAR('Loan maths'!$AK$2)-YEAR(LM_first))*12+MONTH('Loan maths'!$AK$2)-MONTH(LM_first)-(DAY('Loan maths'!$AK$2)<(LM_anchor-(LM_anchor-DAY(EOMONTH('Loan maths'!$AK$2,0)))*(LM_anchor>DAY(EOMONTH('Loan maths'!$AK$2,0))))))/(LM_step+(LM_step=0)))+1))*((INT(((YEAR('Loan maths'!$AK$2)-YEAR(LM_first))*12+MONTH('Loan maths'!$AK$2)-MONTH(LM_first)-(DAY('Loan maths'!$AK$2)<(LM_anchor-(LM_anchor-DAY(EOMONTH('Loan maths'!$AK$2,0)))*(LM_anchor>DAY(EOMONTH('Loan maths'!$AK$2,0))))))/(LM_step+(LM_step=0)))+1)>LM_cycles))+LM_stub*('Loan maths'!$AK$2>=LN_maturity))-LM_paid)-LM_annuity*((1+LM_rate)^((('Loan maths'!$AK$2>=LM_first)*((INT(((YEAR('Loan maths'!$AK$2)-YEAR(LM_first))*12+MONTH('Loan maths'!$AK$2)-MONTH(LM_first)-(DAY('Loan maths'!$AK$2)<(LM_anchor-(LM_anchor-DAY(EOMONTH('Loan maths'!$AK$2,0)))*(LM_anchor>DAY(EOMONTH('Loan maths'!$AK$2,0))))))/(LM_step+(LM_step=0)))+1)+(LM_cycles-(INT(((YEAR('Loan maths'!$AK$2)-YEAR(LM_first))*12+MONTH('Loan maths'!$AK$2)-MONTH(LM_first)-(DAY('Loan maths'!$AK$2)<(LM_anchor-(LM_anchor-DAY(EOMONTH('Loan maths'!$AK$2,0)))*(LM_anchor>DAY(EOMONTH('Loan maths'!$AK$2,0))))))/(LM_step+(LM_step=0)))+1))*((INT(((YEAR('Loan maths'!$AK$2)-YEAR(LM_first))*12+MONTH('Loan maths'!$AK$2)-MONTH(LM_first)-(DAY('Loan maths'!$AK$2)<(LM_anchor-(LM_anchor-DAY(EOMONTH('Loan maths'!$AK$2,0)))*(LM_anchor>DAY(EOMONTH('Loan maths'!$AK$2,0))))))/(LM_step+(LM_step=0)))+1)>LM_cycles))+LM_stub*('Loan maths'!$AK$2>=LN_maturity))-LM_paid)-1)/LM_safe)+(LM_rate=0)*(LM_out-LM_annuity*((('Loan maths'!$AK$2>=LM_first)*((INT(((YEAR('Loan maths'!$AK$2)-YEAR(LM_first))*12+MONTH('Loan maths'!$AK$2)-MONTH(LM_first)-(DAY('Loan maths'!$AK$2)<(LM_anchor-(LM_anchor-DAY(EOMONTH('Loan maths'!$AK$2,0)))*(LM_anchor>DAY(EOMONTH('Loan maths'!$AK$2,0))))))/(LM_step+(LM_step=0)))+1)+(LM_cycles-(INT(((YEAR('Loan maths'!$AK$2)-YEAR(LM_first))*12+MONTH('Loan maths'!$AK$2)-MONTH(LM_first)-(DAY('Loan maths'!$AK$2)<(LM_anchor-(LM_anchor-DAY(EOMONTH('Loan maths'!$AK$2,0)))*(LM_anchor>DAY(EOMONTH('Loan maths'!$AK$2,0))))))/(LM_step+(LM_step=0)))+1))*((INT(((YEAR('Loan maths'!$AK$2)-YEAR(LM_first))*12+MONTH('Loan maths'!$AK$2)-MONTH(LM_first)-(DAY('Loan maths'!$AK$2)<(LM_anchor-(LM_anchor-DAY(EOMONTH('Loan maths'!$AK$2,0)))*(LM_anchor>DAY(EOMONTH('Loan maths'!$AK$2,0))))))/(LM_step+(LM_step=0)))+1)>LM_cycles))+LM_stub*('Loan maths'!$AK$2>=LN_maturity))-LM_paid)))))+SUMPRODUCT(LM_live*((LM_profile<>"EIP")*(LM_profile<>"Annuity"))*(LM_end>'Loan maths'!$AJ$2)*(LM_end<='Loan maths'!$AK$2)*LN_principal) -> 0 | N73: =-D73 -> 0
B74: =IF(DAY(AsAt+1)=1,TEXT(IF(DAY(AsAt+1)=1,EOMONTH(AsAt,8),EDATE(AsAt,8)),"mmm yy"),"to "&TEXT(IF(DAY(AsAt+1)=1,EOMONTH(AsAt,8),EDATE(AsAt,8)),"d mmm yy")) -> May 27 | C74: =SUMPRODUCT(('Deal maths'!$F$4:$F$2000>AsAt)*('Deal maths'!$E$4:$E$2000<=AsAt)*('Deal maths'!$F$4:$F$2000>IF(DAY(AsAt+1)=1,EOMONTH(AsAt,7),EDATE(AsAt,7)))*('Deal maths'!$F$4:$F$2000<=IF(DAY(AsAt+1)=1,EOMONTH(AsAt,8),EDATE(AsAt,8)))*('Deal maths'!$H$4:$H$2000+('Deal maths'!$H$4:$H$2000=0)*'Deal maths'!$D$4:$D$2000)) -> 0 | D74: =SUMPRODUCT(LM_live*(LM_profile="EIP")*LM_eip*((('Loan maths'!$AL$2>=LM_first)*((INT(((YEAR('Loan maths'!$AL$2)-YEAR(LM_first))*12+MONTH('Loan maths'!$AL$2)-MONTH(LM_first)-(DAY('Loan maths'!$AL$2)<(LM_anchor-(LM_anchor-DAY(EOMONTH('Loan maths'!$AL$2,0)))*(LM_anchor>DAY(EOMONTH('Loan maths'!$AL$2,0))))))/(LM_step+(LM_step=0)))+1)+(LM_cycles-(INT(((YEAR('Loan maths'!$AL$2)-YEAR(LM_first))*12+MONTH('Loan maths'!$AL$2)-MONTH(LM_first)-(DAY('Loan maths'!$AL$2)<(LM_anchor-(LM_anchor-DAY(EOMONTH('Loan maths'!$AL$2,0)))*(LM_anchor>DAY(EOMONTH('Loan maths'!$AL$2,0))))))/(LM_step+(LM_step=0)))+1))*((INT(((YEAR('Loan maths'!$AL$2)-YEAR(LM_first))*12+MONTH('Loan maths'!$AL$2)-MONTH(LM_first)-(DAY('Loan maths'!$AL$2)<(LM_anchor-(LM_anchor-DAY(EOMONTH('Loan maths'!$AL$2,0)))*(LM_anchor>DAY(EOMONTH('Loan maths'!$AL$2,0))))))/(LM_step+(LM_step=0)))+1)>LM_cycles))+LM_stub*('Loan maths'!$AL$2>=LN_maturity))-(('Loan maths'!$AK$2>=LM_first)*((INT(((YEAR('Loan maths'!$AK$2)-YEAR(LM_first))*12+MONTH('Loan maths'!$AK$2)-MONTH(LM_first)-(DAY('Loan maths'!$AK$2)<(LM_anchor-(LM_anchor-DAY(EOMONTH('Loan maths'!$AK$2,0)))*(LM_anchor>DAY(EOMONTH('Loan maths'!$AK$2,0))))))/(LM_step+(LM_step=0)))+1)+(LM_cycles-(INT(((YEAR('Loan maths'!$AK$2)-YEAR(LM_first))*12+MONTH('Loan maths'!$AK$2)-MONTH(LM_first)-(DAY('Loan maths'!$AK$2)<(LM_anchor-(LM_anchor-DAY(EOMONTH('Loan maths'!$AK$2,0)))*(LM_anchor>DAY(EOMONTH('Loan maths'!$AK$2,0))))))/(LM_step+(LM_step=0)))+1))*((INT(((YEAR('Loan maths'!$AK$2)-YEAR(LM_first))*12+MONTH('Loan maths'!$AK$2)-MONTH(LM_first)-(DAY('Loan maths'!$AK$2)<(LM_anchor-(LM_anchor-DAY(EOMONTH('Loan maths'!$AK$2,0)))*(LM_anchor>DAY(EOMONTH('Loan maths'!$AK$2,0))))))/(LM_step+(LM_step=0)))+1)>LM_cycles))+LM_stub*('Loan maths'!$AK$2>=LN_maturity))))+SUMPRODUCT(LM_live*(LM_profile="Annuity")*(((LM_rate>0)*(LM_out*(1+LM_rate)^((('Loan maths'!$AK$2>=LM_first)*((INT(((YEAR('Loan maths'!$AK$2)-YEAR(LM_first))*12+MONTH('Loan maths'!$AK$2)-MONTH(LM_first)-(DAY('Loan maths'!$AK$2)<(LM_anchor-(LM_anchor-DAY(EOMONTH('Loan maths'!$AK$2,0)))*(LM_anchor>DAY(EOMONTH('Loan maths'!$AK$2,0))))))/(LM_step+(LM_step=0)))+1)+(LM_cycles-(INT(((YEAR('Loan maths'!$AK$2)-YEAR(LM_first))*12+MONTH('Loan maths'!$AK$2)-MONTH(LM_first)-(DAY('Loan maths'!$AK$2)<(LM_anchor-(LM_anchor-DAY(EOMONTH('Loan maths'!$AK$2,0)))*(LM_anchor>DAY(EOMONTH('Loan maths'!$AK$2,0))))))/(LM_step+(LM_step=0)))+1))*((INT(((YEAR('Loan maths'!$AK$2)-YEAR(LM_first))*12+MONTH('Loan maths'!$AK$2)-MONTH(LM_first)-(DAY('Loan maths'!$AK$2)<(LM_anchor-(LM_anchor-DAY(EOMONTH('Loan maths'!$AK$2,0)))*(LM_anchor>DAY(EOMONTH('Loan maths'!$AK$2,0))))))/(LM_step+(LM_step=0)))+1)>LM_cycles))+LM_stub*('Loan maths'!$AK$2>=LN_maturity))-LM_paid)-LM_annuity*((1+LM_rate)^((('Loan maths'!$AK$2>=LM_first)*((INT(((YEAR('Loan maths'!$AK$2)-YEAR(LM_first))*12+MONTH('Loan maths'!$AK$2)-MONTH(LM_first)-(DAY('Loan maths'!$AK$2)<(LM_anchor-(LM_anchor-DAY(EOMONTH('Loan maths'!$AK$2,0)))*(LM_anchor>DAY(EOMONTH('Loan maths'!$AK$2,0))))))/(LM_step+(LM_step=0)))+1)+(LM_cycles-(INT(((YEAR('Loan maths'!$AK$2)-YEAR(LM_first))*12+MONTH('Loan maths'!$AK$2)-MONTH(LM_first)-(DAY('Loan maths'!$AK$2)<(LM_anchor-(LM_anchor-DAY(EOMONTH('Loan maths'!$AK$2,0)))*(LM_anchor>DAY(EOMONTH('Loan maths'!$AK$2,0))))))/(LM_step+(LM_step=0)))+1))*((INT(((YEAR('Loan maths'!$AK$2)-YEAR(LM_first))*12+MONTH('Loan maths'!$AK$2)-MONTH(LM_first)-(DAY('Loan maths'!$AK$2)<(LM_anchor-(LM_anchor-DAY(EOMONTH('Loan maths'!$AK$2,0)))*(LM_anchor>DAY(EOMONTH('Loan maths'!$AK$2,0))))))/(LM_step+(LM_step=0)))+1)>LM_cycles))+LM_stub*('Loan maths'!$AK$2>=LN_maturity))-LM_paid)-1)/LM_safe)+(LM_rate=0)*(LM_out-LM_annuity*((('Loan maths'!$AK$2>=LM_first)*((INT(((YEAR('Loan maths'!$AK$2)-YEAR(LM_first))*12+MONTH('Loan maths'!$AK$2)-MONTH(LM_first)-(DAY('Loan maths'!$AK$2)<(LM_anchor-(LM_anchor-DAY(EOMONTH('Loan maths'!$AK$2,0)))*(LM_anchor>DAY(EOMONTH('Loan maths'!$AK$2,0))))))/(LM_step+(LM_step=0)))+1)+(LM_cycles-(INT(((YEAR('Loan maths'!$AK$2)-YEAR(LM_first))*12+MONTH('Loan maths'!$AK$2)-MONTH(LM_first)-(DAY('Loan maths'!$AK$2)<(LM_anchor-(LM_anchor-DAY(EOMONTH('Loan maths'!$AK$2,0)))*(LM_anchor>DAY(EOMONTH('Loan maths'!$AK$2,0))))))/(LM_step+(LM_step=0)))+1))*((INT(((YEAR('Loan maths'!$AK$2)-YEAR(LM_first))*12+MONTH('Loan maths'!$AK$2)-MONTH(LM_first)-(DAY('Loan maths'!$AK$2)<(LM_anchor-(LM_anchor-DAY(EOMONTH('Loan maths'!$AK$2,0)))*(LM_anchor>DAY(EOMONTH('Loan maths'!$AK$2,0))))))/(LM_step+(LM_step=0)))+1)>LM_cycles))+LM_stub*('Loan maths'!$AK$2>=LN_maturity))-LM_paid)))-((LM_rate>0)*(LM_out*(1+LM_rate)^((('Loan maths'!$AL$2>=LM_first)*((INT(((YEAR('Loan maths'!$AL$2)-YEAR(LM_first))*12+MONTH('Loan maths'!$AL$2)-MONTH(LM_first)-(DAY('Loan maths'!$AL$2)<(LM_anchor-(LM_anchor-DAY(EOMONTH('Loan maths'!$AL$2,0)))*(LM_anchor>DAY(EOMONTH('Loan maths'!$AL$2,0))))))/(LM_step+(LM_step=0)))+1)+(LM_cycles-(INT(((YEAR('Loan maths'!$AL$2)-YEAR(LM_first))*12+MONTH('Loan maths'!$AL$2)-MONTH(LM_first)-(DAY('Loan maths'!$AL$2)<(LM_anchor-(LM_anchor-DAY(EOMONTH('Loan maths'!$AL$2,0)))*(LM_anchor>DAY(EOMONTH('Loan maths'!$AL$2,0))))))/(LM_step+(LM_step=0)))+1))*((INT(((YEAR('Loan maths'!$AL$2)-YEAR(LM_first))*12+MONTH('Loan maths'!$AL$2)-MONTH(LM_first)-(DAY('Loan maths'!$AL$2)<(LM_anchor-(LM_anchor-DAY(EOMONTH('Loan maths'!$AL$2,0)))*(LM_anchor>DAY(EOMONTH('Loan maths'!$AL$2,0))))))/(LM_step+(LM_step=0)))+1)>LM_cycles))+LM_stub*('Loan maths'!$AL$2>=LN_maturity))-LM_paid)-LM_annuity*((1+LM_rate)^((('Loan maths'!$AL$2>=LM_first)*((INT(((YEAR('Loan maths'!$AL$2)-YEAR(LM_first))*12+MONTH('Loan maths'!$AL$2)-MONTH(LM_first)-(DAY('Loan maths'!$AL$2)<(LM_anchor-(LM_anchor-DAY(EOMONTH('Loan maths'!$AL$2,0)))*(LM_anchor>DAY(EOMONTH('Loan maths'!$AL$2,0))))))/(LM_step+(LM_step=0)))+1)+(LM_cycles-(INT(((YEAR('Loan maths'!$AL$2)-YEAR(LM_first))*12+MONTH('Loan maths'!$AL$2)-MONTH(LM_first)-(DAY('Loan maths'!$AL$2)<(LM_anchor-(LM_anchor-DAY(EOMONTH('Loan maths'!$AL$2,0)))*(LM_anchor>DAY(EOMONTH('Loan maths'!$AL$2,0))))))/(LM_step+(LM_step=0)))+1))*((INT(((YEAR('Loan maths'!$AL$2)-YEAR(LM_first))*12+MONTH('Loan maths'!$AL$2)-MONTH(LM_first)-(DAY('Loan maths'!$AL$2)<(LM_anchor-(LM_anchor-DAY(EOMONTH('Loan maths'!$AL$2,0)))*(LM_anchor>DAY(EOMONTH('Loan maths'!$AL$2,0))))))/(LM_step+(LM_step=0)))+1)>LM_cycles))+LM_stub*('Loan maths'!$AL$2>=LN_maturity))-LM_paid)-1)/LM_safe)+(LM_rate=0)*(LM_out-LM_annuity*((('Loan maths'!$AL$2>=LM_first)*((INT(((YEAR('Loan maths'!$AL$2)-YEAR(LM_first))*12+MONTH('Loan maths'!$AL$2)-MONTH(LM_first)-(DAY('Loan maths'!$AL$2)<(LM_anchor-(LM_anchor-DAY(EOMONTH('Loan maths'!$AL$2,0)))*(LM_anchor>DAY(EOMONTH('Loan maths'!$AL$2,0))))))/(LM_step+(LM_step=0)))+1)+(LM_cycles-(INT(((YEAR('Loan maths'!$AL$2)-YEAR(LM_first))*12+MONTH('Loan maths'!$AL$2)-MONTH(LM_first)-(DAY('Loan maths'!$AL$2)<(LM_anchor-(LM_anchor-DAY(EOMONTH('Loan maths'!$AL$2,0)))*(LM_anchor>DAY(EOMONTH('Loan maths'!$AL$2,0))))))/(LM_step+(LM_step=0)))+1))*((INT(((YEAR('Loan maths'!$AL$2)-YEAR(LM_first))*12+MONTH('Loan maths'!$AL$2)-MONTH(LM_first)-(DAY('Loan maths'!$AL$2)<(LM_anchor-(LM_anchor-DAY(EOMONTH('Loan maths'!$AL$2,0)))*(LM_anchor>DAY(EOMONTH('Loan maths'!$AL$2,0))))))/(LM_step+(LM_step=0)))+1)>LM_cycles))+LM_stub*('Loan maths'!$AL$2>=LN_maturity))-LM_paid)))))+SUMPRODUCT(LM_live*((LM_profile<>"EIP")*(LM_profile<>"Annuity"))*(LM_end>'Loan maths'!$AK$2)*(LM_end<='Loan maths'!$AL$2)*LN_principal) -> 0 | N74: =-D74 -> 0
B75: =IF(DAY(AsAt+1)=1,TEXT(IF(DAY(AsAt+1)=1,EOMONTH(AsAt,9),EDATE(AsAt,9)),"mmm yy"),"to "&TEXT(IF(DAY(AsAt+1)=1,EOMONTH(AsAt,9),EDATE(AsAt,9)),"d mmm yy")) -> Jun 27 | C75: =SUMPRODUCT(('Deal maths'!$F$4:$F$2000>AsAt)*('Deal maths'!$E$4:$E$2000<=AsAt)*('Deal maths'!$F$4:$F$2000>IF(DAY(AsAt+1)=1,EOMONTH(AsAt,8),EDATE(AsAt,8)))*('Deal maths'!$F$4:$F$2000<=IF(DAY(AsAt+1)=1,EOMONTH(AsAt,9),EDATE(AsAt,9)))*('Deal maths'!$H$4:$H$2000+('Deal maths'!$H$4:$H$2000=0)*'Deal maths'!$D$4:$D$2000)) -> 0 | D75: =SUMPRODUCT(LM_live*(LM_profile="EIP")*LM_eip*((('Loan maths'!$AM$2>=LM_first)*((INT(((YEAR('Loan maths'!$AM$2)-YEAR(LM_first))*12+MONTH('Loan maths'!$AM$2)-MONTH(LM_first)-(DAY('Loan maths'!$AM$2)<(LM_anchor-(LM_anchor-DAY(EOMONTH('Loan maths'!$AM$2,0)))*(LM_anchor>DAY(EOMONTH('Loan maths'!$AM$2,0))))))/(LM_step+(LM_step=0)))+1)+(LM_cycles-(INT(((YEAR('Loan maths'!$AM$2)-YEAR(LM_first))*12+MONTH('Loan maths'!$AM$2)-MONTH(LM_first)-(DAY('Loan maths'!$AM$2)<(LM_anchor-(LM_anchor-DAY(EOMONTH('Loan maths'!$AM$2,0)))*(LM_anchor>DAY(EOMONTH('Loan maths'!$AM$2,0))))))/(LM_step+(LM_step=0)))+1))*((INT(((YEAR('Loan maths'!$AM$2)-YEAR(LM_first))*12+MONTH('Loan maths'!$AM$2)-MONTH(LM_first)-(DAY('Loan maths'!$AM$2)<(LM_anchor-(LM_anchor-DAY(EOMONTH('Loan maths'!$AM$2,0)))*(LM_anchor>DAY(EOMONTH('Loan maths'!$AM$2,0))))))/(LM_step+(LM_step=0)))+1)>LM_cycles))+LM_stub*('Loan maths'!$AM$2>=LN_maturity))-(('Loan maths'!$AL$2>=LM_first)*((INT(((YEAR('Loan maths'!$AL$2)-YEAR(LM_first))*12+MONTH('Loan maths'!$AL$2)-MONTH(LM_first)-(DAY('Loan maths'!$AL$2)<(LM_anchor-(LM_anchor-DAY(EOMONTH('Loan maths'!$AL$2,0)))*(LM_anchor>DAY(EOMONTH('Loan maths'!$AL$2,0))))))/(LM_step+(LM_step=0)))+1)+(LM_cycles-(INT(((YEAR('Loan maths'!$AL$2)-YEAR(LM_first))*12+MONTH('Loan maths'!$AL$2)-MONTH(LM_first)-(DAY('Loan maths'!$AL$2)<(LM_anchor-(LM_anchor-DAY(EOMONTH('Loan maths'!$AL$2,0)))*(LM_anchor>DAY(EOMONTH('Loan maths'!$AL$2,0))))))/(LM_step+(LM_step=0)))+1))*((INT(((YEAR('Loan maths'!$AL$2)-YEAR(LM_first))*12+MONTH('Loan maths'!$AL$2)-MONTH(LM_first)-(DAY('Loan maths'!$AL$2)<(LM_anchor-(LM_anchor-DAY(EOMONTH('Loan maths'!$AL$2,0)))*(LM_anchor>DAY(EOMONTH('Loan maths'!$AL$2,0))))))/(LM_step+(LM_step=0)))+1)>LM_cycles))+LM_stub*('Loan maths'!$AL$2>=LN_maturity))))+SUMPRODUCT(LM_live*(LM_profile="Annuity")*(((LM_rate>0)*(LM_out*(1+LM_rate)^((('Loan maths'!$AL$2>=LM_first)*((INT(((YEAR('Loan maths'!$AL$2)-YEAR(LM_first))*12+MONTH('Loan maths'!$AL$2)-MONTH(LM_first)-(DAY('Loan maths'!$AL$2)<(LM_anchor-(LM_anchor-DAY(EOMONTH('Loan maths'!$AL$2,0)))*(LM_anchor>DAY(EOMONTH('Loan maths'!$AL$2,0))))))/(LM_step+(LM_step=0)))+1)+(LM_cycles-(INT(((YEAR('Loan maths'!$AL$2)-YEAR(LM_first))*12+MONTH('Loan maths'!$AL$2)-MONTH(LM_first)-(DAY('Loan maths'!$AL$2)<(LM_anchor-(LM_anchor-DAY(EOMONTH('Loan maths'!$AL$2,0)))*(LM_anchor>DAY(EOMONTH('Loan maths'!$AL$2,0))))))/(LM_step+(LM_step=0)))+1))*((INT(((YEAR('Loan maths'!$AL$2)-YEAR(LM_first))*12+MONTH('Loan maths'!$AL$2)-MONTH(LM_first)-(DAY('Loan maths'!$AL$2)<(LM_anchor-(LM_anchor-DAY(EOMONTH('Loan maths'!$AL$2,0)))*(LM_anchor>DAY(EOMONTH('Loan maths'!$AL$2,0))))))/(LM_step+(LM_step=0)))+1)>LM_cycles))+LM_stub*('Loan maths'!$AL$2>=LN_maturity))-LM_paid)-LM_annuity*((1+LM_rate)^((('Loan maths'!$AL$2>=LM_first)*((INT(((YEAR('Loan maths'!$AL$2)-YEAR(LM_first))*12+MONTH('Loan maths'!$AL$2)-MONTH(LM_first)-(DAY('Loan maths'!$AL$2)<(LM_anchor-(LM_anchor-DAY(EOMONTH('Loan maths'!$AL$2,0)))*(LM_anchor>DAY(EOMONTH('Loan maths'!$AL$2,0))))))/(LM_step+(LM_step=0)))+1)+(LM_cycles-(INT(((YEAR('Loan maths'!$AL$2)-YEAR(LM_first))*12+MONTH('Loan maths'!$AL$2)-MONTH(LM_first)-(DAY('Loan maths'!$AL$2)<(LM_anchor-(LM_anchor-DAY(EOMONTH('Loan maths'!$AL$2,0)))*(LM_anchor>DAY(EOMONTH('Loan maths'!$AL$2,0))))))/(LM_step+(LM_step=0)))+1))*((INT(((YEAR('Loan maths'!$AL$2)-YEAR(LM_first))*12+MONTH('Loan maths'!$AL$2)-MONTH(LM_first)-(DAY('Loan maths'!$AL$2)<(LM_anchor-(LM_anchor-DAY(EOMONTH('Loan maths'!$AL$2,0)))*(LM_anchor>DAY(EOMONTH('Loan maths'!$AL$2,0))))))/(LM_step+(LM_step=0)))+1)>LM_cycles))+LM_stub*('Loan maths'!$AL$2>=LN_maturity))-LM_paid)-1)/LM_safe)+(LM_rate=0)*(LM_out-LM_annuity*((('Loan maths'!$AL$2>=LM_first)*((INT(((YEAR('Loan maths'!$AL$2)-YEAR(LM_first))*12+MONTH('Loan maths'!$AL$2)-MONTH(LM_first)-(DAY('Loan maths'!$AL$2)<(LM_anchor-(LM_anchor-DAY(EOMONTH('Loan maths'!$AL$2,0)))*(LM_anchor>DAY(EOMONTH('Loan maths'!$AL$2,0))))))/(LM_step+(LM_step=0)))+1)+(LM_cycles-(INT(((YEAR('Loan maths'!$AL$2)-YEAR(LM_first))*12+MONTH('Loan maths'!$AL$2)-MONTH(LM_first)-(DAY('Loan maths'!$AL$2)<(LM_anchor-(LM_anchor-DAY(EOMONTH('Loan maths'!$AL$2,0)))*(LM_anchor>DAY(EOMONTH('Loan maths'!$AL$2,0))))))/(LM_step+(LM_step=0)))+1))*((INT(((YEAR('Loan maths'!$AL$2)-YEAR(LM_first))*12+MONTH('Loan maths'!$AL$2)-MONTH(LM_first)-(DAY('Loan maths'!$AL$2)<(LM_anchor-(LM_anchor-DAY(EOMONTH('Loan maths'!$AL$2,0)))*(LM_anchor>DAY(EOMONTH('Loan maths'!$AL$2,0))))))/(LM_step+(LM_step=0)))+1)>LM_cycles))+LM_stub*('Loan maths'!$AL$2>=LN_maturity))-LM_paid)))-((LM_rate>0)*(LM_out*(1+LM_rate)^((('Loan maths'!$AM$2>=LM_first)*((INT(((YEAR('Loan maths'!$AM$2)-YEAR(LM_first))*12+MONTH('Loan maths'!$AM$2)-MONTH(LM_first)-(DAY('Loan maths'!$AM$2)<(LM_anchor-(LM_anchor-DAY(EOMONTH('Loan maths'!$AM$2,0)))*(LM_anchor>DAY(EOMONTH('Loan maths'!$AM$2,0))))))/(LM_step+(LM_step=0)))+1)+(LM_cycles-(INT(((YEAR('Loan maths'!$AM$2)-YEAR(LM_first))*12+MONTH('Loan maths'!$AM$2)-MONTH(LM_first)-(DAY('Loan maths'!$AM$2)<(LM_anchor-(LM_anchor-DAY(EOMONTH('Loan maths'!$AM$2,0)))*(LM_anchor>DAY(EOMONTH('Loan maths'!$AM$2,0))))))/(LM_step+(LM_step=0)))+1))*((INT(((YEAR('Loan maths'!$AM$2)-YEAR(LM_first))*12+MONTH('Loan maths'!$AM$2)-MONTH(LM_first)-(DAY('Loan maths'!$AM$2)<(LM_anchor-(LM_anchor-DAY(EOMONTH('Loan maths'!$AM$2,0)))*(LM_anchor>DAY(EOMONTH('Loan maths'!$AM$2,0))))))/(LM_step+(LM_step=0)))+1)>LM_cycles))+LM_stub*('Loan maths'!$AM$2>=LN_maturity))-LM_paid)-LM_annuity*((1+LM_rate)^((('Loan maths'!$AM$2>=LM_first)*((INT(((YEAR('Loan maths'!$AM$2)-YEAR(LM_first))*12+MONTH('Loan maths'!$AM$2)-MONTH(LM_first)-(DAY('Loan maths'!$AM$2)<(LM_anchor-(LM_anchor-DAY(EOMONTH('Loan maths'!$AM$2,0)))*(LM_anchor>DAY(EOMONTH('Loan maths'!$AM$2,0))))))/(LM_step+(LM_step=0)))+1)+(LM_cycles-(INT(((YEAR('Loan maths'!$AM$2)-YEAR(LM_first))*12+MONTH('Loan maths'!$AM$2)-MONTH(LM_first)-(DAY('Loan maths'!$AM$2)<(LM_anchor-(LM_anchor-DAY(EOMONTH('Loan maths'!$AM$2,0)))*(LM_anchor>DAY(EOMONTH('Loan maths'!$AM$2,0))))))/(LM_step+(LM_step=0)))+1))*((INT(((YEAR('Loan maths'!$AM$2)-YEAR(LM_first))*12+MONTH('Loan maths'!$AM$2)-MONTH(LM_first)-(DAY('Loan maths'!$AM$2)<(LM_anchor-(LM_anchor-DAY(EOMONTH('Loan maths'!$AM$2,0)))*(LM_anchor>DAY(EOMONTH('Loan maths'!$AM$2,0))))))/(LM_step+(LM_step=0)))+1)>LM_cycles))+LM_stub*('Loan maths'!$AM$2>=LN_maturity))-LM_paid)-1)/LM_safe)+(LM_rate=0)*(LM_out-LM_annuity*((('Loan maths'!$AM$2>=LM_first)*((INT(((YEAR('Loan maths'!$AM$2)-YEAR(LM_first))*12+MONTH('Loan maths'!$AM$2)-MONTH(LM_first)-(DAY('Loan maths'!$AM$2)<(LM_anchor-(LM_anchor-DAY(EOMONTH('Loan maths'!$AM$2,0)))*(LM_anchor>DAY(EOMONTH('Loan maths'!$AM$2,0))))))/(LM_step+(LM_step=0)))+1)+(LM_cycles-(INT(((YEAR('Loan maths'!$AM$2)-YEAR(LM_first))*12+MONTH('Loan maths'!$AM$2)-MONTH(LM_first)-(DAY('Loan maths'!$AM$2)<(LM_anchor-(LM_anchor-DAY(EOMONTH('Loan maths'!$AM$2,0)))*(LM_anchor>DAY(EOMONTH('Loan maths'!$AM$2,0))))))/(LM_step+(LM_step=0)))+1))*((INT(((YEAR('Loan maths'!$AM$2)-YEAR(LM_first))*12+MONTH('Loan maths'!$AM$2)-MONTH(LM_first)-(DAY('Loan maths'!$AM$2)<(LM_anchor-(LM_anchor-DAY(EOMONTH('Loan maths'!$AM$2,0)))*(LM_anchor>DAY(EOMONTH('Loan maths'!$AM$2,0))))))/(LM_step+(LM_step=0)))+1)>LM_cycles))+LM_stub*('Loan maths'!$AM$2>=LN_maturity))-LM_paid)))))+SUMPRODUCT(LM_live*((LM_profile<>"EIP")*(LM_profile<>"Annuity"))*(LM_end>'Loan maths'!$AL$2)*(LM_end<='Loan maths'!$AM$2)*LN_principal) -> 0 | N75: =-D75 -> 0
B76: =IF(DAY(AsAt+1)=1,TEXT(IF(DAY(AsAt+1)=1,EOMONTH(AsAt,10),EDATE(AsAt,10)),"mmm yy"),"to "&TEXT(IF(DAY(AsAt+1)=1,EOMONTH(AsAt,10),EDATE(AsAt,10)),"d mmm yy")) -> Jul 27 | C76: =SUMPRODUCT(('Deal maths'!$F$4:$F$2000>AsAt)*('Deal maths'!$E$4:$E$2000<=AsAt)*('Deal maths'!$F$4:$F$2000>IF(DAY(AsAt+1)=1,EOMONTH(AsAt,9),EDATE(AsAt,9)))*('Deal maths'!$F$4:$F$2000<=IF(DAY(AsAt+1)=1,EOMONTH(AsAt,10),EDATE(AsAt,10)))*('Deal maths'!$H$4:$H$2000+('Deal maths'!$H$4:$H$2000=0)*'Deal maths'!$D$4:$D$2000)) -> 0 | D76: =SUMPRODUCT(LM_live*(LM_profile="EIP")*LM_eip*((('Loan maths'!$AN$2>=LM_first)*((INT(((YEAR('Loan maths'!$AN$2)-YEAR(LM_first))*12+MONTH('Loan maths'!$AN$2)-MONTH(LM_first)-(DAY('Loan maths'!$AN$2)<(LM_anchor-(LM_anchor-DAY(EOMONTH('Loan maths'!$AN$2,0)))*(LM_anchor>DAY(EOMONTH('Loan maths'!$AN$2,0))))))/(LM_step+(LM_step=0)))+1)+(LM_cycles-(INT(((YEAR('Loan maths'!$AN$2)-YEAR(LM_first))*12+MONTH('Loan maths'!$AN$2)-MONTH(LM_first)-(DAY('Loan maths'!$AN$2)<(LM_anchor-(LM_anchor-DAY(EOMONTH('Loan maths'!$AN$2,0)))*(LM_anchor>DAY(EOMONTH('Loan maths'!$AN$2,0))))))/(LM_step+(LM_step=0)))+1))*((INT(((YEAR('Loan maths'!$AN$2)-YEAR(LM_first))*12+MONTH('Loan maths'!$AN$2)-MONTH(LM_first)-(DAY('Loan maths'!$AN$2)<(LM_anchor-(LM_anchor-DAY(EOMONTH('Loan maths'!$AN$2,0)))*(LM_anchor>DAY(EOMONTH('Loan maths'!$AN$2,0))))))/(LM_step+(LM_step=0)))+1)>LM_cycles))+LM_stub*('Loan maths'!$AN$2>=LN_maturity))-(('Loan maths'!$AM$2>=LM_first)*((INT(((YEAR('Loan maths'!$AM$2)-YEAR(LM_first))*12+MONTH('Loan maths'!$AM$2)-MONTH(LM_first)-(DAY('Loan maths'!$AM$2)<(LM_anchor-(LM_anchor-DAY(EOMONTH('Loan maths'!$AM$2,0)))*(LM_anchor>DAY(EOMONTH('Loan maths'!$AM$2,0))))))/(LM_step+(LM_step=0)))+1)+(LM_cycles-(INT(((YEAR('Loan maths'!$AM$2)-YEAR(LM_first))*12+MONTH('Loan maths'!$AM$2)-MONTH(LM_first)-(DAY('Loan maths'!$AM$2)<(LM_anchor-(LM_anchor-DAY(EOMONTH('Loan maths'!$AM$2,0)))*(LM_anchor>DAY(EOMONTH('Loan maths'!$AM$2,0))))))/(LM_step+(LM_step=0)))+1))*((INT(((YEAR('Loan maths'!$AM$2)-YEAR(LM_first))*12+MONTH('Loan maths'!$AM$2)-MONTH(LM_first)-(DAY('Loan maths'!$AM$2)<(LM_anchor-(LM_anchor-DAY(EOMONTH('Loan maths'!$AM$2,0)))*(LM_anchor>DAY(EOMONTH('Loan maths'!$AM$2,0))))))/(LM_step+(LM_step=0)))+1)>LM_cycles))+LM_stub*('Loan maths'!$AM$2>=LN_maturity))))+SUMPRODUCT(LM_live*(LM_profile="Annuity")*(((LM_rate>0)*(LM_out*(1+LM_rate)^((('Loan maths'!$AM$2>=LM_first)*((INT(((YEAR('Loan maths'!$AM$2)-YEAR(LM_first))*12+MONTH('Loan maths'!$AM$2)-MONTH(LM_first)-(DAY('Loan maths'!$AM$2)<(LM_anchor-(LM_anchor-DAY(EOMONTH('Loan maths'!$AM$2,0)))*(LM_anchor>DAY(EOMONTH('Loan maths'!$AM$2,0))))))/(LM_step+(LM_step=0)))+1)+(LM_cycles-(INT(((YEAR('Loan maths'!$AM$2)-YEAR(LM_first))*12+MONTH('Loan maths'!$AM$2)-MONTH(LM_first)-(DAY('Loan maths'!$AM$2)<(LM_anchor-(LM_anchor-DAY(EOMONTH('Loan maths'!$AM$2,0)))*(LM_anchor>DAY(EOMONTH('Loan maths'!$AM$2,0))))))/(LM_step+(LM_step=0)))+1))*((INT(((YEAR('Loan maths'!$AM$2)-YEAR(LM_first))*12+MONTH('Loan maths'!$AM$2)-MONTH(LM_first)-(DAY('Loan maths'!$AM$2)<(LM_anchor-(LM_anchor-DAY(EOMONTH('Loan maths'!$AM$2,0)))*(LM_anchor>DAY(EOMONTH('Loan maths'!$AM$2,0))))))/(LM_step+(LM_step=0)))+1)>LM_cycles))+LM_stub*('Loan maths'!$AM$2>=LN_maturity))-LM_paid)-LM_annuity*((1+LM_rate)^((('Loan maths'!$AM$2>=LM_first)*((INT(((YEAR('Loan maths'!$AM$2)-YEAR(LM_first))*12+MONTH('Loan maths'!$AM$2)-MONTH(LM_first)-(DAY('Loan maths'!$AM$2)<(LM_anchor-(LM_anchor-DAY(EOMONTH('Loan maths'!$AM$2,0)))*(LM_anchor>DAY(EOMONTH('Loan maths'!$AM$2,0))))))/(LM_step+(LM_step=0)))+1)+(LM_cycles-(INT(((YEAR('Loan maths'!$AM$2)-YEAR(LM_first))*12+MONTH('Loan maths'!$AM$2)-MONTH(LM_first)-(DAY('Loan maths'!$AM$2)<(LM_anchor-(LM_anchor-DAY(EOMONTH('Loan maths'!$AM$2,0)))*(LM_anchor>DAY(EOMONTH('Loan maths'!$AM$2,0))))))/(LM_step+(LM_step=0)))+1))*((INT(((YEAR('Loan maths'!$AM$2)-YEAR(LM_first))*12+MONTH('Loan maths'!$AM$2)-MONTH(LM_first)-(DAY('Loan maths'!$AM$2)<(LM_anchor-(LM_anchor-DAY(EOMONTH('Loan maths'!$AM$2,0)))*(LM_anchor>DAY(EOMONTH('Loan maths'!$AM$2,0))))))/(LM_step+(LM_step=0)))+1)>LM_cycles))+LM_stub*('Loan maths'!$AM$2>=LN_maturity))-LM_paid)-1)/LM_safe)+(LM_rate=0)*(LM_out-LM_annuity*((('Loan maths'!$AM$2>=LM_first)*((INT(((YEAR('Loan maths'!$AM$2)-YEAR(LM_first))*12+MONTH('Loan maths'!$AM$2)-MONTH(LM_first)-(DAY('Loan maths'!$AM$2)<(LM_anchor-(LM_anchor-DAY(EOMONTH('Loan maths'!$AM$2,0)))*(LM_anchor>DAY(EOMONTH('Loan maths'!$AM$2,0))))))/(LM_step+(LM_step=0)))+1)+(LM_cycles-(INT(((YEAR('Loan maths'!$AM$2)-YEAR(LM_first))*12+MONTH('Loan maths'!$AM$2)-MONTH(LM_first)-(DAY('Loan maths'!$AM$2)<(LM_anchor-(LM_anchor-DAY(EOMONTH('Loan maths'!$AM$2,0)))*(LM_anchor>DAY(EOMONTH('Loan maths'!$AM$2,0))))))/(LM_step+(LM_step=0)))+1))*((INT(((YEAR('Loan maths'!$AM$2)-YEAR(LM_first))*12+MONTH('Loan maths'!$AM$2)-MONTH(LM_first)-(DAY('Loan maths'!$AM$2)<(LM_anchor-(LM_anchor-DAY(EOMONTH('Loan maths'!$AM$2,0)))*(LM_anchor>DAY(EOMONTH('Loan maths'!$AM$2,0))))))/(LM_step+(LM_step=0)))+1)>LM_cycles))+LM_stub*('Loan maths'!$AM$2>=LN_maturity))-LM_paid)))-((LM_rate>0)*(LM_out*(1+LM_rate)^((('Loan maths'!$AN$2>=LM_first)*((INT(((YEAR('Loan maths'!$AN$2)-YEAR(LM_first))*12+MONTH('Loan maths'!$AN$2)-MONTH(LM_first)-(DAY('Loan maths'!$AN$2)<(LM_anchor-(LM_anchor-DAY(EOMONTH('Loan maths'!$AN$2,0)))*(LM_anchor>DAY(EOMONTH('Loan maths'!$AN$2,0))))))/(LM_step+(LM_step=0)))+1)+(LM_cycles-(INT(((YEAR('Loan maths'!$AN$2)-YEAR(LM_first))*12+MONTH('Loan maths'!$AN$2)-MONTH(LM_first)-(DAY('Loan maths'!$AN$2)<(LM_anchor-(LM_anchor-DAY(EOMONTH('Loan maths'!$AN$2,0)))*(LM_anchor>DAY(EOMONTH('Loan maths'!$AN$2,0))))))/(LM_step+(LM_step=0)))+1))*((INT(((YEAR('Loan maths'!$AN$2)-YEAR(LM_first))*12+MONTH('Loan maths'!$AN$2)-MONTH(LM_first)-(DAY('Loan maths'!$AN$2)<(LM_anchor-(LM_anchor-DAY(EOMONTH('Loan maths'!$AN$2,0)))*(LM_anchor>DAY(EOMONTH('Loan maths'!$AN$2,0))))))/(LM_step+(LM_step=0)))+1)>LM_cycles))+LM_stub*('Loan maths'!$AN$2>=LN_maturity))-LM_paid)-LM_annuity*((1+LM_rate)^((('Loan maths'!$AN$2>=LM_first)*((INT(((YEAR('Loan maths'!$AN$2)-YEAR(LM_first))*12+MONTH('Loan maths'!$AN$2)-MONTH(LM_first)-(DAY('Loan maths'!$AN$2)<(LM_anchor-(LM_anchor-DAY(EOMONTH('Loan maths'!$AN$2,0)))*(LM_anchor>DAY(EOMONTH('Loan maths'!$AN$2,0))))))/(LM_step+(LM_step=0)))+1)+(LM_cycles-(INT(((YEAR('Loan maths'!$AN$2)-YEAR(LM_first))*12+MONTH('Loan maths'!$AN$2)-MONTH(LM_first)-(DAY('Loan maths'!$AN$2)<(LM_anchor-(LM_anchor-DAY(EOMONTH('Loan maths'!$AN$2,0)))*(LM_anchor>DAY(EOMONTH('Loan maths'!$AN$2,0))))))/(LM_step+(LM_step=0)))+1))*((INT(((YEAR('Loan maths'!$AN$2)-YEAR(LM_first))*12+MONTH('Loan maths'!$AN$2)-MONTH(LM_first)-(DAY('Loan maths'!$AN$2)<(LM_anchor-(LM_anchor-DAY(EOMONTH('Loan maths'!$AN$2,0)))*(LM_anchor>DAY(EOMONTH('Loan maths'!$AN$2,0))))))/(LM_step+(LM_step=0)))+1)>LM_cycles))+LM_stub*('Loan maths'!$AN$2>=LN_maturity))-LM_paid)-1)/LM_safe)+(LM_rate=0)*(LM_out-LM_annuity*((('Loan maths'!$AN$2>=LM_first)*((INT(((YEAR('Loan maths'!$AN$2)-YEAR(LM_first))*12+MONTH('Loan maths'!$AN$2)-MONTH(LM_first)-(DAY('Loan maths'!$AN$2)<(LM_anchor-(LM_anchor-DAY(EOMONTH('Loan maths'!$AN$2,0)))*(LM_anchor>DAY(EOMONTH('Loan maths'!$AN$2,0))))))/(LM_step+(LM_step=0)))+1)+(LM_cycles-(INT(((YEAR('Loan maths'!$AN$2)-YEAR(LM_first))*12+MONTH('Loan maths'!$AN$2)-MONTH(LM_first)-(DAY('Loan maths'!$AN$2)<(LM_anchor-(LM_anchor-DAY(EOMONTH('Loan maths'!$AN$2,0)))*(LM_anchor>DAY(EOMONTH('Loan maths'!$AN$2,0))))))/(LM_step+(LM_step=0)))+1))*((INT(((YEAR('Loan maths'!$AN$2)-YEAR(LM_first))*12+MONTH('Loan maths'!$AN$2)-MONTH(LM_first)-(DAY('Loan maths'!$AN$2)<(LM_anchor-(LM_anchor-DAY(EOMONTH('Loan maths'!$AN$2,0)))*(LM_anchor>DAY(EOMONTH('Loan maths'!$AN$2,0))))))/(LM_step+(LM_step=0)))+1)>LM_cycles))+LM_stub*('Loan maths'!$AN$2>=LN_maturity))-LM_paid)))))+SUMPRODUCT(LM_live*((LM_profile<>"EIP")*(LM_profile<>"Annuity"))*(LM_end>'Loan maths'!$AM$2)*(LM_end<='Loan maths'!$AN$2)*LN_principal) -> 0 | N76: =-D76 -> 0
B77: =IF(DAY(AsAt+1)=1,TEXT(IF(DAY(AsAt+1)=1,EOMONTH(AsAt,11),EDATE(AsAt,11)),"mmm yy"),"to "&TEXT(IF(DAY(AsAt+1)=1,EOMONTH(AsAt,11),EDATE(AsAt,11)),"d mmm yy")) -> Aug 27 | C77: =SUMPRODUCT(('Deal maths'!$F$4:$F$2000>AsAt)*('Deal maths'!$E$4:$E$2000<=AsAt)*('Deal maths'!$F$4:$F$2000>IF(DAY(AsAt+1)=1,EOMONTH(AsAt,10),EDATE(AsAt,10)))*('Deal maths'!$F$4:$F$2000<=IF(DAY(AsAt+1)=1,EOMONTH(AsAt,11),EDATE(AsAt,11)))*('Deal maths'!$H$4:$H$2000+('Deal maths'!$H$4:$H$2000=0)*'Deal maths'!$D$4:$D$2000)) -> 0 | D77: =SUMPRODUCT(LM_live*(LM_profile="EIP")*LM_eip*((('Loan maths'!$AO$2>=LM_first)*((INT(((YEAR('Loan maths'!$AO$2)-YEAR(LM_first))*12+MONTH('Loan maths'!$AO$2)-MONTH(LM_first)-(DAY('Loan maths'!$AO$2)<(LM_anchor-(LM_anchor-DAY(EOMONTH('Loan maths'!$AO$2,0)))*(LM_anchor>DAY(EOMONTH('Loan maths'!$AO$2,0))))))/(LM_step+(LM_step=0)))+1)+(LM_cycles-(INT(((YEAR('Loan maths'!$AO$2)-YEAR(LM_first))*12+MONTH('Loan maths'!$AO$2)-MONTH(LM_first)-(DAY('Loan maths'!$AO$2)<(LM_anchor-(LM_anchor-DAY(EOMONTH('Loan maths'!$AO$2,0)))*(LM_anchor>DAY(EOMONTH('Loan maths'!$AO$2,0))))))/(LM_step+(LM_step=0)))+1))*((INT(((YEAR('Loan maths'!$AO$2)-YEAR(LM_first))*12+MONTH('Loan maths'!$AO$2)-MONTH(LM_first)-(DAY('Loan maths'!$AO$2)<(LM_anchor-(LM_anchor-DAY(EOMONTH('Loan maths'!$AO$2,0)))*(LM_anchor>DAY(EOMONTH('Loan maths'!$AO$2,0))))))/(LM_step+(LM_step=0)))+1)>LM_cycles))+LM_stub*('Loan maths'!$AO$2>=LN_maturity))-(('Loan maths'!$AN$2>=LM_first)*((INT(((YEAR('Loan maths'!$AN$2)-YEAR(LM_first))*12+MONTH('Loan maths'!$AN$2)-MONTH(LM_first)-(DAY('Loan maths'!$AN$2)<(LM_anchor-(LM_anchor-DAY(EOMONTH('Loan maths'!$AN$2,0)))*(LM_anchor>DAY(EOMONTH('Loan maths'!$AN$2,0))))))/(LM_step+(LM_step=0)))+1)+(LM_cycles-(INT(((YEAR('Loan maths'!$AN$2)-YEAR(LM_first))*12+MONTH('Loan maths'!$AN$2)-MONTH(LM_first)-(DAY('Loan maths'!$AN$2)<(LM_anchor-(LM_anchor-DAY(EOMONTH('Loan maths'!$AN$2,0)))*(LM_anchor>DAY(EOMONTH('Loan maths'!$AN$2,0))))))/(LM_step+(LM_step=0)))+1))*((INT(((YEAR('Loan maths'!$AN$2)-YEAR(LM_first))*12+MONTH('Loan maths'!$AN$2)-MONTH(LM_first)-(DAY('Loan maths'!$AN$2)<(LM_anchor-(LM_anchor-DAY(EOMONTH('Loan maths'!$AN$2,0)))*(LM_anchor>DAY(EOMONTH('Loan maths'!$AN$2,0))))))/(LM_step+(LM_step=0)))+1)>LM_cycles))+LM_stub*('Loan maths'!$AN$2>=LN_maturity))))+SUMPRODUCT(LM_live*(LM_profile="Annuity")*(((LM_rate>0)*(LM_out*(1+LM_rate)^((('Loan maths'!$AN$2>=LM_first)*((INT(((YEAR('Loan maths'!$AN$2)-YEAR(LM_first))*12+MONTH('Loan maths'!$AN$2)-MONTH(LM_first)-(DAY('Loan maths'!$AN$2)<(LM_anchor-(LM_anchor-DAY(EOMONTH('Loan maths'!$AN$2,0)))*(LM_anchor>DAY(EOMONTH('Loan maths'!$AN$2,0))))))/(LM_step+(LM_step=0)))+1)+(LM_cycles-(INT(((YEAR('Loan maths'!$AN$2)-YEAR(LM_first))*12+MONTH('Loan maths'!$AN$2)-MONTH(LM_first)-(DAY('Loan maths'!$AN$2)<(LM_anchor-(LM_anchor-DAY(EOMONTH('Loan maths'!$AN$2,0)))*(LM_anchor>DAY(EOMONTH('Loan maths'!$AN$2,0))))))/(LM_step+(LM_step=0)))+1))*((INT(((YEAR('Loan maths'!$AN$2)-YEAR(LM_first))*12+MONTH('Loan maths'!$AN$2)-MONTH(LM_first)-(DAY('Loan maths'!$AN$2)<(LM_anchor-(LM_anchor-DAY(EOMONTH('Loan maths'!$AN$2,0)))*(LM_anchor>DAY(EOMONTH('Loan maths'!$AN$2,0))))))/(LM_step+(LM_step=0)))+1)>LM_cycles))+LM_stub*('Loan maths'!$AN$2>=LN_maturity))-LM_paid)-LM_annuity*((1+LM_rate)^((('Loan maths'!$AN$2>=LM_first)*((INT(((YEAR('Loan maths'!$AN$2)-YEAR(LM_first))*12+MONTH('Loan maths'!$AN$2)-MONTH(LM_first)-(DAY('Loan maths'!$AN$2)<(LM_anchor-(LM_anchor-DAY(EOMONTH('Loan maths'!$AN$2,0)))*(LM_anchor>DAY(EOMONTH('Loan maths'!$AN$2,0))))))/(LM_step+(LM_step=0)))+1)+(LM_cycles-(INT(((YEAR('Loan maths'!$AN$2)-YEAR(LM_first))*12+MONTH('Loan maths'!$AN$2)-MONTH(LM_first)-(DAY('Loan maths'!$AN$2)<(LM_anchor-(LM_anchor-DAY(EOMONTH('Loan maths'!$AN$2,0)))*(LM_anchor>DAY(EOMONTH('Loan maths'!$AN$2,0))))))/(LM_step+(LM_step=0)))+1))*((INT(((YEAR('Loan maths'!$AN$2)-YEAR(LM_first))*12+MONTH('Loan maths'!$AN$2)-MONTH(LM_first)-(DAY('Loan maths'!$AN$2)<(LM_anchor-(LM_anchor-DAY(EOMONTH('Loan maths'!$AN$2,0)))*(LM_anchor>DAY(EOMONTH('Loan maths'!$AN$2,0))))))/(LM_step+(LM_step=0)))+1)>LM_cycles))+LM_stub*('Loan maths'!$AN$2>=LN_maturity))-LM_paid)-1)/LM_safe)+(LM_rate=0)*(LM_out-LM_annuity*((('Loan maths'!$AN$2>=LM_first)*((INT(((YEAR('Loan maths'!$AN$2)-YEAR(LM_first))*12+MONTH('Loan maths'!$AN$2)-MONTH(LM_first)-(DAY('Loan maths'!$AN$2)<(LM_anchor-(LM_anchor-DAY(EOMONTH('Loan maths'!$AN$2,0)))*(LM_anchor>DAY(EOMONTH('Loan maths'!$AN$2,0))))))/(LM_step+(LM_step=0)))+1)+(LM_cycles-(INT(((YEAR('Loan maths'!$AN$2)-YEAR(LM_first))*12+MONTH('Loan maths'!$AN$2)-MONTH(LM_first)-(DAY('Loan maths'!$AN$2)<(LM_anchor-(LM_anchor-DAY(EOMONTH('Loan maths'!$AN$2,0)))*(LM_anchor>DAY(EOMONTH('Loan maths'!$AN$2,0))))))/(LM_step+(LM_step=0)))+1))*((INT(((YEAR('Loan maths'!$AN$2)-YEAR(LM_first))*12+MONTH('Loan maths'!$AN$2)-MONTH(LM_first)-(DAY('Loan maths'!$AN$2)<(LM_anchor-(LM_anchor-DAY(EOMONTH('Loan maths'!$AN$2,0)))*(LM_anchor>DAY(EOMONTH('Loan maths'!$AN$2,0))))))/(LM_step+(LM_step=0)))+1)>LM_cycles))+LM_stub*('Loan maths'!$AN$2>=LN_maturity))-LM_paid)))-((LM_rate>0)*(LM_out*(1+LM_rate)^((('Loan maths'!$AO$2>=LM_first)*((INT(((YEAR('Loan maths'!$AO$2)-YEAR(LM_first))*12+MONTH('Loan maths'!$AO$2)-MONTH(LM_first)-(DAY('Loan maths'!$AO$2)<(LM_anchor-(LM_anchor-DAY(EOMONTH('Loan maths'!$AO$2,0)))*(LM_anchor>DAY(EOMONTH('Loan maths'!$AO$2,0))))))/(LM_step+(LM_step=0)))+1)+(LM_cycles-(INT(((YEAR('Loan maths'!$AO$2)-YEAR(LM_first))*12+MONTH('Loan maths'!$AO$2)-MONTH(LM_first)-(DAY('Loan maths'!$AO$2)<(LM_anchor-(LM_anchor-DAY(EOMONTH('Loan maths'!$AO$2,0)))*(LM_anchor>DAY(EOMONTH('Loan maths'!$AO$2,0))))))/(LM_step+(LM_step=0)))+1))*((INT(((YEAR('Loan maths'!$AO$2)-YEAR(LM_first))*12+MONTH('Loan maths'!$AO$2)-MONTH(LM_first)-(DAY('Loan maths'!$AO$2)<(LM_anchor-(LM_anchor-DAY(EOMONTH('Loan maths'!$AO$2,0)))*(LM_anchor>DAY(EOMONTH('Loan maths'!$AO$2,0))))))/(LM_step+(LM_step=0)))+1)>LM_cycles))+LM_stub*('Loan maths'!$AO$2>=LN_maturity))-LM_paid)-LM_annuity*((1+LM_rate)^((('Loan maths'!$AO$2>=LM_first)*((INT(((YEAR('Loan maths'!$AO$2)-YEAR(LM_first))*12+MONTH('Loan maths'!$AO$2)-MONTH(LM_first)-(DAY('Loan maths'!$AO$2)<(LM_anchor-(LM_anchor-DAY(EOMONTH('Loan maths'!$AO$2,0)))*(LM_anchor>DAY(EOMONTH('Loan maths'!$AO$2,0))))))/(LM_step+(LM_step=0)))+1)+(LM_cycles-(INT(((YEAR('Loan maths'!$AO$2)-YEAR(LM_first))*12+MONTH('Loan maths'!$AO$2)-MONTH(LM_first)-(DAY('Loan maths'!$AO$2)<(LM_anchor-(LM_anchor-DAY(EOMONTH('Loan maths'!$AO$2,0)))*(LM_anchor>DAY(EOMONTH('Loan maths'!$AO$2,0))))))/(LM_step+(LM_step=0)))+1))*((INT(((YEAR('Loan maths'!$AO$2)-YEAR(LM_first))*12+MONTH('Loan maths'!$AO$2)-MONTH(LM_first)-(DAY('Loan maths'!$AO$2)<(LM_anchor-(LM_anchor-DAY(EOMONTH('Loan maths'!$AO$2,0)))*(LM_anchor>DAY(EOMONTH('Loan maths'!$AO$2,0))))))/(LM_step+(LM_step=0)))+1)>LM_cycles))+LM_stub*('Loan maths'!$AO$2>=LN_maturity))-LM_paid)-1)/LM_safe)+(LM_rate=0)*(LM_out-LM_annuity*((('Loan maths'!$AO$2>=LM_first)*((INT(((YEAR('Loan maths'!$AO$2)-YEAR(LM_first))*12+MONTH('Loan maths'!$AO$2)-MONTH(LM_first)-(DAY('Loan maths'!$AO$2)<(LM_anchor-(LM_anchor-DAY(EOMONTH('Loan maths'!$AO$2,0)))*(LM_anchor>DAY(EOMONTH('Loan maths'!$AO$2,0))))))/(LM_step+(LM_step=0)))+1)+(LM_cycles-(INT(((YEAR('Loan maths'!$AO$2)-YEAR(LM_first))*12+MONTH('Loan maths'!$AO$2)-MONTH(LM_first)-(DAY('Loan maths'!$AO$2)<(LM_anchor-(LM_anchor-DAY(EOMONTH('Loan maths'!$AO$2,0)))*(LM_anchor>DAY(EOMONTH('Loan maths'!$AO$2,0))))))/(LM_step+(LM_step=0)))+1))*((INT(((YEAR('Loan maths'!$AO$2)-YEAR(LM_first))*12+MONTH('Loan maths'!$AO$2)-MONTH(LM_first)-(DAY('Loan maths'!$AO$2)<(LM_anchor-(LM_anchor-DAY(EOMONTH('Loan maths'!$AO$2,0)))*(LM_anchor>DAY(EOMONTH('Loan maths'!$AO$2,0))))))/(LM_step+(LM_step=0)))+1)>LM_cycles))+LM_stub*('Loan maths'!$AO$2>=LN_maturity))-LM_paid)))))+SUMPRODUCT(LM_live*((LM_profile<>"EIP")*(LM_profile<>"Annuity"))*(LM_end>'Loan maths'!$AN$2)*(LM_end<='Loan maths'!$AO$2)*LN_principal) -> 0 | N77: =-D77 -> 0
B78: =IF(DAY(AsAt+1)=1,TEXT(IF(DAY(AsAt+1)=1,EOMONTH(AsAt,12),EDATE(AsAt,12)),"mmm yy"),"to "&TEXT(IF(DAY(AsAt+1)=1,EOMONTH(AsAt,12),EDATE(AsAt,12)),"d mmm yy")) -> Sep 27 | C78: =SUMPRODUCT(('Deal maths'!$F$4:$F$2000>AsAt)*('Deal maths'!$E$4:$E$2000<=AsAt)*('Deal maths'!$F$4:$F$2000>IF(DAY(AsAt+1)=1,EOMONTH(AsAt,11),EDATE(AsAt,11)))*('Deal maths'!$F$4:$F$2000<=IF(DAY(AsAt+1)=1,EOMONTH(AsAt,12),EDATE(AsAt,12)))*('Deal maths'!$H$4:$H$2000+('Deal maths'!$H$4:$H$2000=0)*'Deal maths'!$D$4:$D$2000)) -> 0 | D78: =SUMPRODUCT(LM_live*(LM_profile="EIP")*LM_eip*((('Loan maths'!$AP$2>=LM_first)*((INT(((YEAR('Loan maths'!$AP$2)-YEAR(LM_first))*12+MONTH('Loan maths'!$AP$2)-MONTH(LM_first)-(DAY('Loan maths'!$AP$2)<(LM_anchor-(LM_anchor-DAY(EOMONTH('Loan maths'!$AP$2,0)))*(LM_anchor>DAY(EOMONTH('Loan maths'!$AP$2,0))))))/(LM_step+(LM_step=0)))+1)+(LM_cycles-(INT(((YEAR('Loan maths'!$AP$2)-YEAR(LM_first))*12+MONTH('Loan maths'!$AP$2)-MONTH(LM_first)-(DAY('Loan maths'!$AP$2)<(LM_anchor-(LM_anchor-DAY(EOMONTH('Loan maths'!$AP$2,0)))*(LM_anchor>DAY(EOMONTH('Loan maths'!$AP$2,0))))))/(LM_step+(LM_step=0)))+1))*((INT(((YEAR('Loan maths'!$AP$2)-YEAR(LM_first))*12+MONTH('Loan maths'!$AP$2)-MONTH(LM_first)-(DAY('Loan maths'!$AP$2)<(LM_anchor-(LM_anchor-DAY(EOMONTH('Loan maths'!$AP$2,0)))*(LM_anchor>DAY(EOMONTH('Loan maths'!$AP$2,0))))))/(LM_step+(LM_step=0)))+1)>LM_cycles))+LM_stub*('Loan maths'!$AP$2>=LN_maturity))-(('Loan maths'!$AO$2>=LM_first)*((INT(((YEAR('Loan maths'!$AO$2)-YEAR(LM_first))*12+MONTH('Loan maths'!$AO$2)-MONTH(LM_first)-(DAY('Loan maths'!$AO$2)<(LM_anchor-(LM_anchor-DAY(EOMONTH('Loan maths'!$AO$2,0)))*(LM_anchor>DAY(EOMONTH('Loan maths'!$AO$2,0))))))/(LM_step+(LM_step=0)))+1)+(LM_cycles-(INT(((YEAR('Loan maths'!$AO$2)-YEAR(LM_first))*12+MONTH('Loan maths'!$AO$2)-MONTH(LM_first)-(DAY('Loan maths'!$AO$2)<(LM_anchor-(LM_anchor-DAY(EOMONTH('Loan maths'!$AO$2,0)))*(LM_anchor>DAY(EOMONTH('Loan maths'!$AO$2,0))))))/(LM_step+(LM_step=0)))+1))*((INT(((YEAR('Loan maths'!$AO$2)-YEAR(LM_first))*12+MONTH('Loan maths'!$AO$2)-MONTH(LM_first)-(DAY('Loan maths'!$AO$2)<(LM_anchor-(LM_anchor-DAY(EOMONTH('Loan maths'!$AO$2,0)))*(LM_anchor>DAY(EOMONTH('Loan maths'!$AO$2,0))))))/(LM_step+(LM_step=0)))+1)>LM_cycles))+LM_stub*('Loan maths'!$AO$2>=LN_maturity))))+SUMPRODUCT(LM_live*(LM_profile="Annuity")*(((LM_rate>0)*(LM_out*(1+LM_rate)^((('Loan maths'!$AO$2>=LM_first)*((INT(((YEAR('Loan maths'!$AO$2)-YEAR(LM_first))*12+MONTH('Loan maths'!$AO$2)-MONTH(LM_first)-(DAY('Loan maths'!$AO$2)<(LM_anchor-(LM_anchor-DAY(EOMONTH('Loan maths'!$AO$2,0)))*(LM_anchor>DAY(EOMONTH('Loan maths'!$AO$2,0))))))/(LM_step+(LM_step=0)))+1)+(LM_cycles-(INT(((YEAR('Loan maths'!$AO$2)-YEAR(LM_first))*12+MONTH('Loan maths'!$AO$2)-MONTH(LM_first)-(DAY('Loan maths'!$AO$2)<(LM_anchor-(LM_anchor-DAY(EOMONTH('Loan maths'!$AO$2,0)))*(LM_anchor>DAY(EOMONTH('Loan maths'!$AO$2,0))))))/(LM_step+(LM_step=0)))+1))*((INT(((YEAR('Loan maths'!$AO$2)-YEAR(LM_first))*12+MONTH('Loan maths'!$AO$2)-MONTH(LM_first)-(DAY('Loan maths'!$AO$2)<(LM_anchor-(LM_anchor-DAY(EOMONTH('Loan maths'!$AO$2,0)))*(LM_anchor>DAY(EOMONTH('Loan maths'!$AO$2,0))))))/(LM_step+(LM_step=0)))+1)>LM_cycles))+LM_stub*('Loan maths'!$AO$2>=LN_maturity))-LM_paid)-LM_annuity*((1+LM_rate)^((('Loan maths'!$AO$2>=LM_first)*((INT(((YEAR('Loan maths'!$AO$2)-YEAR(LM_first))*12+MONTH('Loan maths'!$AO$2)-MONTH(LM_first)-(DAY('Loan maths'!$AO$2)<(LM_anchor-(LM_anchor-DAY(EOMONTH('Loan maths'!$AO$2,0)))*(LM_anchor>DAY(EOMONTH('Loan maths'!$AO$2,0))))))/(LM_step+(LM_step=0)))+1)+(LM_cycles-(INT(((YEAR('Loan maths'!$AO$2)-YEAR(LM_first))*12+MONTH('Loan maths'!$AO$2)-MONTH(LM_first)-(DAY('Loan maths'!$AO$2)<(LM_anchor-(LM_anchor-DAY(EOMONTH('Loan maths'!$AO$2,0)))*(LM_anchor>DAY(EOMONTH('Loan maths'!$AO$2,0))))))/(LM_step+(LM_step=0)))+1))*((INT(((YEAR('Loan maths'!$AO$2)-YEAR(LM_first))*12+MONTH('Loan maths'!$AO$2)-MONTH(LM_first)-(DAY('Loan maths'!$AO$2)<(LM_anchor-(LM_anchor-DAY(EOMONTH('Loan maths'!$AO$2,0)))*(LM_anchor>DAY(EOMONTH('Loan maths'!$AO$2,0))))))/(LM_step+(LM_step=0)))+1)>LM_cycles))+LM_stub*('Loan maths'!$AO$2>=LN_maturity))-LM_paid)-1)/LM_safe)+(LM_rate=0)*(LM_out-LM_annuity*((('Loan maths'!$AO$2>=LM_first)*((INT(((YEAR('Loan maths'!$AO$2)-YEAR(LM_first))*12+MONTH('Loan maths'!$AO$2)-MONTH(LM_first)-(DAY('Loan maths'!$AO$2)<(LM_anchor-(LM_anchor-DAY(EOMONTH('Loan maths'!$AO$2,0)))*(LM_anchor>DAY(EOMONTH('Loan maths'!$AO$2,0))))))/(LM_step+(LM_step=0)))+1)+(LM_cycles-(INT(((YEAR('Loan maths'!$AO$2)-YEAR(LM_first))*12+MONTH('Loan maths'!$AO$2)-MONTH(LM_first)-(DAY('Loan maths'!$AO$2)<(LM_anchor-(LM_anchor-DAY(EOMONTH('Loan maths'!$AO$2,0)))*(LM_anchor>DAY(EOMONTH('Loan maths'!$AO$2,0))))))/(LM_step+(LM_step=0)))+1))*((INT(((YEAR('Loan maths'!$AO$2)-YEAR(LM_first))*12+MONTH('Loan maths'!$AO$2)-MONTH(LM_first)-(DAY('Loan maths'!$AO$2)<(LM_anchor-(LM_anchor-DAY(EOMONTH('Loan maths'!$AO$2,0)))*(LM_anchor>DAY(EOMONTH('Loan maths'!$AO$2,0))))))/(LM_step+(LM_step=0)))+1)>LM_cycles))+LM_stub*('Loan maths'!$AO$2>=LN_maturity))-LM_paid)))-((LM_rate>0)*(LM_out*(1+LM_rate)^((('Loan maths'!$AP$2>=LM_first)*((INT(((YEAR('Loan maths'!$AP$2)-YEAR(LM_first))*12+MONTH('Loan maths'!$AP$2)-MONTH(LM_first)-(DAY('Loan maths'!$AP$2)<(LM_anchor-(LM_anchor-DAY(EOMONTH('Loan maths'!$AP$2,0)))*(LM_anchor>DAY(EOMONTH('Loan maths'!$AP$2,0))))))/(LM_step+(LM_step=0)))+1)+(LM_cycles-(INT(((YEAR('Loan maths'!$AP$2)-YEAR(LM_first))*12+MONTH('Loan maths'!$AP$2)-MONTH(LM_first)-(DAY('Loan maths'!$AP$2)<(LM_anchor-(LM_anchor-DAY(EOMONTH('Loan maths'!$AP$2,0)))*(LM_anchor>DAY(EOMONTH('Loan maths'!$AP$2,0))))))/(LM_step+(LM_step=0)))+1))*((INT(((YEAR('Loan maths'!$AP$2)-YEAR(LM_first))*12+MONTH('Loan maths'!$AP$2)-MONTH(LM_first)-(DAY('Loan maths'!$AP$2)<(LM_anchor-(LM_anchor-DAY(EOMONTH('Loan maths'!$AP$2,0)))*(LM_anchor>DAY(EOMONTH('Loan maths'!$AP$2,0))))))/(LM_step+(LM_step=0)))+1)>LM_cycles))+LM_stub*('Loan maths'!$AP$2>=LN_maturity))-LM_paid)-LM_annuity*((1+LM_rate)^((('Loan maths'!$AP$2>=LM_first)*((INT(((YEAR('Loan maths'!$AP$2)-YEAR(LM_first))*12+MONTH('Loan maths'!$AP$2)-MONTH(LM_first)-(DAY('Loan maths'!$AP$2)<(LM_anchor-(LM_anchor-DAY(EOMONTH('Loan maths'!$AP$2,0)))*(LM_anchor>DAY(EOMONTH('Loan maths'!$AP$2,0))))))/(LM_step+(LM_step=0)))+1)+(LM_cycles-(INT(((YEAR('Loan maths'!$AP$2)-YEAR(LM_first))*12+MONTH('Loan maths'!$AP$2)-MONTH(LM_first)-(DAY('Loan maths'!$AP$2)<(LM_anchor-(LM_anchor-DAY(EOMONTH('Loan maths'!$AP$2,0)))*(LM_anchor>DAY(EOMONTH('Loan maths'!$AP$2,0))))))/(LM_step+(LM_step=0)))+1))*((INT(((YEAR('Loan maths'!$AP$2)-YEAR(LM_first))*12+MONTH('Loan maths'!$AP$2)-MONTH(LM_first)-(DAY('Loan maths'!$AP$2)<(LM_anchor-(LM_anchor-DAY(EOMONTH('Loan maths'!$AP$2,0)))*(LM_anchor>DAY(EOMONTH('Loan maths'!$AP$2,0))))))/(LM_step+(LM_step=0)))+1)>LM_cycles))+LM_stub*('Loan maths'!$AP$2>=LN_maturity))-LM_paid)-1)/LM_safe)+(LM_rate=0)*(LM_out-LM_annuity*((('Loan maths'!$AP$2>=LM_first)*((INT(((YEAR('Loan maths'!$AP$2)-YEAR(LM_first))*12+MONTH('Loan maths'!$AP$2)-MONTH(LM_first)-(DAY('Loan maths'!$AP$2)<(LM_anchor-(LM_anchor-DAY(EOMONTH('Loan maths'!$AP$2,0)))*(LM_anchor>DAY(EOMONTH('Loan maths'!$AP$2,0))))))/(LM_step+(LM_step=0)))+1)+(LM_cycles-(INT(((YEAR('Loan maths'!$AP$2)-YEAR(LM_first))*12+MONTH('Loan maths'!$AP$2)-MONTH(LM_first)-(DAY('Loan maths'!$AP$2)<(LM_anchor-(LM_anchor-DAY(EOMONTH('Loan maths'!$AP$2,0)))*(LM_anchor>DAY(EOMONTH('Loan maths'!$AP$2,0))))))/(LM_step+(LM_step=0)))+1))*((INT(((YEAR('Loan maths'!$AP$2)-YEAR(LM_first))*12+MONTH('Loan maths'!$AP$2)-MONTH(LM_first)-(DAY('Loan maths'!$AP$2)<(LM_anchor-(LM_anchor-DAY(EOMONTH('Loan maths'!$AP$2,0)))*(LM_anchor>DAY(EOMONTH('Loan maths'!$AP$2,0))))))/(LM_step+(LM_step=0)))+1)>LM_cycles))+LM_stub*('Loan maths'!$AP$2>=LN_maturity))-LM_paid)))))+SUMPRODUCT(LM_live*((LM_profile<>"EIP")*(LM_profile<>"Annuity"))*(LM_end>'Loan maths'!$AO$2)*(LM_end<='Loan maths'!$AP$2)*LN_principal) -> 0 | N78: =-D78 -> 0
B79: Total | C79: =SUM(C67:C78) -> 0 | D79: =SUM(D67:D78) -> 0
B80: The twelve months after As at, each to the same day of the next month (the calendar months when As at is a month end): term deals by maturity date; loan principal by payment date, instalments included.
B82: Activity in the period
B83: Activity | C83: Amount | D83: Deals
B84: Investments placed | C84: =SUMPRODUCT(('Deal maths'!$E$4:$E$2000>=PeriodFrom)*('Deal maths'!$E$4:$E$2000<=AsAt)*('Deal maths'!$H$4:$H$2000+('Deal maths'!$H$4:$H$2000=0)*'Deal maths'!$D$4:$D$2000)) -> 0 | D84: =SUMPRODUCT(('Deal maths'!$E$4:$E$2000>=PeriodFrom)*('Deal maths'!$E$4:$E$2000<=AsAt)*1) -> 0
B85: Investments matured | C85: =SUMPRODUCT(('Deal maths'!$F$4:$F$2000>=PeriodFrom)*('Deal maths'!$F$4:$F$2000<=AsAt)*('Deal maths'!$H$4:$H$2000+('Deal maths'!$H$4:$H$2000=0)*'Deal maths'!$D$4:$D$2000)) -> 0 | D85: =SUMPRODUCT(('Deal maths'!$F$4:$F$2000>=PeriodFrom)*('Deal maths'!$F$4:$F$2000<=AsAt)*1) -> 0
B86: Borrowing raised | C86: =SUMPRODUCT(LM_live*(LN_start>=PeriodFrom)*(LN_start<=AsAt)*((LM_profile="EIP")*(LM_out+LM_eip*LM_paid)+(LM_profile="Annuity")*((LM_rate>0)*(LM_out*(1+LM_rate)^(0-LM_paid)-LM_annuity*((1+LM_rate)^(0-LM_paid)-1)/LM_safe)+(LM_rate=0)*(LM_out-LM_annuity*(0-LM_paid)))+(LM_profile<>"EIP")*(LM_profile<>"Annuity")*LM_out))+SUMPRODUCT((LN_maturity>=PeriodFrom)*(LN_maturity<=AsAt)*(LN_start>=PeriodFrom)*(LN_start<=AsAt)*LN_principal) -> 0 | D86: =SUMPRODUCT((LN_start>=PeriodFrom)*(LN_start<=AsAt)*(LN_principal>0)*(LN_maturity>0)) -> 0
